Workbook

Sheet Cuenta Corriente
A1: Serie | C1: Bienes | D1: Servicios | E1: Ingreso primario (Renta factorial) | F1: Ingreso secundario (Transferencias corrientes) | G1: Cuenta corriente | H1: PIB | I1: Cuenta corriente (% PIB)
A2: 2021 | B2: I | C2: -2587.5206 | D2: -1100.5483 | E2: -1867.197 | F2: 2450.1726 | G2: =+C2+D2+E2+F2 -> -3105.0933 | H2: 77009.381 | I2: =+G2/H2 -> -0.040320975
B3: II | C3: -3548.1395 | D3: -1473.5711 | E3: -1652.0671 | F3: 2626.5443 | G3: -4047.2334 | H3: 73783.912 | I3: =+G3/H3 -> -0.054852519
B4: III | C4: -3692.5201 | D4: -1566.1433 | E4: -2339.0876 | F4: 2762.9165 | G4: -4834.8345 | H4: 80312.92 | I4: =+G4/H4 -> -0.060199959
B5: IV | C5: -4155.4611 | D5: -1876.7751 | E5: -2864.9072 | F5: 2934.9017 | G5: -5962.2417 | H5: 86926.558 | I5: =+G5/H5 -> -0.068589414
A6: 2022 | B6: I | C6: -3733.9745 | D6: -1223.555 | E6: -3616.8407 | F6: 3176.4942 | G6: -5397.876 | H6: 86147.8 | I6: =+G6/H6 -> -0.062658316
B7: II | C7: -1974.6221 | D7: -1071.5659 | E7: -4530.5394 | F7: 2828.69 | G7: -4748.0374 | H7: 90433.955 | I7: =+G7/H7 -> -0.052502817
B8: III | C8: -3684.4672 | D8: -731.68315 | E8: -4794.7434 | F8: 3103.6651 | G8: -6107.2287 | H8: 87864.978 | I8: =+G8/H8 -> -0.069506973
B9: IV | C9: -2785.1851 | D9: -888.15882 | E9: -4144.2065 | F9: 3192.6167 | G9: -4624.9337 | H9: 82012.922 | I9: =+G9/H9 -> -0.056392744
A10: 2023 | B10: I | C10: -1917.4467 | D10: -259.52309 | E10: -3727.0918 | F10: 3094.4084 | G10: -2809.6533 | H10: 81206.632 | I10: =+G10/H10 -> -0.034598815
B11: II | C11: -1699.2559 | D11: -357.32718 | E11: -3056.0841 | F11: 3029.1709 | G11: -2083.4963 | H11: 86433.423 | I11: =+G11/H11 -> -0.024105216
B12: III | C12: -1352.9821 | D12: -51.011979 | E12: -3507.7165 | F12: 3364.7879 | G12: -1546.9226 | H12: 99315.849 | I12: =+G12/H12 -> -0.015575788
B13: IV | C13: -1837.8732 | D13: -327.78344 | E13: -3147.8981 | F13: 3433.6791 | G13: -1879.8757 | H13: 102227.49 | I13: =+G13/H13 -> -0.018389141
A14: 2024 | B14: I | C14: -2105.2189 | D14: 323.88717 | E14: -3151.9959 | F14: 3331.0707 | G14: -1602.257 | H14: 102695.24 | I14: =+G14/H14 -> -0.015602056
B15: II | C15: -1967.1972 | D15: -392.33653 | E15: -2964.9696 | F15: 3896.7698 | G15: -1427.7335 | H15: 104491.63 | I15: =+G15/H15 -> -0.013663616
B16: III | C16: -2318.0735 | D16: -62.100235 | E16: -3342.6929 | F16: 4073.2696 | G16: -1649.5971 | H16: 106620.36 | I16: =+G16/H16 -> -0.015471689
B17: IV | C17: -2765.2803 | D17: -396.17023 | E17: -3377.3625 | F17: 4206.0449 | G17: -2332.768 | H17: 106481.51 | I17: =+G17/H17 -> -0.021907729
A18: 2025 | B18: I | C18: -3064.9152 | D18: 515.6094 | E18: -2992.8602 | F18: 3846.2214 | G18: -1695.9447 | H18: 106100.9 | I18: =+G18/H18 -> -0.015984263
B19: II | C19: -3631.8213 | D19: -196.42037 | E19: -2780.2973 | F19: 4150.9926 | G19: -2457.5464 | H19: 105316.26 | I19: =+G19/H19 -> -0.023334919
B20: III | C20: -4007.6606 | D20: -29.361023 | E20: -2993.1171 | F20: 4212.9062 | G20: -2817.2325 | H20: 119185.3 | I20: =+G20/H20 -> -0.023637415
B21: IV | C21: -4128.0567 | D21: -328.84666 | E21: -3679.6806 | F21: 4224.4138 | G21: -3912.1703 | H21: 128262.97 | I21: =+G21/H21 -> -0.030501167
A23: Promedio | C23: =+AVERAGE(C2:C21) -> -2847.8836 | D23: =+AVERAGE(D2:D21) -> -574.66925 | E23: =+AVERAGE(E2:E21) -> -3226.5678 | F23: =+AVERAGE(F2:F21) -> 3396.9868
A24: Mediana | C24: =+MEDIAN(C2:C21) -> -2775.2327 | D24: =+MEDIAN(D2:D21) -> -374.83185 | E24: =+MEDIAN(E2:E21) -> -3149.947 | F24: =+MEDIAN(F2:F21) -> 3261.8437 | I24: =+G20 -> -2817.2325
I25: =+G16 -> -1649.5971
A26: Crecimientos | I26: =+(I24/I25)-1 -> 0.70783067
A27: Serie | I27: =+I24-I25 -> -1167.6354
A28: 2022 | B28: I | C28: =+C6/C2-1 -> 0.44307045 | D28: =+D6/D2-1 -> 0.11176855 | E28: =+E6/E2-1 -> 0.93704293 | F28: =+F6/F2-1 -> 0.29643691
B29: II | C29: =+C7/C3-1 -> -0.44347674 | D29: =+D7/D3-1 -> -0.27281021 | E29: =+E7/E3-1 -> 1.7423459 | F29: =+F7/F3-1 -> 0.076962638
B30: III | C30: =+C8/C4-1 -> -0.0021808672 | D30: =+D8/D4-1 -> -0.53281214 | E30: =+E8/E4-1 -> 1.0498349 | F30: =+F8/F4-1 -> 0.12332929
B31: IV | C31: =+C9/C5-1 -> -0.32975306 | D31: =+D9/D5-1 -> -0.52676332 | E31: =+E9/E5-1 -> 0.44654126 | F31: =+F9/F5-1 -> 0.087810423
A32: 2023 | B32: I | C32: =+C10/C6-1 -> -0.48648639 | D32: =+D10/D6-1 -> -0.78789422 | E32: =+E10/E6-1 -> 0.03048272 | F32: =+F10/F6-1 -> -0.025841635
B33: II | C33: =+C11/C7-1 -> -0.13945261 | D33: =+D11/D7-1 -> -0.66653736 | E33: =+E11/E7-1 -> -0.32544808 | F33: =+F11/F7-1 -> 0.0708741
B34: III | C34: =+C12/C8-1 -> -0.63278759 | D34: =+D12/D8-1 -> -0.93028133 | E34: =+E12/E8-1 -> -0.26842456 | F34: =+F12/F8-1 -> 0.084133706
B35: IV | C35: =+C13/C9-1 -> -0.34012529 | D35: =+D13/D9-1 -> -0.63094051 | E35: =+E13/E9-1 -> -0.24040992 | F35: =+F13/F9-1 -> 0.075506224
A36: 2024 | B36: I | C36: =+C14/C10-1 -> 0.097928213 | D36: =+D14/D10-1 -> -2.2480091 | E36: =+E14/E10-1 -> -0.15430151 | F36: =+F14/F10-1 -> 0.076480621
B37: II | C37: =+C15/C11-1 -> 0.15768151 | D37: =+D15/D11-1 -> 0.09797559 | E37: =+E15/E11-1 -> -0.02981411 | F37: =+F15/F11-1 -> 0.28641464
B38: III | C38: =+C16/C12-1 -> 0.71330692 | D38: =+D16/D12-1 -> 0.21736574 | E38: =+E16/E12-1 -> -0.047045874 | F38: =+F16/F12-1 -> 0.21055762
B39: IV | C39: =+C17/C13-1 -> 0.50460883 | D39: =+D17/D13-1 -> 0.20863407 | E39: =+E17/E13-1 -> 0.072894464 | F39: =+F17/F13-1 -> 0.22493827
A40: 2025 | B40: I | C40: =+C18/C14-1 -> 0.45586536 | D40: =+D18/D14-1 -> 0.59194139 | E40: =+E18/E14-1 -> -0.050487278 | F40: =+F18/F14-1 -> 0.15465019
B41: II | C41: =+C19/C15-1 -> 0.84619081 | D41: =+D19/D15-1 -> -0.49935742 | E41: =+E19/E15-1 -> -0.062284724 | F41: =+F19/F15-1 -> 0.065239375
B42: III | C42: =+C20/C16-1 -> 0.72887551 | D42: =+D20/D16-1 -> -0.52719949 | E42: =+E20/E16-1 -> -0.10457911 | F42: =+F20/F16-1 -> 0.034281197
B43: IV | C43: =+C21/C17-1 -> 0.49281674 | D43: =+D21/D17-1 -> -0.16993597 | E43: =+E21/E17-1 -> 0.089513099 | F43: =+F21/F17-1 -> 0.0043672432

Sheet PIB
A1: Fecha (dd/mm/aaaa) | B1: año | C1: Trimestre | D1: Promedio mensual | F1: año | G1: Trimestre | H1: Promedio trimestral | J1: Fecha (dd/mm/aaaa) | K1: Producto interno bruto Valor (Miles de millones COP) | M1: año | N1: Trimestre | O1: Producto interno bruto Valor (Miles de millones USD)
A2: 43861 | B2: =YEAR(A2) -> 2020 | C2: =INT((MONTH(A2)-1)/3)+1 -> 1 | D2: 3317.37 | F2: 2021 | G2: 1 | H2: =AVERAGEIFS(D:D, B:B, F2, C:C, G2) -> 3554.6533 | J2: 43921 | K2: 266805.95 | M2: 2021 | N2: 1 | O2: =+K6/Tabla5[[#This Row],[Promedio trimestral]]*1000 -> 77009.381
A3: 43890 | B3: =YEAR(A3) -> 2020 | C3: =INT((MONTH(A3)-1)/3)+1 -> 1 | D3: 3408.24 | F3: 2021 | G3: 2 | H3: =AVERAGEIFS(D:D, B:B, F3, C:C, G3) -> 3695.6033 | J3: 44012 | K3: 219874.33 | M3: 2021 | N3: 2 | O3: =+K7/Tabla5[[#This Row],[Promedio trimestral]]*1000 -> 73783.912
A4: 43921 | B4: =YEAR(A4) -> 2020 | C4: =INT((MONTH(A4)-1)/3)+1 -> 1 | D4: 3870.01 | F4: 2021 | G4: 3 | H4: =AVERAGEIFS(D:D, B:B, F4, C:C, G4) -> 3846.7333 | J4: 44104 | K4: 245852.69 | M4: 2021 | N4: 3 | O4: =+K8/Tabla5[[#This Row],[Promedio trimestral]]*1000 -> 80312.92
A5: 43951 | B5: =YEAR(A5) -> 2020 | C5: =INT((MONTH(A5)-1)/3)+1 -> 2 | D5: 3986.56 | F5: 2021 | G5: 4 | H5: =AVERAGEIFS(D:D, B:B, F5, C:C, G5) -> 3879.9867 | J5: 44196 | K5: 265938.03 | M5: 2021 | N5: 4 | O5: =+K9/Tabla5[[#This Row],[Promedio trimestral]]*1000 -> 86926.558
A6: 43982 | B6: =YEAR(A6) -> 2020 | C6: =INT((MONTH(A6)-1)/3)+1 -> 2 | D6: 3863.34 | F6: 2022 | G6: 1 | H6: =AVERAGEIFS(D:D, B:B, F6, C:C, G6) -> 3914.8667 | J6: 44286 | K6: 273741.65 | M6: 2022 | N6: 1 | O6: =+K10/Tabla5[[#This Row],[Promedio trimestral]]*1000 -> 86147.8
A7: 44012 | B7: =YEAR(A7) -> 2020 | C7: =INT((MONTH(A7)-1)/3)+1 -> 2 | D7: 3693 | F7: 2022 | G7: 2 | H7: =AVERAGEIFS(D:D, B:B, F7, C:C, G7) -> 3915.4967 | J7: 44377 | K7: 272676.07 | M7: 2022 | N7: 2 | O7: =+K11/Tabla5[[#This Row],[Promedio trimestral]]*1000 -> 90433.955
A8: 44043 | B8: =YEAR(A8) -> 2020 | C8: =INT((MONTH(A8)-1)/3)+1 -> 3 | D8: 3660.6 | F8: 2022 | G8: 3 | H8: =AVERAGEIFS(D:D, B:B, F8, C:C, G8) -> 4386.03 | J8: 44469 | K8: 308942.39 | M8: 2022 | N8: 3 | O8: =+K12/Tabla5[[#This Row],[Promedio trimestral]]*1000 -> 87864.978
A9: 44074 | B9: =YEAR(A9) -> 2020 | C9: =INT((MONTH(A9)-1)/3)+1 -> 3 | D9: 3788.1 | F9: 2022 | G9: 4 | H9: =AVERAGEIFS(D:D, B:B, F9, C:C, G9) -> 4808.3833 | J9: 44561 | K9: 337273.89 | M9: 2022 | N9: 4 | O9: =+K13/Tabla5[[#This Row],[Promedio trimestral]]*1000 -> 82012.922
A10: 44104 | B10: =YEAR(A10) -> 2020 | C10: =INT((MONTH(A10)-1)/3)+1 -> 3 | D10: 3749.86 | F10: 2023 | G10: 1 | H10: =AVERAGEIFS(D:D, B:B, F10, C:C, G10) -> 4758.63 | J10: 44651 | K10: 337257.15 | M10: 2023 | N10: 1 | O10: =+K14/Tabla5[[#This Row],[Promedio trimestral]]*1000 -> 81206.632
A11: 44135 | B11: =YEAR(A11) -> 2020 | C11: =INT((MONTH(A11)-1)/3)+1 -> 4 | D11: 3833.06 | F11: 2023 | G11: 2 | H11: =AVERAGEIFS(D:D, B:B, F11, C:C, G11) -> 4426.3667 | J11: 44742 | K11: 354093.85 | M11: 2023 | N11: 2 | O11: =+K15/Tabla5[[#This Row],[Promedio trimestral]]*1000 -> 86433.423
A12: 44165 | B12: =YEAR(A12) -> 2020 | C12: =INT((MONTH(A12)-1)/3)+1 -> 4 | D12: 3680.67 | F12: 2023 | G12: 3 | H12: =AVERAGEIFS(D:D, B:B, F12, C:C, G12) -> 4047.6367 | J12: 44834 | K12: 385378.43 | M12: 2023 | N12: 3 | O12: =+K16/Tabla5[[#This Row],[Promedio trimestral]]*1000 -> 99315.849
A13: 44196 | B13: =YEAR(A13) -> 2020 | C13: =INT((MONTH(A13)-1)/3)+1 -> 4 | D13: 3468.5 | F13: 2023 | G13: 4 | H13: =AVERAGEIFS(D:D, B:B, F13, C:C, G13) -> 4071.1867 | J13: 44926 | K13: 394349.57 | M13: 2023 | N13: 4 | O13: =+K17/Tabla5[[#This Row],[Promedio trimestral]]*1000 -> 102227.49
... A21: 44439 | B21: =YEAR(A21) -> 2021 | C21: =INT((MONTH(A21)-1)/3)+1 -> 3 | D21: 3887.68 | F21: 2025 | G21: 4 | H21: =AVERAGEIFS(D:D, B:B, F21, C:C, G21) -> 3818.9033 | J21: 45657 | K21: 463374.87 | M21: 2025 | N21: 4 | O21: =+K25/Tabla5[[#This Row],[Promedio trimestral]]*1000 -> 128262.97
A22: 44469 | B22: =YEAR(A22) -> 2021 | C22: =INT((MONTH(A22)-1)/3)+1 -> 3 | D22: 3820.28 | F22: 2026 | G22: 1 | H22: =AVERAGEIFS(D:D, B:B, F22, C:C, G22) -> 3695.9233 | J22: 45747 | K22: 444412.11
A23: 44500 | B23: =YEAR(A23) -> 2021 | C23: =INT((MONTH(A23)-1)/3)+1 -> 4 | D23: 3771.68 | J23: 45838 | K23: 442049.55
A24: 44530 | B24: =YEAR(A24) -> 2021 | C24: =INT((MONTH(A24)-1)/3)+1 -> 4 | D24: 3900.51 | J24: 45930 | K24: 477659.73
A25: 44561 | B25: =YEAR(A25) -> 2021 | C25: =INT((MONTH(A25)-1)/3)+1 -> 4 | D25: 3967.77 | J25: 46022 | K25: 489823.88
A26: 44592 | B26: =YEAR(A26) -> 2022 | C26: =INT((MONTH(A26)-1)/3)+1 -> 1 | D26: 4000.72
A27: 44620 | B27: =YEAR(A27) -> 2022 | C27: =INT((MONTH(A27)-1)/3)+1 -> 1 | D27: 3938.36
A28: 44651 | B28: =YEAR(A28) -> 2022 | C28: =INT((MONTH(A28)-1)/3)+1 -> 1 | D28: 3805.52
A29: 44681 | B29: =YEAR(A29) -> 2022 | C29: =INT((MONTH(A29)-1)/3)+1 -> 2 | D29: 3796.39 | K29: 279339 | M29: 279339 | N29: 273741.65 | O29: 273741.65
A30: 44712 | B30: =YEAR(A30) -> 2022 | C30: =INT((MONTH(A30)-1)/3)+1 -> 2 | D30: 4027.6 | K30: 281883.7 | M30: 281883.7 | N30: 272676.07 | O30: 272676.07
A31: 44742 | B31: =YEAR(A31) -> 2022 | C31: =INT((MONTH(A31)-1)/3)+1 -> 2 | D31: 3922.5 | K31: 305608.79 | M31: 305608.79 | N31: 308942.39 | O31: 308942.39
A32: 44773 | B32: =YEAR(A32) -> 2022 | C32: =INT((MONTH(A32)-1)/3)+1 -> 3 | D32: 4394.01 | K32: 325802.51 | M32: 325802.51 | N32: 337273.89 | O32: 337273.89
A33: 44804 | B33: =YEAR(A33) -> 2022 | C33: =INT((MONTH(A33)-1)/3)+1 -> 3 | D33: 4326.77 | K33: 343812.22 | M33: 343812.22 | N33: 337257.15 | O33: 337257.15
A34: 44834 | B34: =YEAR(A34) -> 2022 | C34: =INT((MONTH(A34)-1)/3)+1 -> 3 | D34: 4437.31 | K34: 365869.86 | M34: 365869.86 | N34: 354093.85 | O34: 354093.85
A35: 44865 | B35: =YEAR(A35) -> 2022 | C35: =INT((MONTH(A35)-1)/3)+1 -> 4 | D35: 4714.96 | K35: 380784.65 | M35: 380784.65 | N35: 385378.43 | O35: 385378.43
A36: 44895 | B36: =YEAR(A36) -> 2022 | C36: =INT((MONTH(A36)-1)/3)+1 -> 4 | D36: 4922.3 | K36: 380612.27 | M36: 380612.27 | N36: 394349.57 | O36: 394349.57
A37: 44926 | B37: =YEAR(A37) -> 2022 | C37: =INT((MONTH(A37)-1)/3)+1 -> 4 | D37: 4787.89 | K37: 393577.25 | M37: 393577.25 | N37: 386432.32 | O37: 386432.32
A38: 44957 | B38: =YEAR(A38) -> 2023 | C38: =INT((MONTH(A38)-1)/3)+1 -> 1 | D38: 4712.18 | K38: 395046.8 | M38: 395046.8 | N38: 382586.02 | O38: 382586.02
A39: 44985 | B39: =YEAR(A39) -> 2023 | C39: =INT((MONTH(A39)-1)/3)+1 -> 1 | D39: 4802.75 | K39: 396686.48 | M39: 396686.48 | N39: 401994.47 | O39: 401994.47
A40: 45016 | B40: =YEAR(A40) -> 2023 | C40: =INT((MONTH(A40)-1)/3)+1 -> 1 | D40: 4760.96 | K40: 401889.47 | M40: 401889.47 | N40: 416187.19 | O40: 416187.19
... A48: 45260 | B48: =YEAR(A48) -> 2023 | C48: =INT((MONTH(A48)-1)/3)+1 -> 4 | D48: 4040.26 | K48: 473028.86 | M48: 473028.86 | N48: 489823.88 | O48: 489823.88
A49: 45291 | B49: =YEAR(A49) -> 2023 | C49: =INT((MONTH(A49)-1)/3)+1 -> 4 | D49: 3954.14
A50: 45322 | B50: =YEAR(A50) -> 2024 | C50: =INT((MONTH(A50)-1)/3)+1 -> 1 | D50: 3920.2
A51: 45351 | B51: =YEAR(A51) -> 2024 | C51: =INT((MONTH(A51)-1)/3)+1 -> 1 | D51: 3931.85
A52: 45382 | B52: =YEAR(A52) -> 2024 | C52: =INT((MONTH(A52)-1)/3)+1 -> 1 | D52: 3908.67
A53: 45412 | B53: =YEAR(A53) -> 2024 | C53: =INT((MONTH(A53)-1)/3)+1 -> 2 | D53: 3866.12
A54: 45443 | B54: =YEAR(A54) -> 2024 | C54: =INT((MONTH(A54)-1)/3)+1 -> 2 | D54: 3865.09
A55: 45473 | B55: =YEAR(A55) -> 2024 | C55: =INT((MONTH(A55)-1)/3)+1 -> 2 | D55: 4054.56
A56: 45504 | B56: =YEAR(A56) -> 2024 | C56: =INT((MONTH(A56)-1)/3)+1 -> 3 | D56: 4036.8
A57: 45535 | B57: =YEAR(A57) -> 2024 | C57: =INT((MONTH(A57)-1)/3)+1 -> 3 | D57: 4062.98
A58: 45565 | B58: =YEAR(A58) -> 2024 | C58: =INT((MONTH(A58)-1)/3)+1 -> 3 | D58: 4191.86
A59: 45596 | B59: =YEAR(A59) -> 2024 | C59: =INT((MONTH(A59)-1)/3)+1 -> 4 | D59: 4257.76
A60: 45626 | B60: =YEAR(A60) -> 2024 | C60: =INT((MONTH(A60)-1)/3)+1 -> 4 | D60: 4411.12
... A76: 46112 | B76: =YEAR(A76) -> 2026 | C76: =INT((MONTH(A76)-1)/3)+1 -> 1 | D76: 3717.31

Sheet Cuenta Financiera 
A1: Serie | C1: Inversión Directa | D1: Inversión de Cartera | E1: Derivados Financieros | F1: Otra Inversión | G1: Activos de Reserva | H1: Cuenta Financiera | I1: PIB | J1: Cuenta Financiera (% PIB)
A2: 2021 | B2: I | C2: -1438.1448 | D2: 1318.8281 | E2: -320.8628 | F2: -2538.9623 | G2: 190.12769 | H2: -2789.0142 | I2: 77009.381 | J2: =+H2/I2 -> -0.036216551
B3: II | C3: -1012.6176 | D3: -6089.3847 | E3: 181.65367 | F3: 2985.7917 | G3: 173.98878 | H3: -3760.5681 | I3: 73783.912 | J3: =+H3/I3 -> -0.050967318
B4: III | C4: -2527.8876 | D4: 850.56586 | E4: 356.06059 | F4: -3336.9983 | G4: 154.45625 | H4: -4503.8032 | I4: 80312.92 | J4: =+H4/I4 -> -0.05607819
B5: IV | C5: -1401.8715 | D5: -675.38217 | E5: 148.30763 | F5: -3845.7681 | G5: 134.97245 | H5: -5639.7417 | I5: 86926.558 | J5: =+H5/I5 -> -0.064879386
A6: 2022 | B6: I | C6: -3650.5735 | D6: 1865.9168 | E6: -377.13608 | F6: -3001.8772 | G6: 126.94617 | H6: -5036.7239 | I6: 86147.8 | J6: =+H6/I6 -> -0.058466076
B7: II | C7: -3660.5871 | D7: -759.03032 | E7: 36.169823 | F7: -642.40142 | G7: 74.078561 | H7: -4951.7705 | I7: 90433.955 | J7: =+H7/I7 -> -0.054755655
B8: III | C8: -2958.9114 | D8: -233.03539 | E8: 487.33717 | F8: -3190.5331 | G8: 159.38366 | H8: -5735.759 | I8: 87864.978 | J8: =+H8/I8 -> -0.06527924
B9: IV | C9: -3528.6486 | D9: -446.84973 | E9: 676.96965 | F9: -1653.3629 | G9: 210.4825 | H9: -4741.4091 | I9: 82012.922 | J9: =+H9/I9 -> -0.057812951
A10: 2023 | B10: I | C10: -3600.4136 | D10: 1111.281 | E10: -248.37005 | F10: -218.92539 | G10: 365.72012 | H10: -2590.708 | I10: 81206.632 | J10: =+H10/I10 -> -0.031902665
B11: II | C11: -5441.7419 | D11: 1519.8079 | E11: -756.289 | F11: 1579.9865 | G11: 399.08936 | H11: -2699.1472 | I11: 86433.423 | J11: =+H11/I11 -> -0.031228049
B12: III | C12: -3334.7106 | D12: 4527.3295 | E12: -690.52363 | F12: -2335.7995 | G12: 457.47195 | H12: -1376.2322 | I12: 99315.849 | J12: =+H12/I12 -> -0.013857126
B13: IV | C13: -3148.0399 | D13: 1504.3073 | E13: -879.40545 | F13: 844.61255 | G13: 496.10653 | H13: -1182.4189 | I13: 102227.49 | J13: =+H13/I13 -> -0.011566546
A14: 2024 | B14: I | C14: -2407.8679 | D14: 1415.8371 | E14: -575.17205 | F14: -869.8318 | G14: 951.37463 | H14: -1485.66 | I14: 102695.24 | J14: =+H14/I14 -> -0.014466687
B15: II | C15: -1646.381 | D15: -451.25025 | E15: 80.169823 | F15: 23.453203 | G15: 914.45395 | H15: -1079.5542 | I15: 104491.63 | J15: =+H15/I15 -> -0.01033149
B16: III | C16: -2455.6267 | D16: 3489.4302 | E16: 281.66982 | F16: -3385.3811 | G16: 1045.5225 | H16: -1024.3852 | I16: 106620.36 | J16: =+H16/I16 -> -0.0096077822
B17: IV | C17: -2662.2075 | D17: -2182.4411 | E17: 156.66982 | F17: 2018.3096 | G17: 681.96286 | H17: -1987.7062 | I17: 106481.51 | J17: =+H17/I17 -> -0.018667149
A18: 2025 | B18: I | C18: -2127.9738 | D18: 2941.0469 | E18: -422.28289 | F18: -2429.2437 | G18: 563.57735 | H18: -1474.8761 | I18: 106100.9 | J18: =+H18/I18 -> -0.013900693
B19: II | C19: -1561.2484 | D19: -3760.1065 | E19: -448.3182 | F19: 3394.6394 | G19: 524.5847 | H19: -1850.4489 | I19: 105316.26 | J19: =+H19/I19 -> -0.017570401
B20: III | C20: -1858.9646 | D20: -4963.3956 | E20: -398.30489 | F20: 4435.3334 | G20: 534.1645 | H20: -2251.1671 | I20: 119185.3 | J20: =+H20/I20 -> -0.018887959
B21: IV | C21: -1761.7596 | D21: -1697.9149 | E21: -438.52609 | F21: -115.63938 | G21: 542.91345 | H21: -3470.9265 | I21: 128262.97 | J21: =+H21/I21 -> -0.027061018
A24: Promedio | C24: =AVERAGE(C2:C21) -> -2609.3089 | D24: =AVERAGE(D2:D21) -> -35.721994 | E24: =AVERAGE(E2:E21) -> -157.50916 | F24: =AVERAGE(F2:F21) -> -614.12989 | G24: =AVERAGE(G2:G21) -> 435.0689 | H24: =AVERAGE(H2:H21) -> -2981.601
A25: Mediana | C25: =MEDIAN(C2:C21) -> -2491.7571 | D25: =MEDIAN(D2:D21) -> 308.76524 | E25: =MEDIAN(E2:E21) -> -284.61643 | F25: =MEDIAN(F2:F21) -> -756.11661 | G25: =MEDIAN(G2:G21) -> 428.28065 | H25: =MEDIAN(H2:H21) -> -2644.9276
A27: Crecimientos
A28: Serie
A29: 2022 | B29: I | C29: =(C6/C2)-1 -> 1.5383908 | D29: =(D6/D2)-1 -> 0.41482947 | E29: =(E6/E2)-1 -> 0.17538112 | F29: =(F6/F2)-1 -> 0.18232444
B30: II | C30: =(C7/C3)-1 -> 2.6149748 | D30: =(D7/D3)-1 -> -0.87535189 | E30: =(E7/E3)-1 -> -0.80088581 | F30: =(F7/F3)-1 -> -1.2151528
B31: III | C31: =(C8/C4)-1 -> 0.17050749 | D31: =(D8/D4)-1 -> -1.2739769 | E31: =(E8/E4)-1 -> 0.36869171 | F31: =(F8/F4)-1 -> -0.043891292
B32: IV | C32: =(C9/C5)-1 -> 1.5170984 | D32: =(D9/D5)-1 -> -0.33837501 | E32: =(E9/E5)-1 -> 3.5646312 | F32: =(F9/F5)-1 -> -0.57008254
A33: 2023 | B33: I | C33: =(C10/C6)-1 -> -0.013740278 | D33: =(D10/D6)-1 -> -0.40443167 | E33: =(E10/E6)-1 -> -0.3414312 | F33: =(F10/F6)-1 -> -0.9270705
B34: II | C34: =(C11/C7)-1 -> 0.48657627 | D34: =(D11/D7)-1 -> -3.0023019 | E34: =(E11/E7)-1 -> -21.909392 | F34: =(F11/F7)-1 -> -3.4595003
B35: III | C35: =(C12/C8)-1 -> 0.12700591 | D35: =(D12/D8)-1 -> -20.427648 | E35: =(E12/E8)-1 -> -2.416932 | F35: =(F12/F8)-1 -> -0.26789682
B36: IV | C36: =(C13/C9)-1 -> -0.10786247 | D36: =(D13/D9)-1 -> -4.3664726 | E36: =(E13/E9)-1 -> -2.2990323 | F36: =(F13/F9)-1 -> -1.5108452
A37: 2024 | B37: I | C37: =(C14/C10)-1 -> -0.33122465 | D37: =(D14/D10)-1 -> 0.27405866 | E37: =(E14/E10)-1 -> 1.3157866 | F37: =(F14/F10)-1 -> 2.9731883
B38: II | C38: =(C15/C11)-1 -> -0.69745332 | D38: =(D15/D11)-1 -> -1.2969127 | E38: =(E15/E11)-1 -> -1.1060042 | F38: =(F15/F11)-1 -> -0.98515607
B39: III | C39: =(C16/C12)-1 -> -0.26361625 | D39: =(D16/D12)-1 -> -0.22925198 | E39: =(E16/E12)-1 -> -1.4079076 | F39: =(F16/F12)-1 -> 0.44934579
B40: IV | C40: =(C17/C13)-1 -> -0.15432855 | D40: =(D17/D13)-1 -> -2.4507947 | E40: =(E17/E13)-1 -> -1.1781543 | F40: =(F17/F13)-1 -> 1.3896278
A41: 2025 | B41: I | C41: =(C18/C14)-1 -> -0.11624148 | D41: =(D18/D14)-1 -> 1.0772495 | E41: =(E18/E14)-1 -> -0.26581465 | F41: =(F18/F14)-1 -> 1.7927741
B42: II | C42: =(C19/C15)-1 -> -0.051708908 | D42: =(D19/D15)-1 -> 7.3326413 | E42: =(E19/E15)-1 -> -6.5921066 | F42: =(F19/F15)-1 -> 143.74098

Sheet Participación Exportaciones
D1: 1 | E1: 2 | F1: 3 | G1: 4 | H1: 5 | I1: 6 | J1: 7 | K1: 8 | L1: 9 | M1: 10 | N1: 11 | O1: 12 | P1: 13 | Q1: 14 | R1: 15 | S1: 16 | T1: 17 | U1: 18 | V1: 19 | W1: 20 | X1: 21 | Y1: 22 | Z1: 23 | AA1: 24 | AB1: 25 | AC1: 26 | AD1: 27 | AE1: 28 | AF1: 29 | AG1: 30 | AH1: 31 | AI1: 32 | AJ1: 33 | AK1: 34 | AL1: 35 | AM1: 36 | AN1: 37 | AO1: 38 | AP1: 39 | AQ1: 40 | AR1: 41 | AS1: 42 | AT1: 43 | AU1: 44 | AV1: 45 | AW1: 46 | AX1: 47 | AY1: 48 | AZ1: 49 | BA1: 50 | BB1: 51 | BC1: 52 | BD1: 53 | BE1: 54 | BF1: 55 | BG1: 56 | BH1: 57 | BI1: 58 | BJ1: 59 | BK1: 60 | BL1: 61 | BM1: 62 | BN1: 63 | BO1: 64 | BP1: 65 | BQ1: 66 | BR1: 67 | BS1: 68 | BT1: 69 | BU1: 70 | BV1: 71 | BW1: 72 | BX1: 73 | BY1: 74 | BZ1: 75 | CA1: 76 | CB1: 78 | CC1: 79 | CD1: 80 | CE1: 81 | CF1: 82 | CG1: 83 | CH1: 84 | CI1: 85 | CJ1: 86 | CK1: 87 | CL1: 88 | CM1: 89 | CN1: 90 | CO1: 91 | CP1: 92 | CQ1: 93 | CR1: 94 | CS1: 95 | CT1: 96 | CU1: 97 | CV1: 98 | CW1: Total exportaciones
D2: Animales vivos | E2: Carnes y despojos comestibles | F2: Pescados y crustáceos, moluscos e invertebrados acuáticos | G2: Leche y productos lácteos, huevos, miel | H2: Demás productos de origen animal | I2: Plantas vivas y productos de la floricultura | J2: Legumbres y hortalizas, plantas, raíces y tubérculos | K2: Frutos comestibles, cortezas de agrios o melones | L2: Café, té, yerba mate y especias | M2: Cereales | N2: Productos de molinería, malta, almidón y fécula | O2: Semillas y frutos oleaginosos, forrajes | P2: Gomas, resinas, y demás jugos y extractos vegetales | Q2: Materias trenzables y demás productos vegetales | R2: Grasas y aceites animales o vegetales | S2: Preparaciones de carne, pescado, crustáceos, moluscos | T2: Azúcares y artículos confitería | U2: Cacao y sus preparaciones | V2: Preparaciones a base de cereal, harina, leche; pastelería | W2: Preparaciones de legumbres u hortalizas, frutos, otras | X2: Preparaciones alimenticias diversas | Y2: Bebidas, líquidos alcohólicos y vinagre | Z2: Residuos industrias alimentarias. Alimentos para animales | AA2: Tabaco, sucedáneos del tabaco elaborados | AB2: Sal; azufre; tierras y piedras; yesos, cales y cementos | AC2: Minerales, escorias y cenizas | AD2: Combustibles y aceites minerales y sus productos | AE2: Productos químicos inorgánicos | AF2: Productos químicos orgánicos | AG2: Productos farmacéuticos | AH2: Abonos | AI2: Extractos curtientes, pinturas, tintas | AJ2: Aceites esenciales, perfumería, cosméticos | AK2: Jabones, ceras artificiales, pastas | AL2: Materias albuminoideas, colas | AM2: Pólvoras, explosivos, fósforos | AN2: Productos fotográficos, cinematográficos | AO2: Productos diversos de las industrias químicas | AP2: Materias plásticas y manufacturas | AQ2: Caucho y manufacturas | AR2: Pieles y cueros | AS2: Manufacturas de cuero, artículos de viaje, bolsos | AT2: Peletería y confecciones | AU2: Madera, carbón vegetal y manufacturas de madera | AV2: Corcho y sus manufacturas | AW2: Manufactura de espartería y cestería | AX2: Pastas de madera, desperdicios de papel o cartón | AY2: Papel, cartón y sus manufacturas | AZ2: Productos editoriales, prensa, textos | BA2: Seda | BB2: Lana y pelo fino u ordinario; hilados y tejidos de crin | BC2: Algodón | BD2: Demás fibras vegetales, hilados de papel | BE2: Filamentos sintéticos o artificiales | BF2: Fibras sintéticas o artificiales discontinuas | BG2: Guata, fieltro y telas sin tejer; cordeles ,cuerdas, cordajes | BH2: Alfombras y materias textiles | BI2: Tejidos especiales, superficies textiles con pelo | BJ2: Tejidos impregnados, recubiertos | BK2: Tejidos de punto | BL2: Prendas y complementos de vestir, de punto | BM2: Prendas y complementos de vestir, excepto de punto | BN2: Demás artículos textiles confeccionados | BO2: Calzado, botines, artículos análogos y partes | BP2: Artículos de sombrerería y partes | BQ2: Paraguas, bastones, látigos y sus partes | BR2: Plumas, flores artificiales; manufactura de cabellos | BS2: Manufacturas de piedra, yeso, cemento, mica y análogas | BT2: Productos cerámicos | BU2: Vidrio y manufacturas | BV2: Perlas finas, piedras y metales preciosos | BW2: Fundición, hierro y acero | BX2: Manufactura de fundición, de hierro o acero | BY2: Cobre y sus manufacturas | BZ2: Níquel y sus manufacturas | CA2: Aluminio y sus manufacturas | CB2: Plomo y manufacturas | CC2: Zinc y manufacturas | CD2: Estaño y manufacturas | CE2: Demás metales comunes, "cermets" y manufacturas | CF2: Herramientas y útiles, cuchillería y cubiertos | CG2: Manufacturas diversas de metales comunes | CH2: Reactores nucleares, calderas, máquinas y partes | CI2: Aparatos y material eléctrico, de grabación o imagen | CJ2: Vehículos y material para vía férrea, aparatos de señalización | CK2: Vehículos automóviles, tractores, ciclos, partes y accesorios | CL2: Navegación aérea o espacial | CM2: Navegación marítima o fluvial | CN2: Instrumentos y aparatos de óptica, fotografía, cinematografía | CO2: Relojería | CP2: Instrumentos de música, partes y accesorios | CQ2: Armas y municiones, sus partes y accesorios | CR2: Muebles | CS2: Juguetes, artículos para recreo, deporte; partes y accesorios | CT2: Manufacturas diversas | CU2: Objetos de arte, de colección o de antigüedad | CV2: Disposiciones de tratamiento especial
A3: 2020 | B3: =ROUNDUP(MONTH($B3)/3, 0) -> 1 | C3: 43831 | D3: 6122.9003 | E3: 7236.148 | F3: 11585.546 | G3: 680.37512 | H3: 2954.1104 | I3: 98100.147 | J3: 2331.0486 | K3: 143866.28 | L3: 249836.31 | M3: 964.12477 | N3: 2633.421 | O3: 3537.8468 | P3: 1298.8281 | Q3: 18.5356 | R3: 38748.95 | S3: 2188.4464 | T3: 40663.19 | U3: 8592.5171 | V3: 10371.43 | W3: 7294.9357 | X3: 26189.791 | Y3: 3066.0825 | Z3: 2913.4527 | AA3: 939.43288 | AB3: 1114.8014 | AC3: 13152.438 | AD3: 2043776.8 | AE3: 8156.1252 | AF3: 6790.1305 | AG3: 29049.362 | AH3: 2803.1585 | AI3: 7080.6298 | AJ3: 34016.233 | AK3: 11667.095 | AL3: 4931.6327 | AM3: 46.9025 | AN3: 6.66746 | AO3: 32286.053 | AP3: 100590.09 | AQ3: 8135.9011 | AR3: 1970.6104 | AS3: 3227.3267 | AT3: 401.41898 | AU3: 3888.593 | AV3: 12.31539 | AW3: 31.44041 | AX3: 11.48123 | AY3: 17665.058 | AZ3: 2995.6465 | BA3: 0 | BB3: 0 | BC3: 1383.4871 | BD3: 64.64511 | BE3: 3481.7337 | BF3: 636.4096 | BG3: 468.10363 | BH3: 29.35186 | BI3: 818.93093 | BJ3: 2272.6412 | BK3: 3957.574 | BL3: 12350.538 | BM3: 14497.092 | BN3: 4885.2416 | BO3: 1618.684 | BP3: 217.94904 | BQ3: 14.96882 | BR3: 0.08604 | BS3: 3592.5515 | BT3: 6114.6121 | BU3: 14219.861 | BV3: 116520.24 | BW3: 43551.952 | BX3: 20879.461 | BY3: 15277.688 | BZ3: 16.75106 | CA3: 20060.531 | CB3: 677.09234 | CC3: 24.70053 | CD3: 8.66622 | CE3: 117.58025 | CF3: 3260.5309 | CG3: 1947.4418 | CH3: 28480.795 | CI3: 34736.171 | CJ3: 26.724 | CK3: 28659.644 | CL3: 1386.4291 | CM3: 29.292 | CN3: 6846.3876 | CO3: 78.97624 | CP3: 0.15017 | CQ3: 52.35165 | CR3: 8875.4384 | CS3: 1672.9645 | CT3: 8823.2392 | CU3: 266.02392 | CV3: 622.23346 | CW3: 3419465.6 | CX3: 3419465.6
A4: 2020 | B4: =ROUNDUP(MONTH($B4)/3, 0) -> 1 | C4: 43862 | D4: 7431.8957 | E4: 9251.6271 | F4: 9498.1699 | G4: 796.68879 | H4: 2423.1888 | I4: 180000.25 | J4: 1953.9865 | K4: 101524.52 | L4: 215605.59 | M4: 15.68003 | N4: 6125.2962 | O4: 2455.8284 | P4: 31.67113 | Q4: 32.58348 | R4: 42627.233 | S4: 1135.9352 | T4: 35424.314 | U4: 8577.5093 | V4: 11517.871 | W4: 9077.7886 | X4: 25901.521 | Y4: 1550.9687 | Z4: 2649.9762 | AA4: 1858.3649 | AB4: 1431.9641 | AC4: 1682.495 | AD4: 1483145.6 | AE4: 7681.4076 | AF4: 6486.9171 | AG4: 23261.158 | AH4: 2773.3533 | AI4: 6845.4544 | AJ4: 38373.277 | AK4: 12773.048 | AL4: 3401.0881 | AM4: 0 | AN4: 31.15843 | AO4: 33745.061 | AP4: 116884.19 | AQ4: 7590.4103 | AR4: 3810.38 | AS4: 4333.2467 | AT4: 542.10329 | AU4: 4564.3174 | AV4: 1.9762 | AW4: 50.05919 | AX4: 153.56825 | AY4: 19458.613 | AZ4: 3605.4033 | BA4: 0 | BB4: 0 | BC4: 1132.0142 | BD4: 123.12639 | BE4: 4088.8184 | BF4: 785.10321 | BG4: 500.05634 | BH4: 36.19873 | BI4: 1255.6574 | BJ4: 2925.2557 | BK4: 4090.1692 | BL4: 13397.588 | BM4: 21135.42 | BN4: 8245.1037 | BO4: 2158.0515 | BP4: 460.4772 | BQ4: 167.35914 | BR4: 10.039 | BS4: 3476.2636 | BT4: 5146.6372 | BU4: 9790.6223 | BV4: 191257.56 | BW4: 4711.4294 | BX4: 12461.115 | BY4: 14635.269 | BZ4: 63.96277 | CA4: 24250.607 | CB4: 742.3143 | CC4: 56.49317 | CD4: 12.56253 | CE4: 124.89492 | CF4: 3852.4969 | CG4: 1876.0374 | CH4: 34905.922 | CI4: 43112.747 | CJ4: 27.761 | CK4: 37511.541 | CL4: 1238.4834 | CM4: 122.72347 | CN4: 8400.3097 | CO4: 52.76473 | CP4: 129.83285 | CQ4: 685.89422 | CR4: 11079.723 | CS4: 1331.0455 | CT4: 10428.054 | CU4: 979.719 | CV4: 555.87673 | CW4: 2943625.8 | CX4: 2943625.8
A5: 2020 | B5: =ROUNDUP(MONTH($B5)/3, 0) -> 1 | C5: 43891 | D5: 18809.798 | E5: 9672.7281 | F5: 5698.4683 | G5: 842.78521 | H5: 3408.1068 | I5: 154802.75 | J5: 2702.951 | K5: 99170.293 | L5: 170321.53 | M5: 791.77326 | N5: 4971.5231 | O5: 2865.5421 | P5: 65.7425 | Q5: 40.60808 | R5: 51135.688 | S5: 1633.2407 | T5: 43779.437 | U5: 10806.655 | V5: 11366.99 | W5: 8291.3173 | X5: 28675.154 | Y5: 1786.1461 | Z5: 3114.1836 | AA5: 939.73532 | AB5: 1390.0653 | AC5: 2568.1071 | AD5: 950857.23 | AE5: 7399.9066 | AF5: 10273.921 | AG5: 25861.58 | AH5: 3378.9237 | AI5: 8777.3787 | AJ5: 38702.422 | AK5: 14495.834 | AL5: 4735.4691 | AM5: 0 | AN5: 32.70972 | AO5: 31129.439 | AP5: 115478.55 | AQ5: 7466.2976 | AR5: 3442.7125 | AS5: 3859.6273 | AT5: 247.772 | AU5: 4084.1238 | AV5: 5.5752 | AW5: 26.37448 | AX5: 122.42539 | AY5: 17931.902 | AZ5: 3278.5344 | BA5: 0 | BB5: 0 | BC5: 1227.544 | BD5: 24.96537 | BE5: 4825.6174 | BF5: 1438.0797 | BG5: 774.30697 | BH5: 32.90939 | BI5: 1208.5972 | BJ5: 2660.0249 | BK5: 4237.5729 | BL5: 10504.286 | BM5: 20002.065 | BN5: 9530.5506 | BO5: 2108.9683 | BP5: 400.6016 | BQ5: 2.15351 | BR5: 4.60138 | BS5: 3174.7323 | BT5: 6588.9122 | BU5: 11037.188 | BV5: 203219.03 | BW5: 54276.676 | BX5: 18792.897 | BY5: 12820.904 | BZ5: 7.02996 | CA5: 23985.909 | CB5: 562.53789 | CC5: 48.19818 | CD5: 0.011 | CE5: 144.23965 | CF5: 4276.7002 | CG5: 2338.1597 | CH5: 30463.273 | CI5: 40494.759 | CJ5: 28.47 | CK5: 39026.89 | CL5: 7926.7196 | CM5: 731.278 | CN5: 6510.3774 | CO5: 53.39901 | CP5: 219.99625 | CQ5: 92.032 | CR5: 11034.146 | CS5: 1356.8451 | CT5: 8670.7026 | CU5: 360.91503 | CV5: 569.80631 | CW5: 2439035.6 | CX5: 2439035.6
A6: 2020 | B6: =ROUNDUP(MONTH($B6)/3, 0) -> 2 | C6: 43922 | D6: 7636.5775 | E6: 11334.171 | F6: 10272.063 | G6: 1033.8918 | H6: 2567.3537 | I6: 107589.82 | J6: 1815.8753 | K6: 90541.925 | L6: 157384.05 | M6: 9.10763 | N6: 8167.5797 | O6: 1872.0622 | P6: 363.0955 | Q6: 44.27424 | R6: 59569.307 | S6: 3613.91 | T6: 34592.498 | U6: 8175.3612 | V6: 12455.963 | W6: 6678.2493 | X6: 33625.343 | Y6: 2408.0981 | Z6: 3412.9711 | AA6: 1215.514 | AB6: 843.94455 | AC6: 2274.7494 | AD6: 701773.55 | AE6: 7591.4636 | AF6: 8069.9645 | AG6: 29251.21 | AH6: 3000.1722 | AI6: 4835.5166 | AJ6: 24231.095 | AK6: 12748.492 | AL6: 5925.1496 | AM6: 0 | AN6: 4.46485 | AO6: 25015.153 | AP6: 116495.32 | AQ6: 2638.9385 | AR6: 1111.7788 | AS6: 1500.1158 | AT6: 44.66694 | AU6: 3989.1284 | AV6: 0 | AW6: 5.5066 | AX6: 32.83954 | AY6: 13464.055 | AZ6: 735.65476 | BA6: 0 | BB6: 0 | BC6: 25.64096 | BD6: 24.24775 | BE6: 2405.8986 | BF6: 164.78519 | BG6: 341.15757 | BH6: 10.14846 | BI6: 337.6931 | BJ6: 1197.161 | BK6: 244.97228 | BL6: 2783.7943 | BM6: 4543.8581 | BN6: 5440.7928 | BO6: 1262.4193 | BP6: 198.34159 | BQ6: 9.841 | BR6: 4.4118 | BS6: 910.21525 | BT6: 2784.7525 | BU6: 8370.059 | BV6: 125274.17 | BW6: 44387.647 | BX6: 4537.4859 | BY6: 10573.852 | BZ6: 0.00594 | CA6: 21766.629 | CB6: 357.56607 | CC6: 2.4368 | CD6: 0 | CE6: 24.156 | CF6: 2109.9722 | CG6: 692.27791 | CH6: 14529.542 | CI6: 17970.01 | CJ6: 0 | CK6: 25841.878 | CL6: 1555.7069 | CM6: 9.466 | CN6: 7105.7616 | CO6: 22.78843 | CP6: 0 | CQ6: 5078 | CR6: 4081.2456 | CS6: 2213.7177 | CT6: 11850.708 | CU6: 930.873 | CV6: 300.75876 | CW6: 1864238.8 | CX6: 1864238.8
A7: 2020 | B7: =ROUNDUP(MONTH($B7)/3, 0) -> 2 | C7: 43952 | D7: 12423.199 | E7: 8739.1907 | F7: 7760.6506 | G7: 1420.3196 | H7: 2295.117 | I7: 146473.07 | J7: 1827.1337 | K7: 101953.32 | L7: 141864.02 | M7: 1613.5924 | N7: 4326.4447 | O7: 2784.706 | P7: 691.47952 | Q7: 18.19796 | R7: 77606.506 | S7: 2405.0459 | T7: 31593.03 | U7: 9986.3881 | V7: 13662.819 | W7: 6915.1673 | X7: 30329.982 | Y7: 1384.2941 | Z7: 2926.7982 | AA7: 803.55958 | AB7: 625.58304 | AC7: 11741.155 | AD7: 928404.78 | AE7: 4828.6107 | AF7: 7867.3875 | AG7: 29397.877 | AH7: 3145.1364 | AI7: 4636.9098 | AJ7: 27472.352 | AK7: 18133.411 | AL7: 3788.9266 | AM7: 0 | AN7: 0 | AO7: 38475.648 | AP7: 84818.214 | AQ7: 3401.4931 | AR7: 837.66025 | AS7: 1837.1784 | AT7: 129.9768 | AU7: 1894.0616 | AV7: 8.02385 | AW7: 16.66733 | AX7: 1064.5958 | AY7: 22432.234 | AZ7: 878.1678 | BA7: 0 | BB7: 0 | BC7: 257.35696 | BD7: 23.50955 | BE7: 2300.4321 | BF7: 897.40533 | BG7: 902.1713 | BH7: 10.32645 | BI7: 441.36278 | BJ7: 1896.7769 | BK7: 633.69167 | BL7: 5047.3628 | BM7: 5390.8963 | BN7: 9293.0801 | BO7: 624.06844 | BP7: 288.64207 | BQ7: 18.48622 | BR7: 0.594 | BS7: 1341.921 | BT7: 1691.8232 | BU7: 11179.301 | BV7: 225502.27 | BW7: 32567.331 | BX7: 5560.2636 | BY7: 5754.4293 | BZ7: 12.00632 | CA7: 27795.905 | CB7: 70.64954 | CC7: 2.45844 | CD7: 0 | CE7: 29.11532 | CF7: 2424.5801 | CG7: 1125.6992 | CH7: 14249.035 | CI7: 27941.728 | CJ7: 219.264 | CK7: 4635.2617 | CL7: 1732.9183 | CM7: 166.10809 | CN7: 6822.7751 | CO7: 61.71479 | CP7: 29.83527 | CQ7: 265.7017 | CR7: 4787.7206 | CS7: 116.16534 | CT7: 9080.0985 | CU7: 135.526 | CV7: 203.64973 | CW7: 2221171.5 | CX7: 2221171.5
A8: 2020 | B8: =ROUNDUP(MONTH($B8)/3, 0) -> 2 | C8: 43983 | D8: 20679.381 | E8: 6372.6097 | F8: 9267.5178 | G8: 1211.9578 | H8: 3161.6928 | I8: 100946.03 | J8: 1537.4502 | K8: 95216.851 | L8: 194805.85 | M8: 752.15871 | N8: 8026.7694 | O8: 3119.1465 | P8: 220.98755 | Q8: 27.36 | R8: 73167.068 | S8: 1548.3924 | T8: 28866.329 | U8: 5285.9972 | V8: 13302.361 | W8: 6843.2821 | X8: 31288.539 | Y8: 2409.5887 | Z8: 2736.0624 | AA8: 2600.9276 | AB8: 949.24465 | AC8: 2225.9328 | AD8: 921343.93 | AE8: 6378.0183 | AF8: 6824.3384 | AG8: 32996.846 | AH8: 3110.0255 | AI8: 5711.8739 | AJ8: 29741.566 | AK8: 13070.226 | AL8: 4845.322 | AM8: 0 | AN8: 56.75789 | AO8: 33506.747 | AP8: 78733.453 | AQ8: 5960.9231 | AR8: 1383.3954 | AS8: 2915.6486 | AT8: 356.43617 | AU8: 1915.1214 | AV8: 0 | AW8: 9.09624 | AX8: 562.99207 | AY8: 21125.981 | AZ8: 2067.5807 | BA8: 0 | BB8: 0.17081 | BC8: 210.34275 | BD8: 68.59759 | BE8: 2868.6449 | BF8: 498.69251 | BG8: 555.94538 | BH8: 39.94354 | BI8: 644.85967 | BJ8: 2576.4763 | BK8: 1165.4057 | BL8: 7819.0367 | BM8: 13128.582 | BN8: 8040.4766 | BO8: 908.47722 | BP8: 706.24604 | BQ8: 0.8842 | BR8: 7.817 | BS8: 2631.7251 | BT8: 3451.7717 | BU8: 8694.1881 | BV8: 247568.94 | BW8: 35879.478 | BX8: 7388.9622 | BY8: 8458.9053 | BZ8: 3.79233 | CA8: 27369.887 | CB8: 498.85748 | CC8: 0 | CD8: 0 | CE8: 0 | CF8: 3503.6078 | CG8: 1726.2529 | CH8: 21462.239 | CI8: 41720.08 | CJ8: 39.0122 | CK8: 23561.033 | CL8: 1110.2288 | CM8: 84.27767 | CN8: 6715.9794 | CO8: 557.01176 | CP8: 0 | CQ8: 64.98823 | CR8: 8234.1387 | CS8: 309.99266 | CT8: 9716.4864 | CU8: 2.3 | CV8: 301.57871 | CW8: 2289482.1 | CX8: 2289482.1
A9: 2020 | B9: =ROUNDUP(MONTH($B9)/3, 0) -> 3 | C9: 44013 | D9: 3462.8314 | E9: 8003.0681 | F9: 13227.402 | G9: 1060.0127 | H9: 2792.4633 | I9: 107332.64 | J9: 1722.265 | K9: 91828.713 | L9: 270277.39 | M9: 598.65566 | N9: 10609.526 | O9: 2401.5718 | P9: 1080.1327 | Q9: 55.03872 | R9: 46343.557 | S9: 4646.7644 | T9: 44149.23 | U9: 8982.3554 | V9: 16069.36 | W9: 9458.2393 | X9: 35857.526 | Y9: 2771.5441 | Z9: 3143.1626 | AA9: 2261.8491 | AB9: 1726.7204 | AC9: 22934.87 | AD9: 936559.69 | AE9: 5837.8874 | AF9: 7522.937 | AG9: 32300.99 | AH9: 5842.7649 | AI9: 7270.2102 | AJ9: 34178.811 | AK9: 16649.27 | AL9: 3996.4515 | AM9: 1.42611 | AN9: 4.8685 | AO9: 46943.579 | AP9: 113001.52 | AQ9: 8842.172 | AR9: 1145.8388 | AS9: 3603.8111 | AT9: 531.8411 | AU9: 2857.0435 | AV9: 15.1052 | AW9: 58.3406 | AX9: 193.97437 | AY9: 24337.799 | AZ9: 2411.9137 | BA9: 0 | BB9: 0.025 | BC9: 386.66372 | BD9: 67.9381 | BE9: 3168.7751 | BF9: 784.05653 | BG9: 1021.9391 | BH9: 66.39818 | BI9: 616.07914 | BJ9: 2642.3285 | BK9: 3010.3127 | BL9: 9087.1263 | BM9: 15819.586 | BN9: 9578.8974 | BO9: 1438.3002 | BP9: 508.00818 | BQ9: 13.75244 | BR9: 9.581 | BS9: 3398.6351 | BT9: 5037.855 | BU9: 11581.019 | BV9: 291202.74 | BW9: 32654.022 | BX9: 11628.994 | BY9: 16587.877 | BZ9: 0.82727 | CA9: 28380.911 | CB9: 573.37866 | CC9: 23.5925 | CD9: 17.07191 | CE9: 157.70372 | CF9: 5201.7083 | CG9: 2301.4357 | CH9: 24557.622 | CI9: 39518.204 | CJ9: 6.1152 | CK9: 36713.524 | CL9: 1926.7839 | CM9: 93.095 | CN9: 7993.5277 | CO9: 110.67312 | CP9: 6.522 | CQ9: 28.9568 | CR9: 6909.2677 | CS9: 1199.2987 | CT9: 8519.1336 | CU9: 0.474 | CV9: 532.41455 | CW9: 2551988.3 | CX9: 2551988.3
A10: 2020 | B10: =ROUNDUP(MONTH($B10)/3, 0) -> 3 | C10: 44044 | D10: 19307.744 | E10: 9069.8061 | F10: 9065.1832 | G10: 1397.4092 | H10: 2587.3571 | I10: 93201.056 | J10: 1674.3694 | K10: 78973.677 | L10: 201786.85 | M10: 178.59874 | N10: 7177.2354 | O10: 1710.133 | P10: 726.66451 | Q10: 14.64 | R10: 48286.822 | S10: 3629.7212 | T10: 42992.298 | U10: 11807.748 | V10: 13359.498 | W10: 8616.5724 | X10: 33037.785 | Y10: 1566.4694 | Z10: 2491.7716 | AA10: 691.00058 | AB10: 1226.6447 | AC10: 2147.7141 | AD10: 1103433.3 | AE10: 6259.649 | AF10: 8736.0522 | AG10: 33823.501 | AH10: 5149.8577 | AI10: 7010.2198 | AJ10: 35480.435 | AK10: 17598.248 | AL10: 3769.0606 | AM10: 0 | AN10: 13.1366 | AO10: 33612.421 | AP10: 106562.53 | AQ10: 7941.4426 | AR10: 2016.8387 | AS10: 3559.2674 | AT10: 541.35067 | AU10: 3628.2314 | AV10: 0.1799 | AW10: 25.89096 | AX10: 297.71655 | AY10: 17781.011 | AZ10: 1649.9764 | BA10: 0 | BB10: 0 | BC10: 181.4757 | BD10: 51.84467 | BE10: 4525.0127 | BF10: 1328.9749 | BG10: 1021.7314 | BH10: 149.81703 | BI10: 887.44201 | BJ10: 2471.0874 | BK10: 3823.8965 | BL10: 12569.863 | BM10: 18452.812 | BN10: 9571.916 | BO10: 1444.4104 | BP10: 220.51369 | BQ10: 39.97421 | BR10: 0.945 | BS10: 3641.1238 | BT10: 7268.9126 | BU10: 10088.61 | BV10: 287292.99 | BW10: 44967.362 | BX10: 8721.334 | BY10: 9598.1892 | BZ10: 5.8698 | CA10: 24346.887 | CB10: 442.07224 | CC10: 20.08335 | CD10: 0 | CE10: 24.565 | CF10: 4498.8126 | CG10: 2266.3248 | CH10: 30672.649 | CI10: 43712.636 | CJ10: 3.72288 | CK10: 24714.622 | CL10: 1612.0636 | CM10: 206.264 | CN10: 7134.6964 | CO10: 120.77534 | CP10: 5.25225 | CQ10: 0 | CR10: 9496.1421 | CS10: 1115.4602 | CT10: 9341.83 | CU10: 148.19317 | CV10: 942.46717 | CW10: 2584766.8 | CX10: 2584766.8
A11: 2020 | B11: =ROUNDUP(MONTH($B11)/3, 0) -> 3 | C11: 44075 | D11: 5328.0891 | E11: 12127.899 | F11: 14334.331 | G11: 1196.3876 | H11: 3292.3668 | I11: 108948.9 | J11: 1730.5213 | K11: 86821.613 | L11: 217897.43 | M11: 14.14866 | N11: 8095.4897 | O11: 2129.5422 | P11: 114.60412 | Q11: 14.61542 | R11: 34311.53 | S11: 3445.0166 | T11: 53438.732 | U11: 9204.3988 | V11: 15094.125 | W11: 9228.5458 | X11: 37043.65 | Y11: 4122.11 | Z11: 2740.2882 | AA11: 345.016 | AB11: 1795.4164 | AC11: 1743.122 | AD11: 931901.67 | AE11: 5215.6114 | AF11: 6635.7382 | AG11: 33616.144 | AH11: 4721.9778 | AI11: 8033.5231 | AJ11: 40503.899 | AK11: 15584.054 | AL11: 4935.7139 | AM11: 3.932 | AN11: 60.42866 | AO11: 46851.074 | AP11: 126820.73 | AQ11: 8124.4356 | AR11: 3742.9268 | AS11: 3901.3047 | AT11: 419.6996 | AU11: 4125.8767 | AV11: 11.79234 | AW11: 4.54522 | AX11: 125.04524 | AY11: 21018.435 | AZ11: 2522.3941 | BA11: 0 | BB11: 2.87525 | BC11: 858.94689 | BD11: 141.8152 | BE11: 3811.6069 | BF11: 831.24142 | BG11: 1263.0381 | BH11: 37.82256 | BI11: 903.16993 | BJ11: 2275.561 | BK11: 4726.8272 | BL11: 10445.939 | BM11: 15710.139 | BN11: 8893.3258 | BO11: 1851.8581 | BP11: 644.5217 | BQ11: 78.55739 | BR11: 4.67457 | BS11: 3977.6395 | BT11: 6090.8854 | BU11: 11970.605 | BV11: 298528.68 | BW11: 38100.985 | BX11: 10914.616 | BY11: 13701.53 | BZ11: 14.01775 | CA11: 27967.044 | CB11: 1523.1041 | CC11: 25.79591 | CD11: 9.65826 | CE11: 231.38383 | CF11: 5876.2768 | CG11: 3100.2285 | CH11: 39417.453 | CI11: 59468.836 | CJ11: 232.2091 | CK11: 32213.334 | CL11: 4319.5195 | CM11: 185.096 | CN11: 6579.5672 | CO11: 96.2227 | CP11: 6.57484 | CQ11: 0 | CR11: 10368.027 | CS11: 1230.3817 | CT11: 11238.754 | CU11: 669.04391 | CV11: 895.37942 | CW11: 2544873.6 | CX11: 2544873.6
A12: 2020 | B12: =ROUNDUP(MONTH($B12)/3, 0) -> 4 | C12: 44105 | D12: 20199.379 | E12: 13383.581 | F12: 9802.6584 | G12: 1615.7324 | H12: 3409.8577 | I12: 101595.86 | J12: 2234.002 | K12: 116055.25 | L12: 173371.85 | M12: 3.80323 | N12: 7618.092 | O12: 4352.7958 | P12: 291.98392 | Q12: 29.91293 | R12: 48942.226 | S12: 2866.4332 | T12: 54238.004 | U12: 9420.1782 | V12: 11635.229 | W12: 9072.5215 | X12: 33705.384 | Y12: 2142.3544 | Z12: 2438.6455 | AA12: 996.44258 | AB12: 1392.8087 | AC12: 17998.639 | AD12: 969246.64 | AE12: 8979.0802 | AF12: 8862.3294 | AG12: 32437.104 | AH12: 3974.7049 | AI12: 7213.2521 | AJ12: 39654.601 | AK12: 11075.233 | AL12: 4275.4118 | AM12: 0 | AN12: 70.51468 | AO12: 43601.579 | AP12: 101781.69 | AQ12: 8372.2972 | AR12: 2892.8009 | AS12: 3427.5338 | AT12: 220.84417 | AU12: 4596.919 | AV12: 12.54245 | AW12: 10.51317 | AX12: 116.01949 | AY12: 22336.759 | AZ12: 2336.2322 | BA12: 1.426 | BB12: 0.3872 | BC12: 558.99209 | BD12: 63.05937 | BE12: 4542.6882 | BF12: 724.01227 | BG12: 1340.3991 | BH12: 58.10527 | BI12: 940.19936 | BJ12: 2795.6299 | BK12: 3692.3818 | BL12: 13150.312 | BM12: 20696.395 | BN12: 6000.6068 | BO12: 1762.0192 | BP12: 488.54595 | BQ12: 54.55435 | BR12: 33.20294 | BS12: 4167.1942 | BT12: 6194.0816 | BU12: 10250.068 | BV12: 378452.1 | BW12: 44892.123 | BX12: 13292.74 | BY12: 16649.751 | BZ12: 27.32535 | CA12: 29222.435 | CB12: 530.7292 | CC12: 47.50697 | CD12: 10.52226 | CE12: 86.87396 | CF12: 5529.053 | CG12: 2340.027 | CH12: 35965.498 | CI12: 56209.662 | CJ12: 200.50294 | CK12: 24834.522 | CL12: 1618.601 | CM12: 181.90585 | CN12: 7856.2383 | CO12: 8.87077 | CP12: 0.38926 | CQ12: 2170.8755 | CR12: 9373.3803 | CS12: 1674.8408 | CT12: 11062.019 | CU12: 221.025 | CV12: 671.49301 | CW12: 2644953.5 | CX12: 2644953.5
A13: 2020 | B13: =ROUNDUP(MONTH($B13)/3, 0) -> 4 | C13: 44136 | D13: 11434.976 | E13: 12689.547 | F13: 17127.983 | G13: 2367.8987 | H13: 3059.5521 | I13: 125965.22 | J13: 2300.9295 | K13: 105597.31 | L13: 227635.81 | M13: 103.29748 | N13: 6559.8745 | O13: 2711.4873 | P13: 210.76136 | Q13: 45.52654 | R13: 42342.796 | S13: 2332.2197 | T13: 46964.819 | U13: 9476.8659 | V13: 12698.756 | W13: 8547.4817 | X13: 29579.604 | Y13: 4036.2958 | Z13: 2414.5017 | AA13: 2494.8859 | AB13: 1379.3152 | AC13: 415.04937 | AD13: 872364.36 | AE13: 8695.9553 | AF13: 8844.3592 | AG13: 27072.153 | AH13: 3521.1182 | AI13: 7749.6485 | AJ13: 40168.27 | AK13: 13522.696 | AL13: 4593.1318 | AM13: 1.17527 | AN13: 0.41946 | AO13: 32413.162 | AP13: 114105.92 | AQ13: 7509.7285 | AR13: 3140.4753 | AS13: 3890.0713 | AT13: 811.48058 | AU13: 3895.8459 | AV13: 4.52443 | AW13: 54.95668 | AX13: 154.62726 | AY13: 21046.03 | AZ13: 2474.816 | BA13: 0 | BB13: 0.308 | BC13: 1054.1781 | BD13: 133.39842 | BE13: 4999.3548 | BF13: 709.23644 | BG13: 1345.9202 | BH13: 109.98537 | BI13: 1130.7437 | BJ13: 2324.315 | BK13: 5528.7195 | BL13: 15238.304 | BM13: 23935.551 | BN13: 7597.9979 | BO13: 2053.5054 | BP13: 518.17182 | BQ13: 64.28021 | BR13: 5.14633 | BS13: 4313.4942 | BT13: 5862.8343 | BU13: 12887.151 | BV13: 298377.68 | BW13: 46651.96 | BX13: 12819.122 | BY13: 12943.418 | BZ13: 8.39972 | CA13: 34693.722 | CB13: 407.93503 | CC13: 28.11501 | CD13: 10.48685 | CE13: 104.71741 | CF13: 5509.7053 | CG13: 3249.9363 | CH13: 33628.241 | CI13: 54030.605 | CJ13: 11.3225 | CK13: 39441.843 | CL13: 2226.8522 | CM13: 282.71055 | CN13: 7848.9929 | CO13: 93.91285 | CP13: 221.89604 | CQ13: 4.93615 | CR13: 10280.908 | CS13: 1774.4079 | CT13: 11161.148 | CU13: 17.20748 | CV13: 1201.4068 | CW13: 2523371.9 | CX13: 2523371.9
A14: 2020 | B14: =ROUNDUP(MONTH($B14)/3, 0) -> 4 | C14: 44166 | D14: 18731.893 | E14: 18498.074 | F14: 8689.1018 | G14: 3092.9563 | H14: 2849.0581 | I14: 106377.55 | J14: 2241.9835 | K14: 172723.44 | L14: 316675.7 | M14: 94.44846 | N14: 3793.1528 | O14: 3309.4849 | P14: 1148.4113 | Q14: 95.30487 | R14: 35751.706 | S14: 3147.1054 | T14: 49451.686 | U14: 9597.2711 | V14: 13657.975 | W14: 8113.947 | X14: 37966.196 | Y14: 4735.4571 | Z14: 3161.1475 | AA14: 2850.4502 | AB14: 1855.0056 | AC14: 6296.006 | AD14: 1092089.4 | AE14: 8599.1426 | AF14: 10801.978 | AG14: 32438.039 | AH14: 5857.629 | AI14: 8454.7189 | AJ14: 40785.754 | AK14: 14279.076 | AL14: 3861.8301 | AM14: 0 | AN14: 22.96484 | AO14: 45485.199 | AP14: 147538.74 | AQ14: 10170.413 | AR14: 3516.4679 | AS14: 4899.0343 | AT14: 763.0953 | AU14: 4618.7441 | AV14: 3.68824 | AW14: 75.41764 | AX14: 191.77426 | AY14: 25227.387 | AZ14: 2467.3389 | BA14: 0 | BB14: 0 | BC14: 970.4037 | BD14: 79.49654 | BE14: 3908.7511 | BF14: 593.48646 | BG14: 1495.0019 | BH14: 36.78806 | BI14: 1394.0852 | BJ14: 3093.7801 | BK14: 3201.6957 | BL14: 16164.95 | BM14: 24209.966 | BN14: 7817.6666 | BO14: 2180.1917 | BP14: 921.06093 | BQ14: 19.03901 | BR14: 12.02943 | BS14: 4594.4342 | BT14: 9228.0256 | BU14: 15446.757 | BV14: 331767.39 | BW14: 55403.827 | BX14: 13288.182 | BY14: 18563.397 | BZ14: 0.87861 | CA14: 30643.849 | CB14: 426.50916 | CC14: 10.08816 | CD14: 2.16388 | CE14: 156.07275 | CF14: 6294.7762 | CG14: 3143.7349 | CH14: 49676.061 | CI14: 53109.598 | CJ14: 107.41517 | CK14: 38938.324 | CL14: 697.54595 | CM14: 1043.8098 | CN14: 7324.9103 | CO14: 109.57466 | CP14: 12.14242 | CQ14: 771.04103 | CR14: 10446.705 | CS14: 1934.9288 | CT14: 11320.846 | CU14: 388.332 | CV14: 835.17413 | CW14: 3028837.2 | CX14: 3028837.2
A15: =YEAR($B15) -> 2021 | B15: =ROUNDUP(MONTH($B15)/3, 0) -> 1 | C15: 44197 | D15: 13911.225 | E15: 12741.043 | F15: 8186.087 | G15: 1891.9865 | H15: 3323.4998 | I15: 130252.4 | J15: 2121.0343 | K15: 104670.6 | L15: 255455.19 | M15: 8.616 | N15: 5722.5441 | O15: 3421.7549 | P15: 178.35035 | Q15: 24.11941 | R15: 25449.877 | S15: 1466.8528 | T15: 32402.132 | U15: 7130.2707 | V15: 8207.6304 | W15: 7073.8667 | X15: 25894.914 | Y15: 2729.6787 | Z15: 2222.3064 | AA15: 1065.1418 | AB15: 1346.7871 | AC15: 1216.829 | AD15: 1182946.7 | AE15: 7957.9687 | AF15: 7984.621 | AG15: 22737.487 | AH15: 3456.1987 | AI15: 5478.1774 | AJ15: 28107.161 | AK15: 11349.955 | AL15: 3423.8799 | AM15: 0 | AN15: 3.34805 | AO15: 42420.967 | AP15: 130770.46 | AQ15: 6729.9684 | AR15: 3127.2572 | AS15: 2325.3111 | AT15: 214.5686 | AU15: 4474.3094 | AV15: 0 | AW15: 8.89161 | AX15: 13.24423 | AY15: 19722.687 | AZ15: 1630.5683 | BA15: 0 | BB15: 0 | BC15: 1005.0161 | BD15: 55.16542 | BE15: 3419.7832 | BF15: 585.19504 | BG15: 712.41378 | BH15: 59.59544 | BI15: 673.0778 | BJ15: 2590.6476 | BK15: 2464.5573 | BL15: 12374.742 | BM15: 15548.679 | BN15: 7110.0383 | BO15: 1158.98 | BP15: 574.49915 | BQ15: 6.67479 | BR15: 0 | BS15: 3739.8368 | BT15: 3626.4941 | BU15: 10494.509 | BV15: 191099.61 | BW15: 36932.943 | BX15: 11468.949 | BY15: 20863.128 | BZ15: 4.73823 | CA15: 29790.564 | CB15: 472.39478 | CC15: 33.57771 | CD15: 10.648 | CE15: 97.0421 | CF15: 3853.9803 | CG15: 2988.9177 | CH15: 28140.863 | CI15: 35554.166 | CJ15: 7.33472 | CK15: 13917.296 | CL15: 1108.1801 | CM15: 32.634 | CN15: 5990.0339 | CO15: 114.03802 | CP15: 1.794 | CQ15: 21.33 | CR15: 8147.4061 | CS15: 1587.5088 | CT15: 8527.2086 | CU15: 59.115 | CV15: 912.61658 | CW15: 2610936.4 | CX15: 2610936.4
A16: =YEAR($B16) -> 2021 | B16: =ROUNDUP(MONTH($B16)/3, 0) -> 1 | C16: 44228 | D16: 15034.396 | E16: 20707.191 | F16: 10782.322 | G16: 1506.7452 | H16: 3992.7001 | I16: 154414.6 | J16: 1960.6725 | K16: 93982.401 | L16: 267999.83 | M16: 185.02897 | N16: 3272.0664 | O16: 2362.8002 | P16: 271.41843 | Q16: 24.71142 | R16: 39288.292 | S16: 1461.23 | T16: 39991.037 | U16: 9210.0935 | V16: 13714.95 | W16: 9355.5469 | X16: 36236.339 | Y16: 2750.1877 | Z16: 3515.5831 | AA16: 284.89469 | AB16: 1645.2511 | AC16: 20083.241 | AD16: 1252154.3 | AE16: 6539.9314 | AF16: 9266.9378 | AG16: 32804.088 | AH16: 3941.2876 | AI16: 8999.9937 | AJ16: 37132.385 | AK16: 15684.013 | AL16: 5521.6506 | AM16: 0 | AN16: 31.71977 | AO16: 29976.551 | AP16: 159060.52 | AQ16: 7635.1124 | AR16: 5152.6784 | AS16: 3534.7149 | AT16: 437.67698 | AU16: 4581.9621 | AV16: 10.5825 | AW16: 62.04493 | AX16: 128.33005 | AY16: 18174.763 | AZ16: 2417.687 | BA16: 0 | BB16: 0 | BC16: 1019.2704 | BD16: 232.19459 | BE16: 4045.4395 | BF16: 797.46989 | BG16: 1234.6013 | BH16: 46.87234 | BI16: 952.68809 | BJ16: 2767.0733 | BK16: 3562.2068 | BL16: 13411.063 | BM16: 19332.57 | BN16: 4691.9404 | BO16: 2146.7511 | BP16: 613.15255 | BQ16: 3.05123 | BR16: 3.20544 | BS16: 5035.3128 | BT16: 6421.3744 | BU16: 12479.737 | BV16: 261144.81 | BW16: 31513.479 | BX16: 13653.655 | BY16: 16420.65 | BZ16: 1.16262 | CA16: 34815.77 | CB16: 411.17659 | CC16: 34.02049 | CD16: 2.62544 | CE16: 63.04497 | CF16: 5584.8127 | CG16: 2996.0559 | CH16: 33554.953 | CI16: 43486.227 | CJ16: 61.00036 | CK16: 20877.374 | CL16: 2183.341 | CM16: 124.44095 | CN16: 7415.5084 | CO16: 135.4824 | CP16: 0 | CQ16: 0.095 | CR16: 12416.108 | CS16: 2549.5041 | CT16: 12099.206 | CU16: 611.19026 | CV16: 760.01858 | CW16: 2938994.1 | CX16: 2938994.1
A17: =YEAR($B17) -> 2021 | B17: =ROUNDUP(MONTH($B17)/3, 0) -> 1 | C17: 44256 | D17: 29470.398 | E17: 20817.408 | F17: 8220.3561 | G17: 2808.6078 | H17: 3754.6105 | I17: 204659.83 | J17: 2566.0262 | K17: 147978.95 | L17: 278224.94 | M17: 1042.5165 | N17: 6402.7726 | O17: 4153.2777 | P17: 1090.3993 | Q17: 65.40321 | R17: 72334.228 | S17: 941.33656 | T17: 54102.918 | U17: 10681.577 | V17: 16281.978 | W17: 10682.154 | X17: 37894.873 | Y17: 3494.4762 | Z17: 4065.5428 | AA17: 4503.0876 | AB17: 1828.431 | AC17: 21116.19 | AD17: 1399605.3 | AE17: 8192.7657 | AF17: 10069.704 | AG17: 30552.389 | AH17: 6125.8823 | AI17: 8029.9868 | AJ17: 43708.143 | AK17: 16178.032 | AL17: 4228.9153 | AM17: 0 | AN17: 4.25687 | AO17: 42013.551 | AP17: 150113.3 | AQ17: 8672.0825 | AR17: 5097.0415 | AS17: 4891.9746 | AT17: 504.11504 | AU17: 5489.8831 | AV17: 1.75295 | AW17: 99.73325 | AX17: 42.27037 | AY17: 24292.125 | AZ17: 2376.992 | BA17: 0 | BB17: 0.69336 | BC17: 1333.9815 | BD17: 295.97396 | BE17: 5026.3458 | BF17: 713.44617 | BG17: 1385.2707 | BH17: 212.78295 | BI17: 1602.3506 | BJ17: 3083.1161 | BK17: 3840.4882 | BL17: 16666.658 | BM17: 24651.798 | BN17: 10176.418 | BO17: 2434.1723 | BP17: 624.02884 | BQ17: 46.39415 | BR17: 7.06 | BS17: 3998.4424 | BT17: 7928.0548 | BU17: 13513.368 | BV17: 279537 | BW17: 35166.377 | BX17: 18627.106 | BY17: 23951.82 | BZ17: 0.87338 | CA17: 41515.611 | CB17: 780.21748 | CC17: 24.57989 | CD17: 10.40122 | CE17: 92.04335 | CF17: 6980.1346 | CG17: 4189.188 | CH17: 37012.958 | CI17: 54884.442 | CJ17: 68.7682 | CK17: 28651.729 | CL17: 2097.5215 | CM17: 813.7623 | CN17: 7849.823 | CO17: 214.91655 | CP17: 1.4352 | CQ17: 1204.1963 | CR17: 9740.1724 | CS17: 2907.6159 | CT17: 9026.5339 | CU17: 521.277 | CV17: 670.2894 | CW17: 3383554.1 | CX17: 3383554.1
A18: =YEAR($B18) -> 2021 | B18: =ROUNDUP(MONTH($B18)/3, 0) -> 2 | C18: 44287 | D18: 14569.425 | E18: 17686.102 | F18: 13186.095 | G18: 3642.8197 | H18: 3659.8691 | I18: 147307.18 | J18: 2763.3516 | K18: 129717.14 | L18: 243363.43 | M18: 1190.8728 | N18: 5872.5744 | O18: 3535.9929 | P18: 499.50416 | Q18: 113.19439 | R18: 67089.74 | S18: 2281.9681 | T18: 40652.568 | U18: 10360.073 | V18: 11475.497 | W18: 10061.091 | X18: 36101.172 | Y18: 2825.6409 | Z18: 3134.8555 | AA18: 685.6413 | AB18: 1939.638 | AC18: 3461.2628 | AD18: 1203308.6 | AE18: 6631.0257 | AF18: 9984.7997 | AG18: 31165.811 | AH18: 3667.6508 | AI18: 10156.703 | AJ18: 38888.289 | AK18: 15541.54 | AL18: 4290.4601 | AM18: 64.20827 | AN18: 43.27812 | AO18: 30786.856 | AP18: 167456.38 | AQ18: 8821.5383 | AR18: 6357.5696 | AS18: 3734.3199 | AT18: 704.20886 | AU18: 5946.0305 | AV18: 8.093 | AW18: 145.54578 | AX18: 132.16722 | AY18: 24023.731 | AZ18: 3465.2664 | BA18: 2.77344 | BB18: 0 | BC18: 1072.5362 | BD18: 248.19484 | BE18: 4775.3604 | BF18: 840.26437 | BG18: 1020.552 | BH18: 30.4849 | BI18: 1067.2748 | BJ18: 2988.7859 | BK18: 4050.5632 | BL18: 13373.781 | BM18: 22157.772 | BN18: 8508.6726 | BO18: 1920.6574 | BP18: 548.91255 | BQ18: 18.99573 | BR18: 1.325 | BS18: 4504.0157 | BT18: 6721.3714 | BU18: 13083.821 | BV18: 272004.22 | BW18: 34528.075 | BX18: 18096.524 | BY18: 18520.455 | BZ18: 0.05131 | CA18: 34011.197 | CB18: 898.1021 | CC18: 49.578 | CD18: 0 | CE18: 125.46468 | CF18: 5819.524 | CG18: 3976.6232 | CH18: 34811.062 | CI18: 52482.696 | CJ18: 49.27559 | CK18: 25739.418 | CL18: 1952.2247 | CM18: 567.688 | CN18: 6534.0832 | CO18: 278.02859 | CP18: 0 | CQ18: 697.45025 | CR18: 11740.7 | CS18: 2291.5342 | CT18: 11016.355 | CU18: 149.9815 | CV18: 595.16119 | CW18: 2976372.3 | CX18: 2976372.3
A19: =YEAR($B19) -> 2021 | B19: =ROUNDUP(MONTH($B19)/3, 0) -> 2 | C19: 44317 | D19: 9896.9705 | E19: 11920.867 | F19: 9325.8651 | G19: 2218.917 | H19: 4317.5893 | I19: 217431.35 | J19: 1704.6654 | K19: 128904.7 | L19: 124318.68 | M19: 719.18411 | N19: 8871.1202 | O19: 2516.199 | P19: 410.48461 | Q19: 9.74467 | R19: 84990.438 | S19: 2179.8639 | T19: 21403.408 | U19: 9860.5064 | V19: 6436.8228 | W19: 8959.6673 | X19: 20793.18 | Y19: 2137.9539 | Z19: 1720.5138 | AA19: 2262.5712 | AB19: 893.28869 | AC19: 6742.9018 | AD19: 1549776.4 | AE19: 8401.7882 | AF19: 9105.7644 | AG19: 21591.929 | AH19: 4912.3857 | AI19: 5769.4155 | AJ19: 23715.399 | AK19: 7547.3874 | AL19: 4193.7434 | AM19: 0 | AN19: 11.35772 | AO19: 39747.331 | AP19: 140940.67 | AQ19: 3638.6351 | AR19: 4764.2305 | AS19: 3902.4271 | AT19: 393.96065 | AU19: 4285.7028 | AV19: 1.1557 | AW19: 37.98328 | AX19: 77.66437 | AY19: 14313.209 | AZ19: 2415.5447 | BA19: 0 | BB19: 0.981 | BC19: 200.59388 | BD19: 210.95231 | BE19: 4319.2026 | BF19: 482.04872 | BG19: 948.83337 | BH19: 266.19917 | BI19: 737.58927 | BJ19: 2728.3696 | BK19: 1643.9057 | BL19: 12103.378 | BM19: 20522.609 | BN19: 6183.1541 | BO19: 1905.8776 | BP19: 302.26726 | BQ19: 3.47325 | BR19: 0 | BS19: 3140.3071 | BT19: 4546.3073 | BU19: 15655.345 | BV19: 302196.72 | BW19: 28484.883 | BX19: 11351.747 | BY19: 18312.046 | BZ19: 6.87009 | CA19: 36536.716 | CB19: 149.04497 | CC19: 8.01438 | CD19: 39.56467 | CE19: 91.57648 | CF19: 3178.0958 | CG19: 1875.5015 | CH19: 16262.65 | CI19: 23087.571 | CJ19: 61.98658 | CK19: 13917.02 | CL19: 4046.1032 | CM19: 166.552 | CN19: 5599.8974 | CO19: 37.3545 | CP19: 0 | CQ19: 757.33063 | CR19: 5510.9506 | CS19: 2170.316 | CT19: 6077.1415 | CU19: 71.609 | CV19: 523.1335 | CW19: 3096913.3 | CX19: 3096913.3
A20: =YEAR($B20) -> 2021 | B20: =ROUNDUP(MONTH($B20)/3, 0) -> 2 | C20: 44348 | D20: 5464.8101 | E20: 16091.965 | F20: 11380.108 | G20: 3069.7153 | H20: 3745.9008 | I20: 125897.16 | J20: 1463.8854 | K20: 125166.53 | L20: 115655.39 | M20: 35.53077 | N20: 9479.2041 | O20: 2618.0511 | P20: 88.36467 | Q20: 50.48794 | R20: 108183.33 | S20: 3658.2585 | T20: 16218.672 | U20: 9929.3562 | V20: 11795.818 | W20: 10057.239 | X20: 31341.313 | Y20: 3069.6076 | Z20: 2754.5234 | AA20: 1273.673 | AB20: 1335.6865 | AC20: 15853.588 | AD20: 1558797.1 | AE20: 5364.3329 | AF20: 8897.4544 | AG20: 30083.496 | AH20: 8073.0242 | AI20: 9014.3157 | AJ20: 33658.802 | AK20: 11327.484 | AL20: 4838.3568 | AM20: 0 | AN20: 31.15501 | AO20: 46416.391 | AP20: 165155.94 | AQ20: 5715.4284 | AR20: 5452.1217 | AS20: 3634.8385 | AT20: 743.33032 | AU20: 3760.0255 | AV20: 3.13995 | AW20: 50.76496 | AX20: 0 | AY20: 15909.532 | AZ20: 3419.6083 | BA20: 0 | BB20: 0.147 | BC20: 1123.4678 | BD20: 200.23165 | BE20: 5340.992 | BF20: 688.87312 | BG20: 1063.6078 | BH20: 35.87789 | BI20: 1202.3479 | BJ20: 3224.1762 | BK20: 5854.7536 | BL20: 15467.986 | BM20: 27651.05 | BN20: 7257.9436 | BO20: 2682.1331 | BP20: 976.28087 | BQ20: 4.57537 | BR20: 5.36396 | BS20: 4213.4008 | BT20: 6053.4255 | BU20: 10634.452 | BV20: 286289.56 | BW20: 42204.379 | BX20: 17574.137 | BY20: 18066.378 | BZ20: 1.28726 | CA20: 39477.091 | CB20: 110.05529 | CC20: 23.64262 | CD20: 1.76158 | CE20: 107.95515 | CF20: 5688.5184 | CG20: 3596.024 | CH20: 32142.464 | CI20: 37984.103 | CJ20: 6.26024 | CK20: 18033.123 | CL20: 1651.6962 | CM20: 2215.5874 | CN20: 6235.1428 | CO20: 135.41243 | CP20: 17.79847 | CQ20: 214.222 | CR20: 8884.0597 | CS20: 2144.0992 | CT20: 8629.5591 | CU20: 129.71 | CV20: 945.80091 | CW20: 3182215.7 | CX20: 3182215.7
A21: =YEAR($B21) -> 2021 | B21: =ROUNDUP(MONTH($B21)/3, 0) -> 3 | C21: 44378 | D21: 3719.3334 | E21: 21743.559 | F21: 9019.3801 | G21: 3075.9489 | H21: 4515.6599 | I21: 106769.88 | J21: 2294.71 | K21: 141759.41 | L21: 309123.08 | M21: 860.16755 | N21: 5996.3833 | O21: 3708.6236 | P21: 1041.0402 | Q21: 93.57512 | R21: 60008.458 | S21: 3284.058 | T21: 39668.284 | U21: 11528.138 | V21: 15746.605 | W21: 12118.647 | X21: 42953.738 | Y21: 4092.5355 | Z21: 5520.9043 | AA21: 397.92305 | AB21: 1378.608 | AC21: 25542.104 | AD21: 1415764.2 | AE21: 13958.959 | AF21: 10748.641 | AG21: 37372.744 | AH21: 5327.6347 | AI21: 9415.175 | AJ21: 47527.934 | AK21: 18366.914 | AL21: 4097.2085 | AM21: 31.18442 | AN21: 16.33865 | AO21: 45199.467 | AP21: 175121.41 | AQ21: 10604.133 | AR21: 5601.686 | AS21: 4837.1058 | AT21: 587.72725 | AU21: 3579.6379 | AV21: 29.05367 | AW21: 35.51878 | AX21: 274.63153 | AY21: 25854.969 | AZ21: 4023.9283 | BA21: 0 | BB21: 0 | BC21: 1095.5426 | BD21: 690.43605 | BE21: 5730.381 | BF21: 858.21668 | BG21: 1286.1304 | BH21: 452.76997 | BI21: 1091.3835 | BJ21: 3635.3101 | BK21: 6013.0904 | BL21: 17639.374 | BM21: 30113.524 | BN21: 6959.0585 | BO21: 2794.7721 | BP21: 1044.625 | BQ21: 204.26804 | BR21: 9.759 | BS21: 4366.15 | BT21: 9021.5138 | BU21: 12252.309 | BV21: 313275.83 | BW21: 50827.657 | BX21: 20078.453 | BY21: 37410.27 | BZ21: 0.11751 | CA21: 47202.285 | CB21: 570.37702 | CC21: 0.14036 | CD21: 29.69072 | CE21: 152.34662 | CF21: 6863.58 | CG21: 4706.7633 | CH21: 45806.557 | CI21: 54037.384 | CJ21: 7.46224 | CK21: 38035.937 | CL21: 2657.757 | CM21: 4691.9796 | CN21: 6200.8736 | CO21: 83.48062 | CP21: 4.14345 | CQ21: 12.645 | CR21: 14261.742 | CS21: 3437.5795 | CT21: 11980.341 | CU21: 643.14164 | CV21: 1583.7581 | CW21: 3444157.9 | CX21: 3444157.9
A22: =YEAR($B22) -> 2021 | B22: =ROUNDUP(MONTH($B22)/3, 0) -> 3 | C22: 44409 | D22: 6056.4972 | E22: 29048.512 | F22: 13332.208 | G22: 3233.0965 | H22: 4138.3266 | I22: 114586.3 | J22: 1347.7057 | K22: 97713.862 | L22: 322175.05 | M22: 446.43979 | N22: 4263.6649 | O22: 2882.2647 | P22: 272.80363 | Q22: 62.73402 | R22: 73838.053 | S22: 2706.922 | T22: 49091.771 | U22: 11666.64 | V22: 14434.547 | W22: 11488.113 | X22: 36089.849 | Y22: 3953.216 | Z22: 4837.8778 | AA22: 165.699 | AB22: 2160.4197 | AC22: 11450.434 | AD22: 1513093.1 | AE22: 10810.046 | AF22: 13039.103 | AG22: 38892.067 | AH22: 3542.8229 | AI22: 11870.652 | AJ22: 44079.981 | AK22: 16049.059 | AL22: 5347.0868 | AM22: 0.36595 | AN22: 44.9395 | AO22: 55621.149 | AP22: 176633.24 | AQ22: 8655.5986 | AR22: 8149.7284 | AS22: 4139.763 | AT22: 686.88757 | AU22: 3923.1501 | AV22: 5.8961 | AW22: 48.58111 | AX22: 148.31189 | AY22: 20941.421 | AZ22: 2446.211 | BA22: 0 | BB22: 0 | BC22: 1424.0869 | BD22: 268.06692 | BE22: 5874.0354 | BF22: 1250.7621 | BG22: 1104.4815 | BH22: 239.15478 | BI22: 1181.1656 | BJ22: 4057.487 | BK22: 6148.4613 | BL22: 15798.532 | BM22: 28104.076 | BN22: 7355.8209 | BO22: 3117.8351 | BP22: 1021.6078 | BQ22: 12.45716 | BR22: 3.04598 | BS22: 4412.095 | BT22: 7267.6478 | BU22: 19021.491 | BV22: 225795.94 | BW22: 49117.047 | BX22: 28577.014 | BY22: 26613.598 | BZ22: 131.58416 | CA22: 38184.047 | CB22: 739.25436 | CC22: 222.49211 | CD22: 0.7659 | CE22: 169.31054 | CF22: 6313.8852 | CG22: 4512.5518 | CH22: 40207.911 | CI22: 53682.171 | CJ22: 162.31276 | CK22: 47047.606 | CL22: 33303.516 | CM22: 2044.541 | CN22: 8695.4864 | CO22: 79.89765 | CP22: 1.965 | CQ22: 2381.7671 | CR22: 15943.514 | CS22: 2715.7558 | CT22: 9972.104 | CU22: 95.899 | CV22: 1156.5033 | CW22: 3465142.9 | CX22: 3465142.9
A23: =YEAR($B23) -> 2021 | B23: =ROUNDUP(MONTH($B23)/3, 0) -> 3 | C23: 44440 | D23: 11653.719 | E23: 27030.913 | F23: 9192.2748 | G23: 2184.0385 | H23: 3695.1896 | I23: 97506.452 | J23: 2078.2528 | K23: 104837.94 | L23: 268316.56 | M23: 551.77448 | N23: 5400.0057 | O23: 2988.6 | P23: 400.37579 | Q23: 145.53475 | R23: 68409.515 | S23: 3311.7441 | T23: 48530.611 | U23: 11452.663 | V23: 15338.523 | W23: 11260.567 | X23: 44504.264 | Y23: 4494.2013 | Z23: 3609.5471 | AA23: 443.207 | AB23: 1556.6929 | AC23: 2855.0815 | AD23: 1854123.2 | AE23: 10887.134 | AF23: 12222.554 | AG23: 37749.632 | AH23: 5140.8665 | AI23: 9644.753 | AJ23: 43696.758 | AK23: 14669.93 | AL23: 4038.3875 | AM23: 28.962 | AN23: 23.56136 | AO23: 54995.309 | AP23: 160172.68 | AQ23: 11205.824 | AR23: 7450.7234 | AS23: 2826.6029 | AT23: 609.01315 | AU23: 5080.7023 | AV23: 23.91032 | AW23: 79.23076 | AX23: 185.95111 | AY23: 22049.566 | AZ23: 4320.8981 | BA23: 5.2888 | BB23: 0 | BC23: 2085.0203 | BD23: 277.60456 | BE23: 6712.5064 | BF23: 1594.8882 | BG23: 1843.3326 | BH23: 30.15602 | BI23: 1214.4347 | BJ23: 3211.3144 | BK23: 7121.8406 | BL23: 16130.353 | BM23: 29593.37 | BN23: 5621.6276 | BO23: 2523.1015 | BP23: 878.32676 | BQ23: 68.30218 | BR23: 6.34178 | BS23: 3995.7604 | BT23: 8028.5862 | BU23: 16320.442 | BV23: 287659.16 | BW23: 117713.27 | BX23: 21700.099 | BY23: 24214.575 | BZ23: 8.81186 | CA23: 33241.123 | CB23: 52.0468 | CC23: 10.95446 | CD23: 69.45593 | CE23: 272.01442 | CF23: 5854.2959 | CG23: 3783.8872 | CH23: 43117.94 | CI23: 55346.858 | CJ23: 45.06392 | CK23: 29579.44 | CL23: 7964.5285 | CM23: 42.87774 | CN23: 7662.2828 | CO23: 190.81821 | CP23: 0.5833 | CQ23: 1480.6206 | CR23: 12661.077 | CS23: 3893.1095 | CT23: 13593.669 | CU23: 154.3863 | CV23: 1685.6129 | CW23: 3792235.5 | CX23: 3792235.5
A24: =YEAR($B24) -> 2021 | B24: =ROUNDUP(MONTH($B24)/3, 0) -> 4 | C24: 44471 | D24: 21132.636 | E24: 29614.429 | F24: 10833.756 | G24: 1805.2683 | H24: 3806.8603 | I24: 149379.36 | J24: 1416.2384 | K24: 118999.77 | L24: 327953.17 | M24: 65.44732 | N24: 7052.059 | O24: 2928.706 | P24: 85.00546 | Q24: 74.89476 | R24: 58170.081 | S24: 3167.5924 | T24: 42854.631 | U24: 11155.675 | V24: 13591.927 | W24: 8348.1748 | X24: 34452.739 | Y24: 5463.4822 | Z24: 4115.2892 | AA24: 5.2629 | AB24: 2006.0284 | AC24: 4365.1464 | AD24: 1890737.8 | AE24: 8495.9377 | AF24: 12898.763 | AG24: 30234.404 | AH24: 2836.1357 | AI24: 9209.7325 | AJ24: 41384.746 | AK24: 12149.903 | AL24: 4923.0022 | AM24: 0 | AN24: 4.87159 | AO24: 58729.669 | AP24: 194209.42 | AQ24: 8835.9271 | AR24: 7678.8815 | AS24: 5439.1775 | AT24: 1055.4007 | AU24: 3603.2514 | AV24: 0.85528 | AW24: 87.03123 | AX24: 163.57084 | AY24: 22205.179 | AZ24: 3681.048 | BA24: 0 | BB24: 3.34023 | BC24: 2193.5313 | BD24: 349.677 | BE24: 6427.1304 | BF24: 908.565 | BG24: 1007.5264 | BH24: 85.86686 | BI24: 1502.0552 | BJ24: 4025.8535 | BK24: 7184.7463 | BL24: 20317.781 | BM24: 28979.331 | BN24: 5051.522 | BO24: 3650.0056 | BP24: 892.64892 | BQ24: 6.21678 | BR24: 5.92437 | BS24: 4649.9567 | BT24: 7552.97 | BU24: 10357.759 | BV24: 242301.26 | BW24: 12692.887 | BX24: 20080.542 | BY24: 24359.156 | BZ24: 1.96685 | CA24: 44475.217 | CB24: 161.00628 | CC24: 2.49346 | CD24: 17.879 | CE24: 103.37065 | CF24: 5749.0859 | CG24: 4356.16 | CH24: 34947.394 | CI24: 56738.851 | CJ24: 105.13535 | CK24: 26023.775 | CL24: 1400.2397 | CM24: 691.678 | CN24: 7488.0963 | CO24: 103.12541 | CP24: 186.99966 | CQ24: 1006.1046 | CR24: 15849.697 | CS24: 2864.8373 | CT24: 10089.285 | CU24: 97.34752 | CV24: 656.93604 | CW24: 3799111.3 | CX24: 3799111.3
A25: =YEAR($B25) -> 2021 | B25: =ROUNDUP(MONTH($B25)/3, 0) -> 4 | C25: 44501 | D25: 3196.9363 | E25: 27618.698 | F25: 11758.717 | G25: 1741.8106 | H25: 4120.1802 | I25: 143428.16 | J25: 2056.207 | K25: 125686.49 | L25: 316349.68 | M25: 211.0102 | N25: 5878.1253 | O25: 3528.7817 | P25: 179.1152 | Q25: 16.535 | R25: 56959.403 | S25: 3992.1531 | T25: 58422.095 | U25: 11620.311 | V25: 13207.605 | W25: 10139.083 | X25: 44459.158 | Y25: 4364.0289 | Z25: 4705.8481 | AA25: 7.507 | AB25: 2259.9182 | AC25: 16259.509 | AD25: 2062251.5 | AE25: 13742.538 | AF25: 10942.672 | AG25: 33545.741 | AH25: 9012.4433 | AI25: 9677.5488 | AJ25: 51921.331 | AK25: 18084.329 | AL25: 5551.4325 | AM25: 0.76067 | AN25: 19.98632 | AO25: 53128.369 | AP25: 174438.7 | AQ25: 10939.05 | AR25: 7605.8468 | AS25: 5574.6421 | AT25: 692.17801 | AU25: 3865.6572 | AV25: 15.48823 | AW25: 180.87913 | AX25: 371.2679 | AY25: 25428.394 | AZ25: 3757.6655 | BA25: 0 | BB25: 0 | BC25: 2695.7143 | BD25: 272.48794 | BE25: 5125.0996 | BF25: 968.97936 | BG25: 946.80561 | BH25: 114.6658 | BI25: 1131.4416 | BJ25: 3467.0216 | BK25: 9856.7547 | BL25: 19306.917 | BM25: 32376.188 | BN25: 7584.9762 | BO25: 3328.7764 | BP25: 1097.5648 | BQ25: 183.98223 | BR25: 7.8132 | BS25: 4623.1688 | BT25: 7412.4308 | BU25: 14700.774 | BV25: 307040.2 | BW25: 81324.84 | BX25: 23557.651 | BY25: 25872.178 | BZ25: 8.41 | CA25: 44708.701 | CB25: 4.40294 | CC25: 54.28696 | CD25: 19.7919 | CE25: 180.92793 | CF25: 6608.6989 | CG25: 3751.8592 | CH25: 30328.513 | CI25: 60283.018 | CJ25: 17.62078 | CK25: 33198.917 | CL25: 4032.2781 | CM25: 1567.688 | CN25: 7576.7343 | CO25: 151.38415 | CP25: 9.51054 | CQ25: 0 | CR25: 14537.182 | CS25: 3246.0998 | CT25: 18737.779 | CU25: 257.95498 | CV25: 610.94181 | CW25: 4155804.7 | CX25: 4155804.7
A26: =YEAR($B26) -> 2021 | B26: =ROUNDUP(MONTH($B26)/3, 0) -> 4 | C26: 44531 | D26: 26618.86 | E26: 15983.784 | F26: 14657.75 | G26: 2053.3803 | H26: 4807.0825 | I26: 164464.75 | J26: 2593.9327 | K26: 90006.402 | L26: 376919.2 | M26: 717.71226 | N26: 6267.7801 | O26: 4159.8986 | P26: 345.08568 | Q26: 39.66629 | R26: 57454.789 | S26: 2538.4088 | T26: 56977.151 | U26: 10711.076 | V26: 16735.684 | W26: 10989.785 | X26: 43173.56 | Y26: 4931.9262 | Z26: 5406.6026 | AA26: 25.00286 | AB26: 2489.1661 | AC26: 33684.684 | AD26: 2297288.1 | AE26: 11023.088 | AF26: 17647.284 | AG26: 44899.673 | AH26: 2343.8498 | AI26: 11960.353 | AJ26: 49126.268 | AK26: 15705.088 | AL26: 4188.8682 | AM26: 0.8766 | AN26: 18.3193 | AO26: 32301.698 | AP26: 189271.43 | AQ26: 11607.808 | AR26: 6236.6794 | AS26: 5626.3862 | AT26: 708.01733 | AU26: 4555.8672 | AV26: 7.81491 | AW26: 97.78601 | AX26: 498.71795 | AY26: 22821.346 | AZ26: 4585.3006 | BA26: 0 | BB26: 0 | BC26: 2320.518 | BD26: 400.4186 | BE26: 6364.668 | BF26: 1037.6052 | BG26: 1696.4279 | BH26: 15.43939 | BI26: 1038.8229 | BJ26: 3357.1773 | BK26: 6349.9186 | BL26: 17374.084 | BM26: 32083.858 | BN26: 5309.8228 | BO26: 3737.1964 | BP26: 1511.9786 | BQ26: 10.5148 | BR26: 3.65421 | BS26: 5177.1202 | BT26: 9155.329 | BU26: 18212.054 | BV26: 377190.32 | BW26: 77264.582 | BX26: 21421.464 | BY26: 33062.03 | BZ26: 7.28101 | CA26: 56871.41 | CB26: 112.08162 | CC26: 0.18852 | CD26: 18.48282 | CE26: 126.86158 | CF26: 7400.286 | CG26: 4518.0087 | CH26: 40507.279 | CI26: 56650.191 | CJ26: 46.73409 | CK26: 27071.742 | CL26: 2162.6682 | CM26: 133.5605 | CN26: 8779.7743 | CO26: 42.16043 | CP26: 2.78644 | CQ26: 3.8745 | CR26: 12589.19 | CS26: 3655.1171 | CT26: 11369.173 | CU26: 428.01832 | CV26: 685.24705 | CW26: 4544550.9 | CX26: 4544550.9
A27: =YEAR($B27) -> 2022 | B27: =ROUNDUP(MONTH($B27)/3, 0) -> 1 | C27: 44562 | D27: 35463.858 | E27: 14720.698 | F27: 9852.4883 | G27: 926.37817 | H27: 2913.7775 | I27: 141635.11 | J27: 2076.7834 | K27: 100970.06 | L27: 332201.37 | M27: 46.25455 | N27: 7182.3324 | O27: 3074.4621 | P27: 1094.6331 | Q27: 110.73953 | R27: 54349.084 | S27: 2143.6982 | T27: 45770.916 | U27: 8881.223 | V27: 8442.5836 | W27: 7080.4039 | X27: 27088.687 | Y27: 3853.381 | Z27: 3626.3248 | AA27: 150.725 | AB27: 2301.845 | AC27: 18592.178 | AD27: 2044351.9 | AE27: 9492.6275 | AF27: 9532.2387 | AG27: 24802.28 | AH27: 3553.1382 | AI27: 6577.4268 | AJ27: 32857.635 | AK27: 11923.719 | AL27: 4402.7045 | AM27: 0 | AN27: 0 | AO27: 31668.506 | AP27: 166726.06 | AQ27: 6710.9301 | AR27: 5039.0165 | AS27: 3541.6709 | AT27: 389.6723 | AU27: 2944.2152 | AV27: 0.0165 | AW27: 152.10622 | AX27: 220.80604 | AY27: 19264.109 | AZ27: 3191.2479 | BA27: 0 | BB27: 0 | BC27: 1164.0971 | BD27: 144.91605 | BE27: 4865.277 | BF27: 713.86572 | BG27: 845.07013 | BH27: 6.16347 | BI27: 546.93627 | BJ27: 4533.3235 | BK27: 5447.9702 | BL27: 16737.305 | BM27: 19308.957 | BN27: 4708.7867 | BO27: 1797.94 | BP27: 992.59837 | BQ27: 179.70108 | BR27: 8.1935 | BS27: 2575.2641 | BT27: 5348.6749 | BU27: 10505.932 | BV27: 190348.59 | BW27: 65414.488 | BX27: 20189.365 | BY27: 28293.202 | BZ27: 0.372 | CA27: 54237.017 | CB27: 989.47415 | CC27: 36.7563 | CD27: 3.6951 | CE27: 139.29383 | CF27: 4095.1889 | CG27: 2989.3795 | CH27: 27743.928 | CI27: 40885.702 | CJ27: 54.28572 | CK27: 27744.821 | CL27: 1922.5619 | CM27: 2903.4127 | CN27: 6524.1383 | CO27: 199.3967 | CP27: 1.53734 | CQ27: 0 | CR27: 10458.209 | CS27: 3353.8084 | CT27: 10009.151 | CU27: 45.32 | CV27: 703.10092 | CW27: 3801609.2 | CX27: 3801609.2
A28: =YEAR($B28) -> 2022 | B28: =ROUNDUP(MONTH($B28)/3, 0) -> 1 | C28: 44593 | D28: 33618.497 | E28: 14824.723 | F28: 10455.145 | G28: 962.81287 | H28: 4264.1285 | I28: 259746.61 | J28: 2605.3555 | K28: 123090.83 | L28: 383477.5 | M28: 1059.4663 | N28: 4976.4543 | O28: 4810.1077 | P28: 40.70456 | Q28: 6.75129 | R28: 89770.389 | S28: 3773.575 | T28: 42565.276 | U28: 10105.178 | V28: 13264.083 | W28: 9164.0006 | X28: 38796.786 | Y28: 2470.4485 | Z28: 3741.9969 | AA28: 38.9708 | AB28: 1653.5385 | AC28: 8269.4318 | AD28: 1992883.2 | AE28: 12203.904 | AF28: 12983.238 | AG28: 30476.692 | AH28: 5903.3428 | AI28: 10604.579 | AJ28: 41251.143 | AK28: 17792.447 | AL28: 3952.7464 | AM28: 0 | AN28: 20.3915 | AO28: 38746.202 | AP28: 175293.44 | AQ28: 8973.6304 | AR28: 3944.2586 | AS28: 4396.3304 | AT28: 528.39932 | AU28: 3280.7335 | AV28: 23.2593 | AW28: 111.54876 | AX28: 265.04419 | AY28: 25121.437 | AZ28: 3246.6229 | BC28: 1498.5024 | BD28: 144.42404 | BE28: 5370.5431 | BF28: 642.33596 | BG28: 1377.0064 | BH28: 97.51544 | BI28: 1130.0709 | BJ28: 3761.2713 | BK28: 6196.1877 | BL28: 17408.058 | BM28: 23502.2 | BN28: 7975.0139 | BO28: 2691.9246 | BP28: 1107.4189 | BQ28: 179.68314 | BR28: 1.92 | BS28: 4665.1092 | BT28: 8134.8284 | BU28: 11106.998 | BV28: 268881.46 | BW28: 65957.668 | BX28: 21752.1 | BY28: 29177.567 | BZ28: 23.85058 | CA28: 60344.881 | CB28: 367.53916 | CC28: 0.10009 | CD28: 18.8046 | CE28: 80.25316 | CF28: 5583.4793 | CG28: 3638.3216 | CH28: 36936.306 | CI28: 54444.986 | CJ28: 37.26401 | CK28: 26173.36 | CL28: 33199.427 | CM28: 1485.5566 | CN28: 10000.047 | CO28: 71.22589 | CP28: 1.342 | CQ28: 77.3332 | CR28: 14515.213 | CS28: 3204.5101 | CT28: 14638.461 | CU28: 1334.7672 | CV28: 705.63642 | CW28: 4209197.8 | CX28: 4209197.8
A29: =YEAR($B29) -> 2022 | B29: =ROUNDUP(MONTH($B29)/3, 0) -> 1 | C29: 44621 | D29: 50298.778 | E29: 15923.364 | F29: 9864.144 | G29: 1347.8425 | H29: 6454.2205 | I29: 223653.38 | J29: 2758.2886 | K29: 104377.57 | L29: 412235.77 | M29: 779.62386 | N29: 6510.4851 | O29: 3844.3993 | P29: 909.38925 | Q29: 216.30581 | R29: 97269.911 | S29: 2088.1544 | T29: 54624.164 | U29: 11870.717 | V29: 16915.21 | W29: 12590.734 | X29: 51191.886 | Y29: 4307.5538 | Z29: 5521.5523 | AA29: 214.35377 | AB29: 2205.9566 | AC29: 20298.58 | AD29: 2452788.8 | AE29: 16709.618 | AF29: 15544.768 | AG29: 36427.951 | AH29: 5815.6497 | AI29: 10995.632 | AJ29: 46613.351 | AK29: 19436.9 | AL29: 4750.4421 | AM29: 2.28201 | AN29: 71.90813 | AO29: 48098.201 | AP29: 200651.77 | AQ29: 10362.684 | AR29: 5181.6531 | AS29: 5901.4169 | AT29: 891.61248 | AU29: 4228.5379 | AV29: 105.9523 | AW29: 94.91142 | AX29: 184.39576 | AY29: 32181.456 | AZ29: 3227.9774 | BA29: 0.14785 | BB29: 15.9974 | BC29: 2146.7236 | BD29: 82.44623 | BE29: 7381.2226 | BF29: 1336.8614 | BG29: 1073.6161 | BH29: 59.41146 | BI29: 1439.6706 | BJ29: 5030.4071 | BK29: 5353.5417 | BL29: 20784.971 | BM29: 32558.806 | BN29: 9220.3303 | BO29: 3920.274 | BP29: 1247.1036 | BQ29: 3.93305 | BR29: 4.33627 | BS29: 4848.8004 | BT29: 7768.5307 | BU29: 14673.965 | BV29: 251884.18 | BW29: 70376.465 | BX29: 27777.036 | BY29: 27195.255 | BZ29: 33.77739 | CA29: 59430.669 | CB29: 0 | CC29: 58.23177 | CD29: 25.63002 | CE29: 288.44406 | CF29: 7156.176 | CG29: 5292.6291 | CH29: 44192.709 | CI29: 52178.455 | CJ29: 405.59235 | CK29: 31609 | CL29: 1446.0192 | CM29: 182.2811 | CN29: 10710.19 | CO29: 41.70432 | CP29: 0.09102 | CQ29: 61.585 | CR29: 15013.81 | CS29: 2960.609 | CT29: 13465.725 | CU29: 111.76576 | CV29: 820.35007 | CW29: 4780209.7 | CX29: 4780209.7
A30: =YEAR($B30) -> 2022 | B30: =ROUNDUP(MONTH($B30)/3, 0) -> 2 | C30: 44652 | D30: 32387.661 | E30: 7448.1019 | F30: 11282.255 | G30: 1330.0705 | H30: 4744.313 | I30: 188739.86 | J30: 2473.3798 | K30: 145770.98 | L30: 327940.15 | M30: 120.82649 | N30: 7640.9538 | O30: 3852.0877 | P30: 125.36203 | Q30: 149.49734 | R30: 178114.53 | S30: 1860.7354 | T30: 56716.467 | U30: 8392.6435 | V30: 13446.795 | W30: 11209.966 | X30: 32289.571 | Y30: 3573.5185 | Z30: 5633.996 | AA30: 309.06252 | AB30: 1878.957 | AC30: 5884.8338 | AD30: 3271666.7 | AE30: 9296.1158 | AF30: 15829.211 | AG30: 31097.241 | AH30: 6741.4446 | AI30: 9221.7049 | AJ30: 40076.919 | AK30: 18985.596 | AL30: 3911.9357 | AM30: 2.615 | AN30: 12.17693 | AO30: 41019.745 | AP30: 144260.89 | AQ30: 8416.2325 | AR30: 5343.1061 | AS30: 4567.7096 | AT30: 726.4405 | AU30: 4456.1182 | AV30: 9.52357 | AW30: 117.5414 | AX30: 137.41927 | AY30: 30487.801 | AZ30: 2289.8807 | BA30: 0 | BB30: 11.172 | BC30: 2152.4411 | BD30: 43.78787 | BE30: 6109.5141 | BF30: 1152.7557 | BG30: 1188.4827 | BH30: 112.04301 | BI30: 1115.6792 | BJ30: 3777.5333 | BK30: 5800.6178 | BL30: 17250.095 | BM30: 24863.543 | BN30: 6155.7367 | BO30: 3552.574 | BP30: 1128.9876 | BQ30: 14.84529 | BR30: 3.85926 | BS30: 4372.3239 | BT30: 7062.5198 | BU30: 15590.291 | BV30: 255165.98 | BW30: 121676.04 | BX30: 24853.841 | BY30: 31232.497 | BZ30: 17.33066 | CA30: 56880.785 | CB30: 0 | CC30: 0 | CD30: 0 | CE30: 91.29108 | CF30: 5042.3994 | CG30: 3671.9326 | CH30: 33247.785 | CI30: 52566.996 | CJ30: 136.91333 | CK30: 31849.031 | CL30: 3081.3938 | CM30: 259.312 | CN30: 8614.6235 | CO30: 46.38571 | CP30: 0 | CQ30: 1759.8624 | CR30: 11772.763 | CS30: 3838.2275 | CT30: 10397.14 | CU30: 20.55966 | CV30: 858.80029 | CW30: 5460531.3 | CX30: 5460531.3
A31: =YEAR($B31) -> 2022 | B31: =ROUNDUP(MONTH($B31)/3, 0) -> 2 | C31: 44682 | D31: 36362.941 | E31: 15432.364 | F31: 12410.438 | G31: 2071.997 | H31: 4066.2499 | I31: 253341.51 | J31: 2383.3416 | K31: 133735.35 | L31: 275625.67 | M31: 456.08751 | N31: 8521.7152 | O31: 4373.0872 | P31: 144.45181 | Q31: 121.33607 | R31: 135447.3 | S31: 2517.5655 | T31: 44781.769 | U31: 10578.735 | V31: 15463.738 | W31: 11312.459 | X31: 48354.129 | Y31: 5016.6037 | Z31: 5230.2014 | AA31: 1349.0733 | AB31: 2194.8229 | AC31: 17786.867 | AD31: 2398280.9 | AE31: 20769.357 | AF31: 16783.912 | AG31: 33951.301 | AH31: 19505.495 | AI31: 11024.556 | AJ31: 44844.06 | AK31: 19136.462 | AL31: 4165.5206 | AM31: 0.438 | AN31: 47.16394 | AO31: 43734.015 | AP31: 172291.07 | AQ31: 9316.2744 | AR31: 3967.1583 | AS31: 5645.9378 | AT31: 460.13075 | AU31: 4588.6154 | AV31: 0.86233 | AW31: 105.52217 | AX31: 236.55095 | AY31: 34471.133 | AZ31: 3710.7714 | BA31: 0 | BB31: 0.90946 | BC31: 1668.5276 | BD31: 61.07864 | BE31: 6074.5215 | BF31: 1117.1751 | BG31: 1028.8797 | BH31: 243.42105 | BI31: 1346.8773 | BJ31: 4175.5802 | BK31: 6378.8187 | BL31: 18967.358 | BM31: 28102.332 | BN31: 6610.4073 | BO31: 3535.1318 | BP31: 1020.5086 | BQ31: 62.24151 | BR31: 7.85114 | BS31: 5166.2703 | BT31: 8372.6738 | BU31: 12148.452 | BV31: 275799.49 | BW31: 89580.639 | BX31: 20316.87 | BY31: 33184.547 | BZ31: 0 | CA31: 68548.005 | CB31: 9.9144 | CC31: 2.135 | CD31: 20.53226 | CE31: 165.66502 | CF31: 6112.787 | CG31: 4343.2193 | CH31: 40260.07 | CI31: 47537.864 | CJ31: 163.03008 | CK31: 23434.063 | CL31: 3928.6794 | CM31: 1296.4727 | CN31: 8448.316 | CO31: 113.05221 | CP31: 1.89146 | CQ31: 0 | CR31: 16581.13 | CS31: 3218.9321 | CT31: 15653.665 | CU31: 1016.215 | CV31: 577.34406 | CW31: 4662520.5 | CX31: 4662520.5
A32: =YEAR($B32) -> 2022 | B32: =ROUNDUP(MONTH($B32)/3, 0) -> 2 | C32: 44713 | D32: 15047.712 | E32: 12134.224 | F32: 10960.113 | G32: 1583.0494 | H32: 5122.185 | I32: 174915.14 | J32: 1789.585 | K32: 154499.19 | L32: 369007.84 | M32: 60.90911 | N32: 8775.8615 | O32: 2887.3609 | P32: 1489.5809 | Q32: 112.02041 | R32: 140203.9 | S32: 1014.7197 | T32: 48652.442 | U32: 11982.967 | V32: 18131.833 | W32: 14436.712 | X32: 50283.784 | Y32: 5341.1594 | Z32: 6709.0207 | AA32: 1502.847 | AB32: 2089.6324 | AC32: 8259.3895 | AD32: 3221138.1 | AE32: 16064.422 | AF32: 17893.974 | AG32: 35407.7 | AH32: 6520.8164 | AI32: 10648.791 | AJ32: 42805.21 | AK32: 20672.7 | AL32: 6067.8763 | AM32: 0.72535 | AN32: 17.32683 | AO32: 58228.056 | AP32: 156211.98 | AQ32: 10062.571 | AR32: 4289.7021 | AS32: 4878.6947 | AT32: 934.83524 | AU32: 4175.1092 | AV32: 9.691 | AW32: 58.38856 | AX32: 217.42552 | AY32: 32693.948 | AZ32: 3422.7844 | BA32: 0 | BB32: 0.18936 | BC32: 1909.1775 | BD32: 90.65172 | BE32: 6847.0778 | BF32: 929.50692 | BG32: 1389.3612 | BH32: 32.20277 | BI32: 1452.8109 | BJ32: 5589.9925 | BK32: 3620.6626 | BL32: 18938.335 | BM32: 26405.868 | BN32: 8665.666 | BO32: 3569.1525 | BP32: 1249.3503 | BQ32: 117.77406 | BR32: 0.71627 | BS32: 4750.9217 | BT32: 7943.8587 | BU32: 16448.543 | BV32: 200499.14 | BW32: 143707.2 | BX32: 27662.3 | BY32: 32163.197 | BZ32: 48.86269 | CA32: 50442.987 | CB32: 869.27854 | CC32: 0.2398 | CD32: 16.55202 | CE32: 163.60256 | CF32: 6638.1503 | CG32: 4935.1923 | CH32: 47517.128 | CI32: 64798.602 | CJ32: 138.05075 | CK32: 38534.09 | CL32: 1518.416 | CM32: 314.91 | CN32: 10096.973 | CO32: 34.58605 | CP32: 0 | CQ32: 1205.5115 | CR32: 17357.89 | CS32: 3998.6311 | CT32: 14798.355 | CU32: 119.44816 | CV32: 671.42532 | CW32: 5497616.5 | CX32: 5497616.5
A33: =YEAR($B33) -> 2022 | B33: =ROUNDUP(MONTH($B33)/3, 0) -> 3 | C33: 44743 | D33: 1477.3434 | E33: 14978.823 | F33: 13017.691 | G33: 1545.559 | H33: 5243.7351 | I33: 146767.56 | J33: 1884.1726 | K33: 92949.944 | L33: 394622.52 | M33: 34.41798 | N33: 8819.0629 | O33: 3419.8251 | P33: 81.43145 | Q33: 106.97864 | R33: 127022.55 | S33: 4144.402 | T33: 44948.214 | U33: 11458.448 | V33: 15106.5 | W33: 11937.931 | X33: 45666.766 | Y33: 4373.077 | Z33: 7931.419 | AA33: 901.44201 | AB33: 2212.9424 | AC33: 35535.059 | AD33: 3649554.3 | AE33: 16483.24 | AF33: 14346.922 | AG33: 36742.863 | AH33: 9608.4872 | AI33: 11981.564 | AJ33: 43946.53 | AK33: 20096.384 | AL33: 5410.9708 | AM33: 5.612 | AN33: 5.43948 | AO33: 55148.984 | AP33: 216109.11 | AQ33: 13387.498 | AR33: 3830.4758 | AS33: 4678.607 | AT33: 220.15704 | AU33: 3990.0265 | AV33: 3.2158 | AW33: 79.30624 | AX33: 419.36793 | AY33: 29248.563 | AZ33: 3876.645 | BA33: 0 | BB33: 0.8778 | BC33: 1721.3973 | BD33: 82.70263 | BE33: 6625.664 | BF33: 954.35315 | BG33: 1031.1692 | BH33: 379.35638 | BI33: 1015.9268 | BJ33: 3318.0033 | BK33: 3947.9417 | BL33: 17580.94 | BM33: 25478.271 | BN33: 6333.5399 | BO33: 3241.0088 | BP33: 1038.7422 | BQ33: 55.15355 | BR33: 14.47753 | BS33: 4187.8552 | BT33: 7651.2404 | BU33: 15930.531 | BV33: 312951.59 | BW33: 88009.95 | BX33: 18686.353 | BY33: 28598.866 | BZ33: 5.609 | CA33: 42707.917 | CB33: 67.32646 | CC33: 36.825 | CD33: 7.0969 | CE33: 143.95632 | CF33: 5226.7131 | CG33: 4259.7463 | CH33: 41876.291 | CI33: 53450.846 | CJ33: 169.1061 | CK33: 35913.525 | CL33: 3029.6054 | CM33: 6034.2788 | CN33: 8369.1379 | CO33: 68.80751 | CP33: 81.49872 | CQ33: 0 | CR33: 11572.605 | CS33: 3506.7916 | CT33: 11164.691 | CU33: 874.24783 | CV33: 917.152 | CW33: 5913681.8 | CX33: 5913681.8
A34: =YEAR($B34) -> 2022 | B34: =ROUNDUP(MONTH($B34)/3, 0) -> 3 | C34: 44774 | D34: 16924.06 | E34: 23625.216 | F34: 15138.874 | G34: 2806.0456 | H34: 6034.4787 | I34: 142231.42 | J34: 1696.9937 | K34: 112489.79 | L34: 323525.42 | M34: 79.43326 | N34: 5904.137 | O34: 3940.1858 | P34: 43.72077 | Q34: 76.92766 | R34: 50473.053 | S34: 5496.1575 | T34: 52553.152 | U34: 12926.625 | V34: 19242.361 | W34: 12333.815 | X34: 51636.691 | Y34: 6738.2024 | Z34: 6477.4127 | AA34: 10.198 | AB34: 2221.5256 | AC34: 15703.087 | AD34: 2225049.8 | AE34: 21922.392 | AF34: 20865.515 | AG34: 40209.63 | AH34: 6758.9749 | AI34: 10640.501 | AJ34: 54254.361 | AK34: 23394.257 | AL34: 7348.9825 | AM34: 0.05632 | AN34: 44.85328 | AO34: 55462.468 | AP34: 200090.36 | AQ34: 10010.683 | AR34: 3740.1942 | AS34: 4759.6898 | AT34: 709.63891 | AU34: 3797.6428 | AV34: 23.82871 | AW34: 67.42905 | AX34: 54.75165 | AY34: 32536.093 | AZ34: 3695.6104 | BA34: 0 | BB34: 0 | BC34: 2068.3745 | BD34: 101.74054 | BE34: 7154.4501 | BF34: 768.32818 | BG34: 1442.1559 | BH34: 58.11006 | BI34: 1283.1777 | BJ34: 4703.3768 | BK34: 8145.5685 | BL34: 14558.518 | BM34: 26872.96 | BN34: 7900.7051 | BO34: 4187.8579 | BP34: 1683.146 | BQ34: 116.54497 | BR34: 8.50507 | BS34: 4520.6376 | BT34: 9752.0087 | BU34: 16089.182 | BV34: 267405.84 | BW34: 86017.328 | BX34: 27679.475 | BY34: 22346.145 | BZ34: 23.7192 | CA34: 59608.457 | CB34: 13.38 | CC34: 1.99912 | CD34: 14.52285 | CE34: 181.90508 | CF34: 6638.3628 | CG34: 6116.6278 | CH34: 45866.22 | CI34: 52966.992 | CJ34: 382.40207 | CK34: 38022.131 | CL34: 964.68914 | CM34: 772.90997 | CN34: 7970.8417 | CO34: 11.84909 | CP34: 0.41 | CQ34: 351.75 | CR34: 14098.044 | CS34: 4048.6263 | CT34: 17823.846 | CU34: 318.92789 | CV34: 1907.2084 | CW34: 4388736.6 | CX34: 4388736.6
A35: =YEAR($B35) -> 2022 | B35: =ROUNDUP(MONTH($B35)/3, 0) -> 3 | C35: 44805 | D35: 24977.031 | E35: 24614.921 | F35: 12650.799 | G35: 2617.3527 | H35: 3724.4207 | I35: 125432.34 | J35: 1931.0164 | K35: 150369.32 | L35: 339103.65 | M35: 70.70367 | N35: 7495.4424 | O35: 4433.7292 | P35: 47.92142 | Q35: 139.95311 | R35: 73913.754 | S35: 1863.913 | T35: 58231.553 | U35: 11841.499 | V35: 19032.93 | W35: 12591.815 | X35: 51019.946 | Y35: 5679.4947 | Z35: 7648.2927 | AA35: 183.14923 | AB35: 2336.3394 | AC35: 25501.806 | AD35: 2590601 | AE35: 13268.203 | AF35: 20055.546 | AG35: 32493.525 | AH35: 12696.805 | AI35: 10446.016 | AJ35: 49012.347 | AK35: 22120.573 | AL35: 6962.8828 | AM35: 11.86409 | AN35: 127.09297 | AO35: 57588.896 | AP35: 160466.16 | AQ35: 13771.728 | AR35: 3842.2745 | AS35: 3660.9846 | AT35: 538.88225 | AU35: 5368.0947 | AV35: 28.88987 | AW35: 61.42456 | AX35: 116.24365 | AY35: 32140.915 | AZ35: 3807.0861 | BA35: 0 | BB35: 1.2891 | BC35: 2116.4651 | BD35: 101.44917 | BE35: 5659.8558 | BF35: 1133.6917 | BG35: 1181.3284 | BH35: 12.76208 | BI35: 1087.4077 | BJ35: 3892.1402 | BK35: 5981.5986 | BL35: 18607.431 | BM35: 22007.369 | BN35: 7764.7785 | BO35: 3792.2539 | BP35: 1316.2904 | BQ35: 38.41393 | BR35: 32.47598 | BS35: 4047.1933 | BT35: 8282.611 | BU35: 16988.248 | BV35: 251842.26 | BW35: 88807.397 | BX35: 22574.277 | BY35: 21914.463 | BZ35: 39.73208 | CA35: 75305.896 | CB35: 442.57231 | CC35: 0.344 | CD35: 8.31413 | CE35: 198.17279 | CF35: 5962.5647 | CG35: 4517.9178 | CH35: 41740.135 | CI35: 62404.016 | CJ35: 324.91292 | CK35: 40180.755 | CL35: 10167.92 | CM35: 208.912 | CN35: 7506.7499 | CO35: 22.67062 | CP35: 3.48363 | CQ35: 19.896 | CR35: 15384.422 | CS35: 1722.8768 | CT35: 15477.969 | CU35: 180.015 | CV35: 875.35197 | CW35: 4778519.6 | CX35: 4778519.6
A36: =YEAR($B36) -> 2022 | B36: =ROUNDUP(MONTH($B36)/3, 0) -> 4 | C36: 44835 | D36: 34686.167 | E36: 21286.983 | F36: 14351.045 | G36: 2015.8553 | H36: 5612.9978 | I36: 144035.81 | J36: 1800.2074 | K36: 106316.77 | L36: 323641.12 | M36: 57.3604 | N36: 5689.8644 | O36: 3000.1285 | P36: 258.90865 | Q36: 116.34215 | R36: 32617.228 | S36: 3780.5705 | T36: 59529.484 | U36: 10372.929 | V36: 15290.655 | W36: 12039.623 | X36: 56576.001 | Y36: 5033.3769 | Z36: 6468.0636 | AA36: 36.6115 | AB36: 2119.1031 | AC36: 13845.181 | AD36: 2183740.1 | AE36: 18222.193 | AF36: 13089.199 | AG36: 33110.032 | AH36: 6056.8544 | AI36: 10523.841 | AJ36: 44110.275 | AK36: 21685.703 | AL36: 7479.239 | AM36: 212.22235 | AN36: 172.23058 | AO36: 56558.157 | AP36: 144227.6 | AQ36: 10562.566 | AR36: 2784.0584 | AS36: 3538.9775 | AT36: 574.23182 | AU36: 3491.9802 | AV36: 2.63197 | AW36: 95.69465 | AX36: 79.36652 | AY36: 30742.919 | AZ36: 3380.8389 | BA36: 0 | BB36: 0.264 | BC36: 1723.6987 | BD36: 71.99735 | BE36: 5495.957 | BF36: 1285.4124 | BG36: 1288.5663 | BH36: 64.32229 | BI36: 1118.0329 | BJ36: 2894.2805 | BK36: 5247.8106 | BL36: 18866.899 | BM36: 25844.202 | BN36: 7000.4575 | BO36: 3818.9924 | BP36: 1303.4392 | BQ36: 11.05875 | BR36: 9.30887 | BS36: 4817.632 | BT36: 7758.9591 | BU36: 11498.694 | BV36: 290034.63 | BW36: 53037.272 | BX36: 24777.91 | BY36: 23778.817 | BZ36: 5.4037 | CA36: 53098.562 | CB36: 45.6 | CC36: 1939.1432 | CD36: 16.40484 | CE36: 75.01433 | CF36: 6883.2416 | CG36: 4313.0941 | CH36: 39500.655 | CI36: 56940.575 | CJ36: 57.228 | CK36: 35589.365 | CL36: 975.32148 | CM36: 444.2611 | CN36: 10665.501 | CO36: 118.65045 | CP36: 90.60236 | CQ36: 0 | CR36: 15626.166 | CS36: 3544.1724 | CT36: 15293.214 | CU36: 288.12843 | CV36: 904.05325 | CW36: 4213182.3 | CX36: 4213182.3
A37: =YEAR($B37) -> 2022 | B37: =ROUNDUP(MONTH($B37)/3, 0) -> 4 | C37: 44866 | D37: 13422.375 | E37: 16251.66 | F37: 10848.252 | G37: 2039.147 | H37: 4887.1857 | I37: 149848.44 | J37: 2456.31 | K37: 120862.45 | L37: 293141.45 | M37: 580.81472 | N37: 4470.5359 | O37: 3792.9456 | P37: 179.20837 | Q37: 121.43062 | R37: 67866.521 | S37: 1475.6295 | T37: 61754.23 | U37: 9946.13 | V37: 16087.335 | W37: 10891.036 | X37: 58604.302 | Y37: 7442.7787 | Z37: 6092.6549 | AA37: 312.00132 | AB37: 2569.3468 | AC37: 22097.137 | AD37: 2544083.4 | AE37: 17050.852 | AF37: 13798.924 | AG37: 37845.255 | AH37: 4276.9565 | AI37: 14114.017 | AJ37: 43527.438 | AK37: 21030.337 | AL37: 7157.4358 | AM37: 0 | AN37: 21.1216 | AO37: 41293.031 | AP37: 127457.5 | AQ37: 10399.995 | AR37: 3570.9571 | AS37: 4554.1533 | AT37: 730.98138 | AU37: 3933.8672 | AV37: 16.30197 | AW37: 122.86035 | AX37: 25.18623 | AY37: 29508.378 | AZ37: 3147.7586 | BA37: 0 | BB37: 0.74008 | BC37: 1694.6226 | BD37: 105.63152 | BE37: 6311.7775 | BF37: 1395.0829 | BG37: 1095.1522 | BH37: 80.04598 | BI37: 770.65928 | BJ37: 2906.5569 | BK37: 5000.7456 | BL37: 18611.912 | BM37: 27852.397 | BN37: 7118.4402 | BO37: 5038.0816 | BP37: 1414.4495 | BQ37: 47.37791 | BR37: 5.50117 | BS37: 5167.7931 | BT37: 7695.8894 | BU37: 14933.486 | BV37: 258848.66 | BW37: 55561.158 | BX37: 26496.266 | BY37: 25782.243 | BZ37: 12.64302 | CA37: 65476.516 | CB37: 0.42841 | CC37: 724.35437 | CD37: 4.45645 | CE37: 141.68775 | CF37: 5005.1301 | CG37: 4737.6265 | CH37: 46489.265 | CI37: 58115.538 | CJ37: 57.69 | CK37: 41355.1 | CL37: 9320.4884 | CM37: 193.21271 | CN37: 7223.0067 | CO37: 122.57993 | CP37: 15.58537 | CQ37: 589.1894 | CR37: 13720.331 | CS37: 3798.0738 | CT37: 13514.876 | CU37: 1298.962 | CV37: 688.21622 | CW37: 4562247.6 | CX37: 4562247.6
A38: =YEAR($B38) -> 2022 | B38: =ROUNDUP(MONTH($B38)/3, 0) -> 4 | C38: 44896 | D38: 26064.469 | E38: 12375.728 | F38: 21200.404 | G38: 3650.1913 | H38: 5664.2248 | I38: 132492.68 | J38: 3360.5058 | K38: 130361.16 | L38: 348771.02 | M38: 14.88757 | N38: 6602.1364 | O38: 4196.4486 | P38: 452.43185 | Q38: 117.8246 | R38: 50226.081 | S38: 2850.1544 | T38: 74385.707 | U38: 12753.724 | V38: 18812.066 | W38: 10655.3 | X38: 52215.169 | Y38: 6310.1615 | Z38: 6834.8344 | AA38: 825.02666 | AB38: 3630.5028 | AC38: 22961.916 | AD38: 2456611.3 | AE38: 10836.721 | AF38: 18071.663 | AG38: 33805.704 | AH38: 6275.8737 | AI38: 12481.689 | AJ38: 47064.397 | AK38: 19887.716 | AL38: 6651.4536 | AM38: 0.03901 | AN38: 56.65804 | AO38: 41933.036 | AP38: 135879.01 | AQ38: 12052.82 | AR38: 3446.3843 | AS38: 4596.027 | AT38: 577.96323 | AU38: 4202.3071 | AV38: 21.19144 | AW38: 104.55582 | AX38: 40.9551 | AY38: 32861.108 | AZ38: 3945.3466 | BA38: 0.06 | BB38: 0.005 | BC38: 2285.4911 | BD38: 86.22924 | BE38: 6132.4121 | BF38: 1234.1085 | BG38: 1226.1652 | BH38: 68.04656 | BI38: 1006.1393 | BJ38: 3444.2541 | BK38: 6127.1853 | BL38: 20228.673 | BM38: 25143.936 | BN38: 6353.8768 | BO38: 3824.1816 | BP38: 1450.9376 | BQ38: 84.59699 | BR38: 5.97801 | BS38: 3645.3752 | BT38: 8286.9352 | BU38: 14823.606 | BV38: 323684.68 | BW38: 73373.4 | BX38: 22401.123 | BY38: 26805.471 | BZ38: 26.93744 | CA38: 82005.264 | CB38: 26.84621 | CC38: 1315.66 | CD38: 4.36156 | CE38: 102.38195 | CF38: 5963.5068 | CG38: 3790.4721 | CH38: 45658.277 | CI38: 58844.631 | CJ38: 16.88436 | CK38: 31118.298 | CL38: 4903.0611 | CM38: 37.02733 | CN38: 7112.0208 | CO38: 22.52729 | CP38: 102.58264 | CQ38: 4170.0461 | CR38: 17098.887 | CS38: 2525.8245 | CT38: 15515.533 | CU38: 52.278 | CV38: 758.76081 | CW38: 4642083.6 | CX38: 4642083.6
A39: =YEAR($B39) -> 2023 | B39: =ROUNDUP(MONTH($B39)/3, 0) -> 1 | C39: 44927 | D39: 23926.183 | E39: 12908.983 | F39: 10941.2 | G39: 1777.1997 | H39: 5283.9728 | I39: 159105.05 | J39: 2522.0638 | K39: 53594.923 | L39: 250131.82 | M39: 26.83553 | N39: 4919.1666 | O39: 4059.8466 | P39: 247.80037 | Q39: 93.0199 | R39: 63628.918 | S39: 5451.8694 | T39: 54989.448 | U39: 7254.5145 | V39: 10198.826 | W39: 10223.742 | X39: 42551.8 | Y39: 4640.7448 | Z39: 5032.7101 | AA39: 2.80888 | AB39: 1731.769 | AC39: 27256.908 | AD39: 1986087.5 | AE39: 13266.937 | AF39: 9646.3747 | AG39: 21225.331 | AH39: 17524.254 | AI39: 6141.4477 | AJ39: 39026.201 | AK39: 17256.372 | AL39: 6203.3437 | AM39: 0 | AN39: 66.93897 | AO39: 33825.64 | AP39: 108354.06 | AQ39: 4965.8631 | AR39: 2190.6456 | AS39: 3761.2905 | AT39: 310.3871 | AU39: 3315.45 | AV39: 1.03549 | AW39: 50.26002 | AX39: 48.35803 | AY39: 28193.501 | AZ39: 2804.3648 | BA39: 0.53355 | BB39: 2.3468 | BC39: 472.38171 | BD39: 15.97133 | BE39: 4875.0162 | BF39: 670.60489 | BG39: 863.08959 | BH39: 72.33906 | BI39: 523.39794 | BJ39: 3884.9402 | BK39: 3029.4444 | BL39: 14474.632 | BM39: 15703.491 | BN39: 5434.976 | BO39: 2186.4833 | BP39: 813.70156 | BQ39: 120.97204 | BR39: 1.99176 | BS39: 3368.8996 | BT39: 5809.8789 | BU39: 11178.498 | BV39: 258153.47 | BW39: 105402.68 | BX39: 18940.917 | BY39: 25193.544 | BZ39: 24.53464 | CA39: 59909.171 | CB39: 1404.8207 | CC39: 204.69924 | CD39: 0.29826 | CE39: 152.90883 | CF39: 2712.6865 | CG39: 2690.5421 | CH39: 26276.428 | CI39: 45086.195 | CJ39: 29.26231 | CK39: 10646.509 | CL39: 413.74443 | CM39: 454.97772 | CN39: 5022.5191 | CO39: 27.05274 | CP39: 3.73496 | CQ39: 0 | CR39: 18209.336 | CS39: 2418.2404 | CT39: 8437.6009 | CU39: 10.252 | CV39: 1095.8305 | CW39: 3733193.2 | CX39: 3733193.2
A40: =YEAR($B40) -> 2023 | B40: =ROUNDUP(MONTH($B40)/3, 0) -> 1 | C40: 44958 | D40: 3887.0889 | E40: 14271.256 | F40: 11585.12 | G40: 2138.7252 | H40: 4648.5381 | I40: 225436.32 | J40: 3571.2044 | K40: 90430.657 | L40: 261153.29 | M40: 49.13674 | N40: 7729.1669 | O40: 4103.8752 | P40: 100.6499 | Q40: 60.78274 | R40: 80804.065 | S40: 2122.4802 | T40: 44454.871 | U40: 9614.7075 | V40: 16320.012 | W40: 11410.84 | X40: 43543.767 | Y40: 5036.1546 | Z40: 6087.6198 | AA40: 350.2396 | AB40: 1913.1878 | AC40: 13799.54 | AD40: 2314800.3 | AE40: 14668.146 | AF40: 11684.994 | AG40: 32798.149 | AH40: 9579.3548 | AI40: 10642.554 | AJ40: 51668.264 | AK40: 18383.533 | AL40: 7130.0105 | AM40: 0 | AN40: 37.51417 | AO40: 29455.381 | AP40: 119966.83 | AQ40: 9872.058 | AR40: 3371.4112 | AS40: 3212.285 | AT40: 543.11111 | AU40: 3532.9527 | AV40: 12.62216 | AW40: 103.40045 | AX40: 35.64594 | AY40: 27429.053 | AZ40: 3499.3138 | BA40: 0 | BB40: 1.75187 | BC40: 1915.1364 | BD40: 37.23621 | BE40: 4095.2963 | BF40: 709.90521 | BG40: 999.90047 | BH40: 144.47733 | BI40: 623.146 | BJ40: 3773.5639 | BK40: 5272.1387 | BL40: 17101.08 | BM40: 21358.576 | BN40: 4936.7972 | BO40: 2426.0112 | BP40: 1357.8333 | BQ40: 28.82052 | BR40: 6.13728 | BS40: 3519.1113 | BT40: 7832.6493 | BU40: 11608.584 | BV40: 269931.93 | BW40: 46409.513 | BX40: 16443.527 | BY40: 25414.653 | BZ40: 1.52141 | CA40: 93245.527 | CB40: 0.38002 | CC40: 481.19985 | CD40: 2.37454 | CE40: 179.9108 | CF40: 5689.9406 | CG40: 4551.3868 | CH40: 35538.879 | CI40: 50558.467 | CJ40: 24.856 | CK40: 26119.143 | CL40: 392.21548 | CM40: 132.256 | CN40: 6601.5406 | CO40: 44.82373 | CP40: 9.07244 | CQ40: 2717.6548 | CR40: 11222.32 | CS40: 2416.1362 | CT40: 13817.288 | CU40: 876.16891 | CV40: 1073.0192 | CW40: 4238694.1 | CX40: 4238694.1
... A50: =YEAR($B50) -> 2023 | B50: =ROUNDUP(MONTH($B50)/3, 0) -> 4 | C50: 45261 | D50: 29503.436 | E50: 10541.742 | F50: 7739.0464 | G50: 2404.0196 | H50: 5026.136 | I50: 165986.13 | J50: 3917.3098 | K50: 141556.89 | L50: 306637.15 | M50: 218.82732 | N50: 6481.8495 | O50: 4001.291 | P50: 70.83773 | Q50: 232.88634 | R50: 47999.696 | S50: 2006.4555 | T50: 55663.776 | U50: 12151.397 | V50: 14885.921 | W50: 15504.319 | X50: 55718.614 | Y50: 8310.0657 | Z50: 9367.8416 | AA50: 342.68615 | AB50: 2975.0048 | AC50: 12682.927 | AD50: 2337004.3 | AE50: 11498.588 | AF50: 14277.99 | AG50: 41053.853 | AH50: 3077.5524 | AI50: 11318.301 | AJ50: 54593.617 | AK50: 16720.565 | AL50: 5057.8659 | AM50: 3.60375 | AN50: 23.57461 | AO50: 45688.022 | AP50: 144332.79 | AQ50: 10134.059 | AR50: 3355.2892 | AS50: 5561.6625 | AT50: 550.75257 | AU50: 3459.5469 | AV50: 5.61375 | AW50: 145.03254 | AX50: 55.82103 | AY50: 26319.397 | AZ50: 2898.6032 | BA50: 0 | BB50: 6.606 | BC50: 1348.0222 | BD50: 136.28371 | BE50: 5920.4838 | BF50: 475.69399 | BG50: 957.87449 | BH50: 137.10419 | BI50: 676.07697 | BJ50: 2413.5909 | BK50: 5571.2028 | BL50: 17316.345 | BM50: 21099.374 | BN50: 6527.4541 | BO50: 4201.6506 | BP50: 1927.8024 | BQ50: 203.00076 | BR50: 16.90312 | BS50: 5040.4133 | BT50: 8111.1468 | BU50: 13312.623 | BV50: 330051.87 | BW50: 37732.714 | BX50: 23001.063 | BY50: 18340.088 | BZ50: 54.70191 | CA50: 53314.885 | CB50: 638.70553 | CC50: 33.41044 | CD50: 5.61896 | CE50: 279.8607 | CF50: 6956.338 | CG50: 3827.1117 | CH50: 49770.422 | CI50: 80512.432 | CJ50: 7.5581 | CK50: 31063.589 | CL50: 22426.066 | CM50: 103.738 | CN50: 7033.4485 | CO50: 13.72086 | CP50: 15.32515 | CQ50: 5.371 | CR50: 12830.083 | CS50: 2064.9599 | CT50: 11894.016 | CU50: 460.47926 | CV50: 833.1037 | CW50: 4447732.9 | CX50: 4447732.9
A51: =YEAR($B51) -> 2024 | B51: =ROUNDUP(MONTH($B51)/3, 0) -> 1 | C51: 45292 | D51: 17111.511 | E51: 6449.0962 | F51: 20008.963 | G51: 3520.3578 | H51: 3978.1759 | I51: 168251.14 | J51: 4206.5626 | K51: 154145.98 | L51: 231800.57 | M51: 47.12898 | N51: 6311.7206 | O51: 5757.2482 | P51: 742.22934 | Q51: 120.37297 | R51: 49600.414 | S51: 1548.1783 | T51: 50748.424 | U51: 11126.458 | V51: 12512.156 | W51: 14547.487 | X51: 27438 | Y51: 4989.9396 | Z51: 3766.2471 | AA51: 549.5296 | AB51: 2960.2694 | AC51: 25088.385 | AD51: 1758565.4 | AE51: 10783.333 | AF51: 13845.529 | AG51: 27035.483 | AH51: 4600.0247 | AI51: 9944.0153 | AJ51: 50557.094 | AK51: 15937.988 | AL51: 5541.7581 | AN51: 6.36054 | AO51: 39177.78 | AP51: 121064.07 | AQ51: 7418.5097 | AR51: 1845.0081 | AS51: 2669.4012 | AT51: 262.62351 | AU51: 4483.3139 | AW51: 84.6954 | AX51: 34.61718 | AY51: 26200.917 | AZ51: 3651.1056 | BB51: 1.95799 | BC51: 1162.8237 | BD51: 104.19298 | BE51: 4643.7763 | BF51: 383.20243 | BG51: 999.42111 | BH51: 193.63999 | BI51: 541.20473 | BJ51: 1863.2446 | BK51: 3514.3189 | BL51: 13318.936 | BM51: 12687.758 | BN51: 6882.7585 | BO51: 1977.1281 | BP51: 1024.3937 | BQ51: 125.70232 | BS51: 4111.8204 | BT51: 6802.6021 | BU51: 11658.753 | BV51: 279058.18 | BW51: 42033.734 | BX51: 14767.93 | BY51: 29082.145 | BZ51: 20.21762 | CA51: 59730.317 | CB51: 1027.8866 | CC51: 8.39328 | CE51: 162.94434 | CF51: 3700.4149 | CG51: 4429.1651 | CH51: 37059.118 | CI51: 71496.965 | CJ51: 51.05295 | CK51: 43841.469 | CL51: 1337.9364 | CM51: 122.804 | CN51: 7254.0422 | CO51: 5.35663 | CP51: 8.44403 | CQ51: 7.48716 | CR51: 11679.562 | CS51: 1377.2858 | CT51: 8898.3249 | CU51: 82.70896 | CV51: 846.89185 | CW51: 3621124 | CX51: 3621124
A52: =YEAR($B52) -> 2024 | B52: =ROUNDUP(MONTH($B52)/3, 0) -> 1 | C52: 45323 | D52: 14598.72 | E52: 7075.1845 | F52: 11500.741 | G52: 4029.8846 | H52: 4916.9629 | I52: 255049.76 | J52: 4011.4741 | K52: 160244.84 | L52: 258106.5 | M52: 29.35097 | N52: 8495.0528 | O52: 4682.5564 | P52: 91.17957 | Q52: 216.22138 | R52: 63503.624 | S52: 1250.7565 | T52: 58847.967 | U52: 19172.874 | V52: 14148.708 | W52: 15373.224 | X52: 41087.682 | Y52: 6069.6001 | Z52: 6280.9635 | AA52: 211.24309 | AB52: 5063.1983 | AC52: 5716.1659 | AD52: 1767110.1 | AE52: 14227.189 | AF52: 13902.997 | AG52: 32147.696 | AH52: 6096.2025 | AI52: 12175.575 | AJ52: 54860.889 | AK52: 19345.421 | AL52: 5443.8488 | AM52: 399.5664 | AN52: 31.89442 | AO52: 36188.872 | AP52: 134058.16 | AQ52: 8771.7942 | AR52: 2308.9898 | AS52: 4469.1394 | AT52: 641.28425 | AU52: 3769.8045 | AV52: 22.45098 | AW52: 111.32467 | AX52: 52.95983 | AY52: 28816.541 | AZ52: 3992.4757 | BB52: 0.24916 | BC52: 952.36811 | BD52: 148.60125 | BE52: 4970.453 | BF52: 1089.658 | BG52: 1362.7213 | BH52: 126.73234 | BI52: 670.08181 | BJ52: 2098.1995 | BK52: 5498.6053 | BL52: 18301.797 | BM52: 17639.451 | BN52: 6459.0067 | BO52: 3232.9165 | BP52: 1353.9244 | BQ52: 85.64972 | BR52: 7.891 | BS52: 5809.4874 | BT52: 8307.4782 | BU52: 13338.601 | BV52: 248400.01 | BW52: 37060.103 | BX52: 32251.805 | BY52: 25663.857 | BZ52: 7.97135 | CA52: 58809.091 | CB52: 336.59936 | CC52: 24.08734 | CD52: 8.89218 | CE52: 118.01888 | CF52: 5863.7579 | CG52: 2951.8662 | CH52: 52872.183 | CI52: 70686.339 | CJ52: 34.07264 | CK52: 29071.14 | CL52: 1480.1403 | CM52: 1002.0111 | CN52: 8105.5616 | CO52: 0.99634 | CP52: 1.00368 | CQ52: 1179.7736 | CR52: 12757.883 | CS52: 1372.7957 | CT52: 9588.6347 | CU52: 252.42345 | CV52: 876.52716 | CW52: 3810951.1 | CX52: 3810951.1
A53: =YEAR($B53) -> 2024 | B53: =ROUNDUP(MONTH($B53)/3, 0) -> 1 | C53: 45352 | D53: 47586.066 | E53: 7357.5973 | F53: 9244.3821 | G53: 3561.4233 | H53: 4538.2971 | I53: 223584.45 | J53: 3712.9497 | K53: 127680.57 | L53: 238506.48 | M53: 592.72145 | N53: 6016.2558 | O53: 5960.4847 | P53: 232.51148 | Q53: 150.7211 | R53: 70303.314 | S53: 2121.5573 | T53: 63213.812 | U53: 21492.893 | V53: 12799.092 | W53: 15489.296 | X53: 43818.665 | Y53: 4732.6899 | Z53: 6268.681 | AA53: 474.7717 | AB53: 2597.5252 | AC53: 18770.18 | AD53: 1880150.3 | AE53: 10132.193 | AF53: 14190.067 | AG53: 31530.171 | AH53: 7814.859 | AI53: 12479.073 | AJ53: 49383.925 | AK53: 21502.994 | AL53: 4502.933 | AM53: 0.07608 | AN53: 31.54485 | AO53: 30144.181 | AP53: 119223.43 | AQ53: 7659.2949 | AR53: 2649.3279 | AS53: 3533.9873 | AT53: 270.60631 | AU53: 4661.4342 | AV53: 7.178 | AW53: 97.29665 | AX53: 33.25968 | AY53: 31193.55 | AZ53: 4053.0783 | BB53: 1.322 | BC53: 985.40168 | BD53: 57.32017 | BE53: 5924.3741 | BF53: 637.45198 | BG53: 831.14671 | BH53: 378.64164 | BI53: 940.10476 | BJ53: 3162.8776 | BK53: 5606.6082 | BL53: 14608.056 | BM53: 18327.307 | BN53: 6692.5106 | BO53: 3308.4791 | BP53: 1003.3043 | BQ53: 300.12936 | BR53: 1.98441 | BS53: 4411.7168 | BT53: 7515.9432 | BU53: 12032.3 | BV53: 242633.83 | BW53: 33937.217 | BX53: 24447.248 | BY53: 29274.568 | BZ53: 13.03647 | CA53: 64156.771 | CB53: 218.98288 | CC53: 7.63246 | CE53: 282.371 | CF53: 5099.129 | CG53: 4070.211 | CH53: 49212.048 | CI53: 69959.806 | CJ53: 81.17508 | CK53: 42857.685 | CL53: 752.8686 | CM53: 708.14937 | CN53: 10370.083 | CO53: 24.05027 | CP53: 4.0052 | CR53: 11671.3 | CS53: 2061.3677 | CT53: 11467.735 | CU53: 319.78 | CV53: 535.27376 | CW53: 3866945.5 | CX53: 3866945.5
A54: =YEAR($B54) -> 2024 | B54: =ROUNDUP(MONTH($B54)/3, 0) -> 2 | C54: 45383 | D54: 11186.361 | E54: 5869.7454 | F54: 16065.828 | G54: 4353.0904 | H54: 5182.0792 | I54: 180109.03 | J54: 3947.8559 | K54: 188475.02 | L54: 261112.47 | M54: 808.57698 | N54: 7222.3619 | O54: 4255.3883 | P54: 268.27855 | Q54: 161.3022 | R54: 74154.054 | S54: 1992.1775 | T54: 65965.994 | U54: 23765.364 | V54: 16562.736 | W54: 16957.792 | X54: 43247.678 | Y54: 4464.1716 | Z54: 7545.7092 | AA54: 972.65714 | AB54: 3143.825 | AC54: 29961.859 | AD54: 2053557.1 | AE54: 14500.892 | AF54: 21106.492 | AG54: 32096.558 | AH54: 12857.658 | AI54: 10940.92 | AJ54: 69382.108 | AK54: 23539.081 | AL54: 6302.4091 | AN54: 29.60903 | AO54: 43834.319 | AP54: 155654.68 | AQ54: 8745.8517 | AR54: 2342.5077 | AS54: 3442.5608 | AT54: 411.85196 | AU54: 4211.5107 | AV54: 1.55395 | AW54: 114.22346 | AX54: 303.40991 | AY54: 35107.94 | AZ54: 4107.6564 | BA54: 0.02098 | BC54: 1226.4279 | BD54: 147.45821 | BE54: 5811.7626 | BF54: 1716.3652 | BG54: 1145.1766 | BH54: 174.86904 | BI54: 1115.3233 | BJ54: 2664.7083 | BK54: 5376.9402 | BL54: 16163.929 | BM54: 20659.408 | BN54: 7638.9546 | BO54: 3195.5896 | BP54: 1856.0267 | BQ54: 57.58021 | BR54: 5.50399 | BS54: 6334.223 | BT54: 11773.052 | BU54: 13310.916 | BV54: 390568.87 | BW54: 59533.144 | BX54: 32780.173 | BY54: 31053.574 | BZ54: 16.54372 | CA54: 64587.578 | CB54: 470.36825 | CC54: 89.86811 | CD54: 0.4296 | CE54: 179.52892 | CF54: 6402.2441 | CG54: 4768.3421 | CH54: 45646.848 | CI54: 96673.498 | CJ54: 143.26759 | CK54: 41391.058 | CL54: 10541.335 | CM54: 170.63683 | CN54: 12292.965 | CO54: 8.88934 | CP54: 1.5169 | CQ54: 2252.2104 | CR54: 14654.53 | CS54: 1891.7484 | CT54: 11165.281 | CU54: 195.57621 | CV54: 629.43394 | CW54: 4408826 | CX54: 4408826
A55: =YEAR($B55) -> 2024 | B55: =ROUNDUP(MONTH($B55)/3, 0) -> 2 | C55: 45413 | D55: 5137.0637 | E55: 5177.1577 | F55: 10523.807 | G55: 5969.7967 | H55: 5596.2974 | I55: 257444.58 | J55: 3245.7944 | K55: 203945.08 | L55: 268005.6 | M55: 269.4481 | N55: 7070.7198 | O55: 4445.6975 | P55: 844.22501 | Q55: 223.53038 | R55: 96468.866 | S55: 1509.52 | T55: 43924.39 | U55: 24227.272 | V55: 18438.419 | W55: 16702.874 | X55: 48921.81 | Y55: 5237.0983 | Z55: 6606.4622 | AA55: 1341.518 | AB55: 2653.9416 | AC55: 8257.7349 | AD55: 2065070.9 | AE55: 12783.683 | AF55: 20950.923 | AG55: 31396.609 | AH55: 8600.4658 | AI55: 11509.27 | AJ55: 65774.326 | AK55: 23464.63 | AL55: 5296.5588 | AN55: 184.51755 | AO55: 42025.91 | AP55: 139224.27 | AQ55: 7976.3114 | AR55: 2608.3929 | AS55: 4265.6265 | AT55: 552.57925 | AU55: 4401.8332 | AV55: 13.95897 | AW55: 83.59357 | AX55: 280.56799 | AY55: 33361.734 | AZ55: 5056.1473 | BB55: 0.30942 | BC55: 700.289 | BD55: 81.89436 | BE55: 5671.6731 | BF55: 849.17829 | BG55: 1887.7215 | BH55: 440.28702 | BI55: 741.24417 | BJ55: 3388.7695 | BK55: 4995.4615 | BL55: 16615.821 | BM55: 20642.622 | BN55: 9980.5139 | BO55: 3947.765 | BP55: 1631.4846 | BQ55: 33.09016 | BR55: 2.6784 | BS55: 6661.1885 | BT55: 8987.7857 | BU55: 13712.362 | BV55: 349993.84 | BW55: 73895.861 | BX55: 25494.924 | BY55: 34378.12 | BZ55: 12.20947 | CA55: 77869.782 | CB55: 280.9634 | CC55: 82.79201 | CD55: 16.19588 | CE55: 92.06576 | CF55: 5712.7456 | CG55: 4660.0109 | CH55: 57043.782 | CI55: 88902.058 | CJ55: 19.58 | CK55: 49234.287 | CL55: 395.9001 | CM55: 305.91329 | CN55: 10568.559 | CO55: 200.41978 | CP55: 10.07675 | CQ55: 219.88 | CR55: 17819.467 | CS55: 1665.3854 | CT55: 12809.327 | CU55: 409.23241 | CV55: 775.92767 | CW55: 4450913 | CX55: 4450913
A56: =YEAR($B56) -> 2024 | B56: =ROUNDUP(MONTH($B56)/3, 0) -> 2 | C56: 45444 | D56: 10814.019 | E56: 7951.0641 | F56: 8215.7923 | G56: 6721.9482 | H56: 4049.6962 | I56: 204488.78 | J56: 2449.6023 | K56: 137686.26 | L56: 285915.9 | M56: 116.72596 | N56: 5766.1414 | O56: 4914.7115 | P56: 42.43517 | Q56: 124.74704 | R56: 66849.579 | S56: 2045.3409 | T56: 44514.928 | U56: 20825.596 | V56: 16962.476 | W56: 16239.49 | X56: 39234.743 | Y56: 5579.1271 | Z56: 5246.6721 | AA56: 1678.6823 | AB56: 2770.3705 | AC56: 6058.2212 | AD56: 1786374.4 | AE56: 16542.144 | AF56: 18285.501 | AG56: 30654.326 | AH56: 4683.4575 | AI56: 12533.507 | AJ56: 56895.016 | AK56: 19485.925 | AL56: 7576.1075 | AN56: 5.9927 | AO56: 52710.231 | AP56: 144058.86 | AQ56: 9111.7667 | AR56: 3256.0896 | AS56: 3959.0979 | AT56: 216.96266 | AU56: 3902.5418 | AV56: 39.21645 | AW56: 57.80212 | AX56: 159.38483 | AY56: 36356.551 | AZ56: 3729.8148 | BB56: 1.10496 | BC56: 967.13814 | BD56: 37.47044 | BE56: 5341.1469 | BF56: 531.22636 | BG56: 930.1801 | BH56: 268.55845 | BI56: 817.23446 | BJ56: 3163.2473 | BK56: 6092.0664 | BL56: 14095.999 | BM56: 17036.085 | BN56: 7274.7244 | BO56: 3327.6633 | BP56: 1827.3213 | BQ56: 57.60511 | BR56: 2.29142 | BS56: 5075.2138 | BT56: 6849.0964 | BU56: 12183.067 | BV56: 282200.43 | BW56: 36488.036 | BX56: 22096.2 | BY56: 40241.385 | BZ56: 53.85543 | CA56: 67828.207 | CB56: 627.66597 | CC56: 48.3039 | CD56: 10.90355 | CE56: 170.94988 | CF56: 5019.3491 | CG56: 3863.313 | CH56: 44610.236 | CI56: 65566.5 | CJ56: 55.64522 | CK56: 37605.96 | CL56: 10534.339 | CM56: 73.5732 | CN56: 6627.8994 | CO56: 24.87099 | CP56: 68.14096 | CQ56: 1197.335 | CR56: 15411.221 | CS56: 1181.2918 | CT56: 12887.258 | CU56: 249.79037 | CV56: 851.00812 | CW56: 3859329.8 | CX56: 3859329.8
A57: =YEAR($B57) -> 2024 | B57: =ROUNDUP(MONTH($B57)/3, 0) -> 3 | C57: 45474 | D57: 17916.292 | E57: 8067.4722 | F57: 24945.046 | G57: 7762.8555 | H57: 6096.7591 | I57: 216369.61 | J57: 2666.6638 | K57: 129277.16 | L57: 291114.44 | M57: 47.73112 | N57: 6794.3435 | O57: 4110.8886 | P57: 247.44919 | Q57: 207.0393 | R57: 50199.052 | S57: 1537.0976 | T57: 57855.981 | U57: 27441.854 | V57: 17762.35 | W57: 17987.127 | X57: 38600.212 | Y57: 7005.4724 | Z57: 6761.6138 | AA57: 535.21094 | AB57: 1901.9075 | AC57: 31051.735 | AD57: 2227329.9 | AE57: 16637.276 | AF57: 16177.951 | AG57: 37280.949 | AH57: 4476.1242 | AI57: 11234.5 | AJ57: 57901.141 | AK57: 23916.471 | AL57: 4947.2527 | AN57: 21.92914 | AO57: 76205.315 | AP57: 154100.31 | AQ57: 9590.1793 | AR57: 2636.2204 | AS57: 3328.0731 | AT57: 485.81378 | AU57: 5922.3393 | AV57: 3.95195 | AW57: 84.75534 | AX57: 273.56764 | AY57: 39312.408 | AZ57: 6507.3627 | BA57: 1.59159 | BB57: 0.54 | BC57: 1267.2079 | BD57: 90.09596 | BE57: 6378.7591 | BF57: 917.63544 | BG57: 1261.6113 | BH57: 134.93985 | BI57: 756.18345 | BJ57: 3507.6423 | BK57: 6013.6242 | BL57: 15799.588 | BM57: 20448.118 | BN57: 8121.7342 | BO57: 3337.8749 | BP57: 1658.7619 | BQ57: 126.07098 | BR57: 20.6414 | BS57: 5954.5777 | BT57: 9568.3676 | BU57: 15796.091 | BV57: 416363.08 | BW57: 55360.125 | BX57: 23373.912 | BY57: 43370.098 | BZ57: 1.18112 | CA57: 76870.006 | CB57: 121.81807 | CC57: 61.98944 | CD57: 7.12685 | CE57: 128.02298 | CF57: 5485.4461 | CG57: 3354.2279 | CH57: 48803.596 | CI57: 86102.788 | CJ57: 46.978 | CK57: 33367.418 | CL57: 5181.9754 | CM57: 1185.9329 | CN57: 13380.087 | CO57: 315.53923 | CP57: 26.42765 | CQ57: 220.425 | CR57: 13774.065 | CS57: 1652.9657 | CT57: 14790.82 | CU57: 75.54105 | CV57: 1064.8113 | CW57: 4618285.2 | CX57: 4618285.2
A58: =YEAR($B58) -> 2024 | B58: =ROUNDUP(MONTH($B58)/3, 0) -> 3 | C58: 45505 | D58: 7097.2613 | E58: 8803.4955 | F58: 5697.1953 | G58: 5217.3708 | H58: 6734.6899 | I58: 152906.27 | J58: 2617.3449 | K58: 104381.89 | L58: 318115.41 | M58: 398.86561 | N58: 5402.6521 | O58: 4387.3049 | P58: 251.31444 | Q58: 80.32797 | R58: 54469.952 | S58: 1538.3064 | T58: 51061.024 | U58: 19899.209 | V58: 16765.782 | W58: 17513.021 | X58: 48497.557 | Y58: 6922.5827 | Z58: 7403.4902 | AA58: 272.20543 | AB58: 2035.5709 | AC58: 9503.475 | AD58: 1656952.7 | AE58: 14067.667 | AF58: 20728.977 | AG58: 31479.792 | AH58: 2710.2884 | AI58: 11106.783 | AJ58: 64187.361 | AK58: 21798.513 | AL58: 7629.8778 | AN58: 26.45325 | AO58: 56968.77 | AP58: 152377.83 | AQ58: 11619.839 | AR58: 3181.005 | AS58: 3769.2392 | AT58: 500.17314 | AU58: 3243.6331 | AV58: 46.93164 | AW58: 66.98185 | AX58: 133.38164 | AY58: 30926.992 | AZ58: 4483.3029 | BA58: 0.54744 | BB58: 0 | BC58: 736.15332 | BD58: 120.58165 | BE58: 5397.6673 | BF58: 467.81704 | BG58: 894.81524 | BH58: 123.76266 | BI58: 1108.5881 | BJ58: 2505.2844 | BK58: 5901.1444 | BL58: 14966.673 | BM58: 19100.867 | BN58: 7712.7759 | BO58: 3220.0455 | BP58: 1779.3333 | BQ58: 32.96756 | BR58: 1.73881 | BS58: 6769.6879 | BT58: 8165.0925 | BU58: 14405.964 | BV58: 331497.27 | BW58: 71761.485 | BX58: 23113.092 | BY58: 36960.067 | BZ58: 108.67232 | CA58: 79091.322 | CB58: 688.96426 | CC58: 182.50266 | CD58: 2.78195 | CE58: 343.18854 | CF58: 5580.7143 | CG58: 4197.5466 | CH58: 50203.513 | CI58: 91685.895 | CJ58: 53.284 | CK58: 52002.783 | CL58: 5663.6479 | CM58: 687.544 | CN58: 8923.304 | CO58: 724.33561 | CP58: 1.6731 | CQ58: 298.654 | CR58: 14984.315 | CS58: 2248.8518 | CT58: 12387.825 | CU58: 1806.4695 | CV58: 1119.2585 | CW58: 3845710.6 | CX58: 3845710.6
A59: =YEAR($B59) -> 2024 | B59: =ROUNDUP(MONTH($B59)/3, 0) -> 3 | C59: 45536 | D59: 2259.8896 | E59: 15045.692 | F59: 11423.575 | G59: 2950.6498 | H59: 4679.045 | I59: 173478.16 | J59: 2406.2883 | K59: 171397.61 | L59: 284093.59 | M59: 10508.04 | N59: 5168.7486 | O59: 4023.3341 | P59: 436.42757 | Q59: 272.578 | R59: 60387.973 | S59: 2591.6226 | T59: 72987.83 | U59: 27394.001 | V59: 18431.662 | W59: 16697.558 | X59: 51190.881 | Y59: 5444.2323 | Z59: 6825.8437 | AA59: 307.39869 | AB59: 2058.6743 | AC59: 25104.183 | AD59: 1791341.1 | AE59: 14819.215 | AF59: 18158.878 | AG59: 35679.899 | AH59: 4853.2712 | AI59: 14776.576 | AJ59: 61021.63 | AK59: 22553.71 | AL59: 5421.1503 | AN59: 124.52378 | AO59: 56620.291 | AP59: 127052.44 | AQ59: 8567.8562 | AR59: 2015.5313 | AS59: 3438.4612 | AT59: 562.1369 | AU59: 3669.6194 | AV59: 15.68881 | AW59: 65.08969 | AX59: 43.95886 | AY59: 27733.579 | AZ59: 6548.9697 | BA59: 2.66189 | BB59: 0.66068 | BC59: 1233.3274 | BD59: 71.32522 | BE59: 5997.3422 | BF59: 530.30886 | BG59: 1385.1762 | BH59: 156.63625 | BI59: 823.54589 | BJ59: 2895.7877 | BK59: 5039.8733 | BL59: 13998.142 | BM59: 16168.862 | BN59: 8511.6949 | BO59: 3270.5984 | BP59: 1383.2256 | BQ59: 160.03589 | BR59: 1.657 | BS59: 4571.2053 | BT59: 9239.9037 | BU59: 14562.174 | BV59: 449429.7 | BW59: 62850.171 | BX59: 19655.608 | BY59: 35837.187 | BZ59: 29.05825 | CA59: 71956.614 | CB59: 980.25749 | CC59: 46.33812 | CE59: 91.25825 | CF59: 4686.4639 | CG59: 3729.2456 | CH59: 51688.21 | CI59: 92927.722 | CJ59: 155.31989 | CK59: 39942.084 | CL59: 2760.8417 | CM59: 258.7944 | CN59: 13642.494 | CO59: 759.40489 | CP59: 10.32885 | CQ59: 1233.4074 | CR59: 15827.565 | CS59: 2652.3379 | CT59: 13825.45 | CU59: 31.10199 | CV59: 1031.7075 | CW59: 4158691.9 | CX59: 4158691.9
A60: =YEAR($B60) -> 2024 | B60: =ROUNDUP(MONTH($B60)/3, 0) -> 4 | C60: 45566 | D60: 26048.725 | E60: 12044.283 | F60: 11624.673 | G60: 5334.9828 | H60: 2031.3816 | I60: 176824.98 | J60: 3949.1275 | K60: 140235.52 | L60: 338376.87 | M60: 10786.881 | N60: 7054.095 | O60: 3993.8769 | P60: 344.90873 | Q60: 179.58108 | R60: 47096.406 | S60: 1886.3124 | T60: 83910.009 | U60: 21462.997 | V60: 19080.312 | W60: 17042.955 | X60: 46365.179 | Y60: 10243.505 | Z60: 9850.1045 | AA60: 350.52685 | AB60: 3472.4685 | AC60: 33432.019 | AD60: 1767167.6 | AE60: 14572.929 | AF60: 17528.847 | AG60: 32718.017 | AH60: 3651.5501 | AI60: 12804.956 | AJ60: 56811.21 | AK60: 23240.048 | AL60: 6659.4361 | AM60: 0.1875 | AN60: 61.88851 | AO60: 69856.715 | AP60: 171291.7 | AQ60: 9522.226 | AR60: 4004.2469 | AS60: 5251.6384 | AT60: 570.79559 | AU60: 3256.7276 | AV60: 15.63619 | AW60: 53.90671 | AX60: 184.67683 | AY60: 38867.552 | AZ60: 5333.7773 | BA60: 2.23647 | BB60: 2.22601 | BC60: 1245.199 | BD60: 52.71342 | BE60: 5137.1246 | BF60: 867.13077 | BG60: 1244.4708 | BH60: 214.32777 | BI60: 684.17251 | BJ60: 2842.7181 | BK60: 5462.1379 | BL60: 17187.291 | BM60: 18923.267 | BN60: 9744.1172 | BO60: 3469.9535 | BP60: 1252.6609 | BQ60: 24.4578 | BR60: 8.32907 | BS60: 4745.6456 | BT60: 7130.5081 | BU60: 13565.688 | BV60: 515368.42 | BW60: 51511.704 | BX60: 16681.248 | BY60: 34864.144 | BZ60: 0.65829 | CA60: 72817.036 | CB60: 1924.1709 | CC60: 35.1501 | CD60: 1.39916 | CE60: 86.09206 | CF60: 6721.7734 | CG60: 3712.1494 | CH60: 62942.991 | CI60: 89380.057 | CJ60: 127.51566 | CK60: 34597.756 | CL60: 2691.623 | CM60: 590.83842 | CN60: 8667.5359 | CO60: 381.06975 | CP60: 2.1396 | CQ60: 1248.1681 | CR60: 17400.226 | CS60: 2353.5698 | CT60: 13542.418 | CU60: 107.66009 | CV60: 1123.263 | CW60: 4309136.1 | CX60: 4309136.1
A61: =YEAR($B61) -> 2024 | B61: =ROUNDUP(MONTH($B61)/3, 0) -> 4 | C61: 45597 | D61: 12225.368 | E61: 20492.768 | F61: 7878.7665 | G61: 3877.0442 | H61: 3200.1059 | I61: 174182.09 | J61: 3292.0974 | K61: 145042.87 | L61: 325234.86 | M61: 400.30704 | N61: 6240.421 | O61: 3823.1052 | P61: 764.84848 | Q61: 39.91378 | R61: 73630.56 | S61: 2492.9252 | T61: 61962.816 | U61: 22769.104 | V61: 16755.992 | W61: 16754.627 | X61: 47447.983 | Y61: 7212.0091 | Z61: 7747.5704 | AA61: 250.82072 | AB61: 2693.309 | AC61: 11767.478 | AD61: 1849219.8 | AE61: 12903.153 | AF61: 15017.859 | AG61: 31849.443 | AH61: 2924.1337 | AI61: 13630.231 | AJ61: 60613.44 | AK61: 22192.062 | AL61: 8297.0329 | AM61: 1.5012 | AN61: 2.61284 | AO61: 51376.647 | AP61: 117688.52 | AQ61: 10593.862 | AR61: 2880.1148 | AS61: 4260.8789 | AT61: 381.09852 | AU61: 2402.8367 | AV61: 16.95251 | AW61: 163.53554 | AX61: 399.47006 | AY61: 38601.1 | AZ61: 3646.8409 | BA61: 0 | BB61: 1.34205 | BC61: 899.15082 | BD61: 23.61345 | BE61: 5125.8007 | BF61: 1276.0369 | BG61: 1303.7797 | BH61: 342.52197 | BI61: 846.85641 | BJ61: 2063.0608 | BK61: 5799.9531 | BL61: 15554.789 | BM61: 22151.314 | BN61: 8013.5538 | BO61: 4143.7137 | BP61: 1714.4622 | BQ61: 36.25942 | BR61: 13.85826 | BS61: 5130.2682 | BT61: 7990.1741 | BU61: 13378.207 | BV61: 421141.93 | BW61: 41269.185 | BX61: 22843.808 | BY61: 35732.983 | BZ61: 23.81142 | CA61: 63543.821 | CB61: 787.37923 | CC61: 65.48057 | CD61: 54.0753 | CE61: 219.18729 | CF61: 6400.2592 | CG61: 4556.8713 | CH61: 39842.01 | CI61: 88876.759 | CJ61: 108.1866 | CK61: 32366.395 | CL61: 1868.2194 | CM61: 2445.1529 | CN61: 9232.8407 | CO61: 508.14253 | CP61: 16.15495 | CQ61: 2.036 | CR61: 17280.431 | CS61: 1591.5274 | CT61: 11595.732 | CU61: 68.89575 | CV61: 606.78667 | CW61: 4126099.7 | CX61: 4126099.7
A62: =YEAR($B62) -> 2024 | B62: =ROUNDUP(MONTH($B62)/3, 0) -> 4 | C62: 45627 | D62: 27700.993 | E62: 17622.981 | F62: 7255.2776 | G62: 5032.0756 | H62: 5225.9356 | I62: 203156.91 | J62: 3531.0018 | K62: 159694.22 | L62: 462940.06 | M62: 4665.4795 | N62: 5818.3475 | O62: 4913.3134 | P62: 471.7367 | Q62: 62.69799 | R62: 74547.898 | S62: 3237.046 | T62: 60231.854 | U62: 25534.631 | V62: 18453.877 | W62: 16756.795 | X62: 42684.939 | Y62: 11917.728 | Z62: 9978.6049 | AA62: 748.96327 | AB62: 2318.7258 | AC62: 33436.159 | AD62: 1857556.4 | AE62: 14868.728 | AF62: 17053.918 | AG62: 42099.304 | AH62: 5112.4387 | AI62: 14561.809 | AJ62: 65674.071 | AK62: 25562.409 | AL62: 6903.8812 | AM62: 9.1375 | AN62: 51.50562 | AO62: 49595.136 | AP62: 141123.46 | AQ62: 12393.729 | AR62: 2707.0904 | AS62: 4444.2662 | AT62: 482.23593 | AU62: 3209.4402 | AV62: 0.93104 | AW62: 56.65464 | AX62: 158.38082 | AY62: 31696.397 | AZ62: 7159.6978 | BA62: 0 | BB62: 0.20426 | BC62: 1069.1872 | BD62: 68.17873 | BE62: 4912.7367 | BF62: 1059.0355 | BG62: 1282.9665 | BH62: 314.23104 | BI62: 715.49199 | BJ62: 2054.2647 | BK62: 5272.9149 | BL62: 18094.987 | BM62: 21439.281 | BN62: 9608.6184 | BO62: 4023.4347 | BP62: 2234.653 | BQ62: 32.16942 | BR62: 3.91669 | BS62: 4575.5248 | BT62: 9727.6324 | BU62: 13533.579 | BV62: 398510.23 | BW62: 64660.96 | BX62: 29481.116 | BY62: 37108.796 | BZ62: 10.14086 | CA62: 69618.81 | CB62: 1249.9661 | CC62: 13.37326 | CD62: 0 | CE62: 116.89592 | CF62: 6946.44 | CG62: 3767.8115 | CH62: 68182.243 | CI62: 93107.179 | CJ62: 170.81112 | CK62: 49150.651 | CL62: 2792.3838 | CM62: 3953.167 | CN62: 10151.864 | CO62: 1068.8736 | CP62: 26.58168 | CQ62: 78.9118 | CR62: 14588.488 | CS62: 1134.6067 | CT62: 13382.567 | CU62: 124.621 | CV62: 668.58119 | CW62: 4480508.3 | CX62: 4480508.3
A63: =YEAR($B63) -> 2025 | B63: =ROUNDUP(MONTH($B63)/3, 0) -> 1 | C63: 45658 | D63: 31982.796 | E63: 19411.132 | F63: 7200.261 | G63: 4545.7217 | H63: 3100.4694 | I63: 192730.53 | J63: 3290.2558 | K63: 146117.03 | L63: 474078.64 | M63: 778.555 | N63: 5111.9935 | O63: 4747.0854 | P63: 314.86763 | Q63: 98.53548 | R63: 67504.301 | S63: 3657.8184 | T63: 64528.096 | U63: 29046.638 | V63: 14626.926 | W63: 14377.92 | X63: 39668.943 | Y63: 6045.9202 | Z63: 6148.1419 | AA63: 547.27796 | AB63: 1970.7245 | AC63: 26948.502 | AD63: 1479980.5 | AE63: 11031.962 | AF63: 15259.128 | AG63: 21067.482 | AH63: 3503.6188 | AI63: 10047.59 | AJ63: 56686.868 | AK63: 15893.363 | AL63: 4854.6457 | AM63: 2.8798 | AN63: 19.71239 | AO63: 45806.666 | AP63: 133508.12 | AQ63: 4801.0191 | AR63: 2736.7195 | AS63: 3533.6706 | AT63: 439.56612 | AU63: 3445.2005 | AV63: 17.9877 | AW63: 126.71376 | AX63: 179.67892 | AY63: 27991.917 | AZ63: 4254.4756 | BA63: 0 | BB63: 0.78074 | BC63: 1085.7661 | BD63: 19.89899 | BE63: 2845.3095 | BF63: 1219.729 | BG63: 719.64399 | BH63: 6.52756 | BI63: 523.93711 | BJ63: 1978.6128 | BK63: 3690.7694 | BL63: 11777.288 | BM63: 12814.876 | BN63: 10122.382 | BO63: 2573.0536 | BP63: 1540.5637 | BQ63: 269.21255 | BR63: 6.38812 | BS63: 5038.6278 | BT63: 6469.9747 | BU63: 10533.141 | BV63: 341543.54 | BW63: 43272.399 | BX63: 19015.669 | BY63: 36078.931 | BZ63: 2.62921 | CA63: 71788.156 | CB63: 949.77727 | CC63: 63.48254 | CD63: 54.18 | CE63: 91.24232 | CF63: 3603.9749 | CG63: 3864.7801 | CH63: 48976.309 | CI63: 77682.635 | CJ63: 12.738 | CK63: 10342.95 | CL63: 1457.7446 | CM63: 189.24205 | CN63: 6760.2784 | CO63: 939.17673 | CP63: 9.95503 | CQ63: 0 | CR63: 10795.689 | CS63: 1493.7902 | CT63: 9534.854 | CU63: 347.65612 | CV63: 844.54283 | CW63: 3776721.4 | CX63: 3776721.4
A64: 2025 | B64: 1 | C64: 45689 | D64: 15013.329 | E64: 21311.936 | F64: 9735.2746 | G64: 6927.5214 | H64: 3090.5134 | I64: 235417.29 | J64: 2810.5945 | K64: 134227.56 | L64: 434404.71 | M64: 572.84199 | N64: 6363.4013 | O64: 4626.4721 | P64: 111.08353 | Q64: 143.96509 | R64: 72854.115 | S64: 2415.9666 | T64: 54910.003 | U64: 36199.783 | V64: 16970.872 | W64: 15827.904 | X64: 48209.506 | Y64: 6609.7071 | Z64: 8662.495 | AA64: 754.90566 | AB64: 2808.8918 | AC64: 69123.902 | AD64: 1374729.2 | AE64: 15411.304 | AF64: 17438.787 | AG64: 33055.571 | AH64: 7512.4833 | AI64: 11771.85 | AJ64: 61732.358 | AK64: 26821.538 | AL64: 5758.3663 | AM64: 0.536 | AN64: 5.37901 | AO64: 32930.451 | AP64: 130711.23 | AQ64: 6769.3124 | AR64: 2974.2062 | AS64: 4442.9044 | AT64: 406.68135 | AU64: 4139.7539 | AV64: 54.5646 | AW64: 77.9111 | AX64: 566.46495 | AY64: 38193.776 | AZ64: 3861.9183 | BA64: 0 | BB64: 1.11446 | BC64: 2228.2214 | BD64: 52.44365 | BE64: 5119.6754 | BF64: 1872.0205 | BG64: 1142.1426 | BH64: 268.05553 | BI64: 660.56293 | BJ64: 2560.5926 | BK64: 4421.4974 | BL64: 18235.239 | BM64: 17058.991 | BN64: 8785.1259 | BO64: 2887.2421 | BP64: 1514.8234 | BQ64: 8.23787 | BR64: 12.56139 | BS64: 5664.4648 | BT64: 8104.4 | BU64: 11874.868 | BV64: 343151.7 | BW64: 39281.966 | BX64: 16908.022 | BY64: 34132.883 | BZ64: 1.77519 | CA64: 57171.519 | CB64: 2350.4101 | CC64: 31.36338 | CD64: 390.35546 | CE64: 215.00224 | CF64: 4782.5159 | CG64: 3239.7655 | CH64: 50635.933 | CI64: 73278.137 | CJ64: 29.82196 | CK64: 30327.123 | CL64: 7440.0709 | CM64: 596.082 | CN64: 8469.718 | CO64: 257.72408 | CP64: 3.54293 | CQ64: 23.3025 | CR64: 12365.83 | CS64: 983.30264 | CT64: 11541.702 | CU64: 77.60191 | CV64: 644.4133 | CW64: 3780274.9 | CX64: 3780274.9
A65: 2025 | B65: 1 | C65: 45717 | D65: 23704.607 | E65: 16952.664 | F65: 9725.931 | G65: 5674.9635 | H65: 3206.4197 | I65: 276007.19 | J65: 4560.9028 | K65: 157081.4 | L65: 550164.4 | M65: 647.88191 | N65: 6499.0356 | O65: 5165.537 | P65: 209.47439 | Q65: 240.13592 | R65: 108199.52 | S65: 2766.0298 | T65: 61683.926 | U65: 52486.907 | V65: 19469.219 | W65: 17440.753 | X65: 50910.14 | Y65: 8197.9779 | Z65: 8760.0538 | AA65: 391.81069 | AB65: 2604.5818 | AC65: 9915.5364 | AD65: 1704501.5 | AE65: 12668.17 | AF65: 16045.112 | AG65: 36584.564 | AH65: 5278.2754 | AI65: 16227.972 | AJ65: 61366.458 | AK65: 25210.165 | AL65: 5703.2796 | AM65: 0 | AN65: 61.41926 | AO65: 46135.236 | AP65: 157003.47 | AQ65: 7351.8306 | AR65: 3021.8386 | AS65: 3838.1806 | AT65: 513.35263 | AU65: 3814.4763 | AV65: 9.87468 | AW65: 187.47872 | AX65: 92.97444 | AY65: 42706.257 | AZ65: 4053.2229 | BA65: 1.77314 | BB65: 0 | BC65: 1092.6472 | BD65: 83.23037 | BE65: 4666.0436 | BF65: 1263.3583 | BG65: 1088.8341 | BH65: 242.52832 | BI65: 1093.2341 | BJ65: 2340.3131 | BK65: 5637.7244 | BL65: 16079.157 | BM65: 19767.355 | BN65: 8067.2346 | BO65: 3264.365 | BP65: 2008.9048 | BQ65: 3.69572 | BR65: 3.76795 | BS65: 6064.0463 | BT65: 9905.616 | BU65: 10570.408 | BV65: 359021.71 | BW65: 51139.87 | BX65: 20095.742 | BY65: 34815.662 | BZ65: 3.57985 | CA65: 66188.803 | CB65: 617.80995 | CC65: 110.85733 | CD65: 216.6 | CE65: 17.37886 | CF65: 5912.4133 | CG65: 3970.6143 | CH65: 46143.969 | CI65: 93246.621 | CJ65: 390.34166 | CK65: 28523.915 | CL65: 305.04289 | CM65: 3345.9837 | CN65: 7888.9075 | CO65: 769.18694 | CP65: 3.60141 | CQ65: 0 | CR65: 11810.672 | CS65: 1022.3132 | CT65: 13443.933 | CU65: 75.03278 | CV65: 454.63608 | CW65: 4397821.5 | CX65: 4397821.5
A66: 2025 | B66: 2 | C66: 45748 | D66: 30727.495 | E66: 10377.83 | F66: 14917.815 | G66: 5493.5039 | H66: 4503.9852 | I66: 198997 | J66: 3066.7854 | K66: 247102.37 | L66: 483948.25 | M66: 1616.7977 | N66: 5983.6445 | O66: 4689.6455 | P66: 241.47751 | Q66: 202.3598 | R66: 166517.56 | S66: 721.73557 | T66: 69020.32 | U66: 44350.922 | V66: 16315.258 | W66: 17859.94 | X66: 46649.104 | Y66: 9099.5621 | Z66: 9659.1663 | AA66: 1220.4983 | AB66: 2975.6523 | AC66: 39737.957 | AD66: 1344704.1 | AE66: 17795.16 | AF66: 14313.085 | AG66: 31873.274 | AH66: 10662.976 | AI66: 13440.263 | AJ66: 70147.742 | AK66: 23595.084 | AL66: 5918.3751 | AM66: 331.5 | AN66: 19.81446 | AO66: 46966.03 | AP66: 146621.59 | AQ66: 6065.2934 | AR66: 4391.2827 | AS66: 4704.2563 | AT66: 534.18324 | AU66: 5052.364 | AV66: 27.56688 | AW66: 89.77936 | AX66: 618.35685 | AY66: 36700.167 | AZ66: 5000.7588 | BA66: 10.70787 | BB66: 3.00316 | BC66: 996.28977 | BD66: 35.56816 | BE66: 5640.2725 | BF66: 643.99692 | BG66: 1211.7062 | BH66: 87.82498 | BI66: 771.78129 | BJ66: 2833.6413 | BK66: 4987.8027 | BL66: 18442.603 | BM66: 17823.769 | BN66: 6461.211 | BO66: 3082.042 | BP66: 1920.1432 | BQ66: 14.30725 | BR66: 41.57889 | BS66: 5679.7579 | BT66: 10049.297 | BU66: 11865.999 | BV66: 367847.67 | BW66: 50800.296 | BX66: 23889.317 | BY66: 25444.737 | BZ66: 284.75682 | CA66: 66952.086 | CB66: 1280.4569 | CC66: 99.40139 | CD66: 379.86973 | CE66: 237.40081 | CF66: 6538.6253 | CG66: 4263.0427 | CH66: 68777.372 | CI66: 114278.32 | CJ66: 24.54859 | CK66: 28688.486 | CL66: 1665.4545 | CM66: 689.35719 | CN66: 7876.372 | CO66: 544.94294 | CP66: 18.23253 | CQ66: 739.66813 | CR66: 13523.286 | CS66: 1811.4643 | CT66: 13605.704 | CU66: 273.559 | CV66: 702.32639 | CW66: 4119409.7 | CX66: 4119409.7
A67: 2025 | B67: 2 | C67: 45778 | D67: 1359.6221 | E67: 12141.021 | F67: 19105.793 | G67: 3777.7945 | H67: 5047.001 | I67: 242333.44 | J67: 3414.3706 | K67: 229086.47 | L67: 427844.61 | M67: 2025.6828 | N67: 8359.1881 | O67: 4278.2369 | P67: 780.30954 | Q67: 144.67088 | R67: 149091.34 | S67: 2504.4017 | T67: 58178.164 | U67: 29610.783 | V67: 18461.478 | W67: 18790.75 | X67: 60460.824 | Y67: 5937.5637 | Z67: 9939.0673 | AA67: 3550.0742 | AB67: 3403.5376 | AC67: 51203.778 | AD67: 1617917.1 | AE67: 14569.351 | AF67: 16568.431 | AG67: 39447.958 | AH67: 9412.8169 | AI67: 14616.559 | AJ67: 70833.187 | AK67: 27164.813 | AL67: 8631.2277 | AM67: 0 | AN67: 61.33319 | AO67: 56968.646 | AP67: 142975.86 | AQ67: 11365.593 | AR67: 2877.5767 | AS67: 5149.852 | AT67: 312.85438 | AU67: 4528.9429 | AV67: 28.51257 | AW67: 72.92737 | AX67: 44.96021 | AY67: 40725.379 | AZ67: 5238.9156 | BA67: 0 | BB67: 0.70676 | BC67: 1197.5561 | BD67: 36.44386 | BE67: 4029.0059 | BF67: 261.27509 | BG67: 1144.6089 | BH67: 245.58437 | BI67: 777.43843 | BJ67: 2055.3577 | BK67: 6259.7787 | BL67: 16430.967 | BM67: 19663.412 | BN67: 12290.449 | BO67: 4155.8284 | BP67: 1268.723 | BQ67: 34.17656 | BR67: 35.55609 | BS67: 6185.0664 | BT67: 10027.119 | BU67: 12528.04 | BV67: 368401.09 | BW67: 46515.317 | BX67: 26864.367 | BY67: 38291.592 | BZ67: 50.24913 | CA67: 85310.641 | CB67: 60.42911 | CC67: 243.38985 | CD67: 75.21576 | CE67: 142.61746 | CF67: 5710.5175 | CG67: 4582.9099 | CH67: 42933.746 | CI67: 82444.226 | CJ67: 558.70812 | CK67: 44947.139 | CL67: 2418.959 | CM67: 1389.6294 | CN67: 9888.8771 | CO67: 610.92975 | CP67: 66.37135 | CQ67: 1675.6686 | CR67: 15199.7 | CS67: 1803.7292 | CT67: 16609.717 | CU67: 1218.3605 | CV67: 419.69324 | CW67: 4357403.6 | CX67: 4358143.9
A68: 2025 | B68: 2 | C68: 45809 | D68: 8130.4122 | E68: 9832.19 | F68: 18866.64 | G68: 4436.9714 | H68: 5840.0124 | I68: 270128.66 | J68: 2168.522 | K68: 160418.29 | L68: 419873.07 | M68: 1236.4417 | N68: 6114.3782 | O68: 3719.7535 | P68: 33.61369 | Q68: 202.23895 | R68: 112867.27 | S68: 1322.44 | T68: 42452.161 | U68: 34163.951 | V68: 17988.064 | W68: 18263.904 | X68: 65796.154 | Y68: 7361.5812 | Z68: 10437.28 | AA68: 2084.2866 | AB68: 3365.407 | AC68: 12619.883 | AD68: 1468760.4 | AE68: 12812.969 | AF68: 13871.538 | AG68: 37338.881 | AH68: 6348.4878 | AI68: 13881.17 | AJ68: 61109.931 | AK68: 22878.725 | AL68: 6126.5138 | AM68: 0.66777 | AN68: 56.3375 | AO68: 56796.239 | AP68: 138182.13 | AQ68: 8739.2602 | AR68: 2957.4558 | AS68: 5110.6651 | AT68: 410.31625 | AU68: 2646.5908 | AV68: 19.84815 | AW68: 59.84877 | AX68: 355.77004 | AY68: 28268.89 | AZ68: 4836.2815 | BA68: 0 | BB68: 0.41935 | BC68: 1274.4402 | BD68: 23.89425 | BE68: 4494.0253 | BF68: 1005.794 | BG68: 1094.2286 | BH68: 103.48748 | BI68: 870.69584 | BJ68: 1350.0079 | BK68: 4249.5528 | BL68: 15603.364 | BM68: 18084.992 | BN68: 10356.888 | BO68: 2453.0521 | BP68: 1792.9424 | BQ68: 16.82472 | BR68: 0.422 | BS68: 5969.8558 | BT68: 7289.8252 | BU68: 12672.509 | BV68: 322623.72 | BW68: 47023.719 | BX68: 20321.619 | BY68: 30253.873 | BZ68: 4.7139 | CA68: 86879.193 | CB68: 257.41415 | CC68: 84.9029 | CD68: 60 | CE68: 90.94861 | CF68: 5299.4071 | CG68: 4511.0456 | CH68: 51778.514 | CI68: 95984.484 | CJ68: 123.10936 | CK68: 31195.71 | CL68: 2104.9431 | CM68: 1197.7994 | CN68: 5852.8081 | CO68: 217.39722 | CP68: 11.24258 | CQ68: 23.9 | CR68: 14404.52 | CS68: 1131.4987 | CT68: 15131.089 | CU68: 331.82292 | CV68: 779.7945 | CW68: 3957678.9 | CX68: 3957678.9
A69: 2025 | B69: 3 | C69: 45839 | D69: 35603.957 | E69: 16941.816 | F69: 12779.758 | G69: 5720.3851 | H69: 3918.2128 | I69: 162554.21 | J69: 3088.5462 | K69: 174803.16 | L69: 481898.81 | M69: 464.83475 | N69: 8721.3196 | O69: 4159.8109 | P69: 162.02263 | Q69: 263.43663 | R69: 116602.2 | S69: 3698.2705 | T69: 59265.154 | U69: 36000.057 | V69: 21793.848 | W69: 22559.239 | X69: 56058.041 | Y69: 7576.154 | Z69: 10504.187 | AA69: 557.12653 | AB69: 4283.7142 | AC69: 69055.748 | AD69: 1587043.3 | AE69: 17568.182 | AF69: 19717.291 | AG69: 41861.512 | AH69: 12413.979 | AI69: 15177.699 | AJ69: 81524.815 | AK69: 24982.832 | AL69: 6976.0954 | AM69: 180.98482 | AN69: 83.69537 | AO69: 107491.12 | AP69: 159691.12 | AQ69: 10573.18 | AR69: 2886.1469 | AS69: 4804.6914 | AT69: 620.05373 | AU69: 4235.0212 | AV69: 7.20229 | AW69: 61.90847 | AX69: 91.71862 | AY69: 33772.129 | AZ69: 5832.7846 | BA69: 0 | BB69: 2.32503 | BC69: 1407.7237 | BD69: 82.40557 | BE69: 6005.4637 | BF69: 737.32334 | BG69: 1609.1956 | BH69: 263.65868 | BI69: 674.93629 | BJ69: 2672.0431 | BK69: 6913.9217 | BL69: 17745.879 | BM69: 18557.207 | BN69: 7949.3395 | BO69: 2942.9495 | BP69: 2086.4339 | BQ69: 31.49804 | BR69: 13.65892 | BS69: 7708.0322 | BT69: 9314.6256 | BU69: 13254.344 | BV69: 414431.61 | BW69: 48677.227 | BX69: 20676.365 | BY69: 40925.074 | BZ69: 10.48201 | CA69: 91403.8 | CB69: 2025.3636 | CC69: 57.39612 | CD69: 245.76199 | CE69: 297.90254 | CF69: 6573.8711 | CG69: 5453.5093 | CH69: 57093.193 | CI69: 100453.5 | CJ69: 88.21419 | CK69: 28255.238 | CL69: 9151.3746 | CM69: 190.80422 | CN69: 9277.8092 | CO69: 570.18032 | CP69: 5.33814 | CQ69: 83.29639 | CR69: 16360.66 | CS69: 1811.437 | CT69: 14886.574 | CU69: 137.65081 | CV69: 1736.7404 | CW69: 4427484.8 | CX69: 4427484.8
A70: 2025 | B70: 3 | C70: 45870 | D70: 11181.523 | E70: 14582.565 | F70: 12832.248 | G70: 4456.3671 | H70: 3967.2748 | I70: 152942.48 | J70: 2359.5487 | K70: 162379.67 | L70: 535820.25 | M70: 10442.808 | N70: 7544.4083 | O70: 3873.1434 | P70: 286.49671 | Q70: 271.70938 | R70: 101412.64 | S70: 1035.5639 | T70: 71130.579 | U70: 33143.989 | V70: 17695.451 | W70: 19470.893 | X70: 84440.066 | Y70: 7821.7828 | Z70: 7723.2311 | AA70: 337.00346 | AB70: 3045.8421 | AC70: 173620.45 | AD70: 1214240.6 | AE70: 13502.531 | AF70: 17368.163 | AG70: 36657.46 | AH70: 4643.331 | AI70: 12286.754 | AJ70: 56384.603 | AK70: 20696.898 | AL70: 7700.3733 | AM70: 21.25161 | AN70: 103.71349 | AO70: 51133.07 | AP70: 134339.59 | AQ70: 6439.615 | AR70: 3818.3157 | AS70: 3309.8796 | AT70: 357.84815 | AU70: 1939.2619 | AV70: 11.81774 | AW70: 77.11124 | AX70: 369.13038 | AY70: 28530.504 | AZ70: 4701.831 | BA70: 7.21635 | BB70: 1.34244 | BC70: 990.3582 | BD70: 10.92904 | BE70: 5598.5574 | BF70: 968.29965 | BG70: 1969.2228 | BH70: 120.61996 | BI70: 912.32114 | BJ70: 2407.836 | BK70: 5509.3181 | BL70: 16133.4 | BM70: 16775.143 | BN70: 8338.0482 | BO70: 3112.9122 | BP70: 1749.4223 | BQ70: 21.90469 | BR70: 38.74252 | BS70: 5681.6803 | BT70: 7612.4407 | BU70: 10853.76 | BV70: 324427.48 | BW70: 49794.914 | BX70: 21867.44 | BY70: 28633.643 | BZ70: 16.29339 | CA70: 63569.894 | CB70: 2039.9922 | CC70: 93.182 | CD70: 3.84519 | CE70: 247.60809 | CF70: 6119.5395 | CG70: 4803.2565 | CH70: 51626.684 | CI70: 85997.018 | CJ70: 199.55238 | CK70: 45745.574 | CL70: 2577.5509 | CM70: 357.68655 | CN70: 5531.5193 | CO70: 333.17589 | CP70: 1.49713 | CQ70: 0 | CR70: 13954.427 | CS70: 754.26417 | CT70: 9934.9539 | CU70: 255.514 | CV70: 1392.6374 | CW70: 3871544.3 | CX70: 3842152.2
A71: 2025 | B71: 3 | C71: 45901 | D71: 7728.5909 | E71: 11483.748 | F71: 11760.319 | G71: 4640.8921 | H71: 6195.5968 | I71: 159769.44 | J71: 3050.5208 | K71: 206522.72 | L71: 507682.29 | M71: 9858.0491 | N71: 5601.511 | O71: 4386.3734 | P71: 159.15743 | Q71: 242.85658 | R71: 86605.495 | S71: 1905.2145 | T71: 59441.582 | U71: 29193.781 | V71: 19578.753 | W71: 17993.715 | X71: 57367.021 | Y71: 6179.0625 | Z71: 13616.647 | AA71: 397.45941 | AB71: 3455.1309 | AC71: 320837.64 | AD71: 1593708.2 | AE71: 11708.101 | AF71: 16162.801 | AG71: 44281.902 | AH71: 5518.2111 | AI71: 15398.675 | AJ71: 76305.248 | AK71: 26535.581 | AL71: 9072.6666 | AM71: 119.97315 | AN71: 92.40268 | AO71: 88936.889 | AP71: 160913.87 | AQ71: 10722.019 | AR71: 4099.673 | AS71: 4170.9273 | AT71: 554.74499 | AU71: 2941.4859 | AV71: 7.81309 | AW71: 82.39431 | AX71: 534.16629 | AY71: 34486.956 | AZ71: 5921.5618 | BA71: 3.39256 | BB71: 0.22322 | BC71: 1390.833 | BD71: 150.85285 | BE71: 5683.2728 | BF71: 733.50801 | BG71: 2172.5566 | BH71: 284.08121 | BI71: 906.07046 | BJ71: 2167.417 | BK71: 6400.0006 | BL71: 17096.025 | BM71: 17167.211 | BN71: 7976.7879 | BO71: 3601.1365 | BP71: 2067.6681 | BQ71: 61.36736 | BR71: 39.43882 | BS71: 6883.5261 | BT71: 9648.1503 | BU71: 9004.4124 | BV71: 450539.39 | BW71: 49142.102 | BX71: 23462.374 | BY71: 31071.432 | BZ71: 2.40705 | CA71: 74857.634 | CB71: 1161.7131 | CC71: 77.68034 | CD71: 56.19 | CE71: 57.0957 | CF71: 7437.5938 | CG71: 4181.209 | CH71: 54735.007 | CI71: 97069.739 | CJ71: 198.86034 | CK71: 50900.033 | CL71: 2390.8725 | CM71: 246.24222 | CN71: 10719.147 | CO71: 285.51338 | CP71: 4.2037 | CQ71: 16.71039 | CR71: 15659.576 | CS71: 1418.5283 | CT71: 11823.186 | CU71: 188.54909 | CV71: 1263.1453 | CW71: 4650333.9
A72: 2025 | B72: 4 | C72: 45931 | D72: 8462.1969 | E72: 10387.281 | F72: 24199.088 | G72: 7389.1642 | H72: 3178.7002 | I72: 170607.01 | J72: 3154.1759 | K72: 221112.25 | L72: 547763.43 | M72: 5324.0336 | N72: 7134.811 | O72: 4280.2805 | P72: 526.92056 | Q72: 265.75344 | R72: 102401.37 | S72: 1840.5014 | T72: 66978.664 | U72: 32860.486 | V72: 19581.64 | W72: 17552.45 | X72: 47685.948 | Y72: 7543.416 | Z72: 10289.992 | AA72: 996.3475 | AB72: 3423.1451 | AC72: 58808.442 | AD72: 1389501.2 | AE72: 13439.145 | AF72: 20592.382 | AG72: 36821.224 | AH72: 5818.6306 | AI72: 15030.558 | AJ72: 65520.308 | AK72: 23618.508 | AL72: 6994.6131 | AM72: 0 | AN72: 151.11503 | AO72: 70747.009 | AP72: 168486.88 | AQ72: 9386.6594 | AR72: 3478.7021 | AS72: 3733.3754 | AT72: 791.67797 | AU72: 3069.0887 | AV72: 0.681 | AW72: 129.43853 | AX72: 0.1893 | AY72: 32351.407 | AZ72: 6485.8087 | BA72: 3.01419 | BB72: 23.52077 | BC72: 712.20043 | BD72: 79.95317 | BE72: 5656.08 | BF72: 677.07843 | BG72: 1117.9893 | BH72: 184.92442 | BI72: 758.16726 | BJ72: 2515.7143 | BK72: 6230.457 | BL72: 20009.905 | BM72: 19965.864 | BN72: 6763.1572 | BO72: 3830.4188 | BP72: 1557.0905 | BQ72: 11.09979 | BR72: 16.48452 | BS72: 6229.7618 | BT72: 8284.0153 | BU72: 13921.451 | BV72: 472569.19 | BW72: 49823.291 | BX72: 23423.845 | BY72: 26991.072 | BZ72: 4.03932 | CA72: 75530.363 | CB72: 1228.9067 | CC72: 33.38006 | CD72: 129.72972 | CE72: 169.02873 | CF72: 6465.4434 | CG72: 5341.9452 | CH72: 52004.037 | CI72: 81746.812 | CJ72: 163.03974 | CK72: 55453.744 | CL72: 48811.45 | CM72: 56.266 | CN72: 8711.5338 | CO72: 81.29246 | CP72: 3.43777 | CQ72: 3690.9618 | CR72: 15937.728 | CS72: 1469.8564 | CT72: 9389.3807 | CU72: 439.35452 | CV72: 1036.3032 | CW72: 4299149.9
A73: 2025 | B73: 4 | C73: 45962 | D73: 12050.493 | E73: 10130.504 | F73: 7708.2116 | G73: 7232.8464 | H73: 3285.776 | I73: 192810.3 | J73: 2642.0892 | K73: 185002.37 | L73: 592944.36 | M73: 3721.8142 | N73: 5920.2078 | O73: 5419.8212 | P73: 291.4694 | Q73: 185.63428 | R73: 113820.51 | S73: 776.31297 | T73: 47564.741 | U73: 26268.355 | V73: 15337.592 | W73: 15442.994 | X73: 84200.518 | Y73: 7498.0968 | Z73: 9276.4199 | AA73: 156.89273 | AB73: 2578.6282 | AC73: 45297.86 | AD73: 1316741.9 | AE73: 9552.6628 | AF73: 13831.344 | AG73: 41283.713 | AH73: 5985.1378 | AI73: 14625.672 | AJ73: 62920.433 | AK73: 21378.92 | AL73: 7614.9175 | AM73: 33.2081 | AN73: 6.16268 | AO73: 56559.382 | AP73: 139710.77 | AQ73: 11557.43 | AR73: 3950.5624 | AS73: 4031.7312 | AT73: 572.94581 | AU73: 1760.0312 | AV73: 31.79479 | AW73: 171.61355 | AX73: 5.89552 | AY73: 34305.221 | AZ73: 5408.7618 | BA73: 0 | BB73: 0 | BC73: 1132.7542 | BD73: 25.69969 | BE73: 4531.3756 | BF73: 543.07322 | BG73: 1095.7362 | BH73: 249.54823 | BI73: 639.08216 | BJ73: 1238.8424 | BK73: 4142.9725 | BL73: 17884.213 | BM73: 20079.18 | BN73: 7336.4053 | BO73: 4015.1076 | BP73: 2131.2663 | BQ73: 97.29969 | BR73: 19.55609 | BS73: 6013.9537 | BT73: 7866.688 | BU73: 10823.563 | BV73: 349733.06 | BW73: 53046.812 | BX73: 20812.06 | BY73: 32171.509 | BZ73: 33.28026 | CA73: 70900.994 | CB73: 1576.5467 | CC73: 58.62754 | CD73: 68.75272 | CE73: 87.01445 | CF73: 5568.5016 | CG73: 4362.8026 | CH73: 47973.379 | CI73: 101647.33 | CJ73: 41.16 | CK73: 55255.065 | CL73: 1342.7533 | CM73: 1180.3685 | CN73: 6064.3485 | CO73: 30.41672 | CP73: 14.505 | CQ73: 0 | CR73: 15826.117 | CS73: 1901.4177 | CT73: 8311.5139 | CU73: 445.99905 | CV73: 567.03906 | CW73: 4018492.7
A74: 2025 | B74: 4 | C74: 45992 | D74: 12432.287 | E74: 9897.8164 | F74: 13005.779 | G74: 8367.6874 | H74: 4515.3147 | I74: 185231.81 | J74: 3585.5264 | K74: 169454.06 | L74: 524602.69 | M74: 1600.892 | N74: 6774.7923 | O74: 5531.1411 | P74: 114.62905 | Q74: 222.49214 | R74: 86642.488 | S74: 572.51085 | T74: 75320.63 | U74: 29856.31 | V74: 16744.591 | W74: 18083.43 | X74: 49534.293 | Y74: 6447.1442 | Z74: 11280.043 | AA74: 286.37785 | AB74: 4149.5212 | AC74: 79917.145 | AD74: 1430491.5 | AE74: 13462.6 | AF74: 13917.339 | AG74: 45294.881 | AH74: 5744.3735 | AI74: 16888.78 | AJ74: 80099.539 | AK74: 27707.766 | AL74: 8507.9939 | AM74: 718.5781 | AN74: 30.31687 | AO74: 51938.45 | AP74: 125342.36 | AQ74: 8035.3048 | AR74: 2890.9464 | AS74: 3693.4041 | AT74: 611.92139 | AU74: 2624.7117 | AV74: 1.33782 | AW74: 60.41434 | AX74: 0.145 | AY74: 32708.007 | AZ74: 7238.2811 | BA74: 2.76351 | BB74: 3.39086 | BC74: 819.12562 | BD74: 28.95032 | BE74: 6106.0252 | BF74: 387.59347 | BG74: 1116.5419 | BH74: 214.08637 | BI74: 795.75816 | BJ74: 1918.7941 | BK74: 7756.3564 | BL74: 17577.83 | BM74: 23124.276 | BN74: 7259.2003 | BO74: 4004.1264 | BP74: 2137.2924 | BQ74: 32.41143 | BR74: 22.03902 | BS74: 6125.0552 | BT74: 9540.5087 | BU74: 14353.683 | BV74: 740469.62 | BW74: 51700.071 | BX74: 25303.373 | BY74: 30640.944 | BZ74: 19.43048 | CA74: 85241.904 | CB74: 1853.0144 | CC74: 240.00574 | CD74: 555.20403 | CE74: 95.31599 | CF74: 6183.2373 | CG74: 4430.3179 | CH74: 52307.077 | CI74: 84031.747 | CJ74: 269.74982 | CK74: 50935.433 | CL74: 2215.872 | CM74: 60175.055 | CN74: 9759.1666 | CO74: 1129.097 | CP74: 2.81178 | CQ74: 1413.0756 | CR74: 15329.929 | CS74: 677.81289 | CT74: 11906.3 | CU74: 1453.703 | CV74: 1337.4891 | CW74: 4545182.9
A75: 2026 | B75: 1 | C75: 46023 | D75: 15266.385 | E75: 7581.3346 | F75: 14538.102 | G75: 4621.2943 | H75: 1782.7062 | I75: 186045.67 | J75: 3350.3312 | K75: 232619.02 | L75: 631874.86 | M75: 1386.9674 | N75: 6257.6088 | O75: 5880.0918 | P75: 254.36971 | Q75: 76.28294 | R75: 96909.306 | S75: 1164.2602 | T75: 57994.886 | U75: 29104.861 | V75: 12851.873 | W75: 14219.107 | X75: 65665.943 | Y75: 6285.8663 | Z75: 10252.939 | AA75: 590.57503 | AB75: 1999.3309 | AC75: 31969.012 | AD75: 1362189.9 | AE75: 10370.457 | AF75: 11667.868 | AG75: 24957.208 | AH75: 4047.4692 | AI75: 10508.278 | AJ75: 57257.187 | AK75: 19340.847 | AL75: 5592.2223 | AM75: 0 | AN75: 6.84604 | AO75: 45260.213 | AP75: 146268.16 | AQ75: 4194.8683 | AR75: 1863.618 | AS75: 2596.2783 | AT75: 487.13664 | AU75: 1470.6611 | AV75: 0.26755 | AW75: 149.02454 | AX75: 15.46656 | AY75: 25955.988 | AZ75: 5120.2081 | BA75: 2.73521 | BB75: 0 | BC75: 347.00128 | BD75: 107.68767 | BE75: 4281.8554 | BF75: 559.48075 | BG75: 1108.7086 | BH75: 63.90934 | BI75: 693.90506 | BJ75: 888.19275 | BK75: 3476.1037 | BL75: 15275.639 | BM75: 13136.927 | BN75: 5075.2226 | BO75: 2741.3069 | BP75: 2026.3645 | BQ75: 4.70641 | BR75: 1.56112 | BS75: 5084.0179 | BT75: 5211.9929 | BU75: 10071.737 | BV75: 706447.56 | BW75: 4959.2409 | BX75: 18605.011 | BY75: 33025.526 | BZ75: 1.23122 | CA75: 58239.958 | CB75: 1647.7895 | CC75: 1.54021 | CD75: 145.9905 | CE75: 62.32202 | CF75: 4037.6411 | CG75: 3557.8185 | CH75: 53846.037 | CI75: 64239.272 | CJ75: 217.23767 | CK75: 24048.271 | CL75: 6659.1123 | CM75: 48.52051 | CN75: 6832.964 | CO75: 588.49413 | CP75: 14.54585 | CQ75: 0 | CR75: 11766.918 | CS75: 1313.6332 | CT75: 7600.4641 | CU75: 209.27077 | CV75: 515.0905 | CW75: 4258653.7
A76: 2026 | B76: 1 | C76: 46054 | D76: 7162.1603 | E76: 9232.6647 | F76: 13196.446 | G76: 5576.0131 | H76: 3803.6045 | I76: 218122.6 | J76: 4182.7004 | K76: 262444.59 | L76: 415416.71 | M76: 1713.6589 | N76: 4614.9223 | O76: 4852.6249 | P76: 224.25683 | Q76: 250.74842 | R76: 122016.39 | S76: 832.64792 | T76: 59037.117 | U76: 19648.366 | V76: 15895.797 | W76: 15614.556 | X76: 66452.578 | Y76: 8972.1693 | Z76: 10004.371 | AA76: 1155.1579 | AB76: 2986.2411 | AC76: 78622.11 | AD76: 1260797.3 | AE76: 11064.794 | AF76: 15469.887 | AG76: 34715.956 | AH76: 4117.034 | AI76: 13407.574 | AJ76: 63200.271 | AK76: 24843.702 | AL76: 7610.0335 | AM76: 0 | AN76: 34.85441 | AO76: 39958.907 | AP76: 125601.72 | AQ76: 6629.1833 | AR76: 3040.1241 | AS76: 2970.6324 | AT76: 364.23931 | AU76: 2444.0238 | AV76: 1.83944 | AW76: 81.34872 | AX76: 0 | AY76: 27940.261 | AZ76: 5815.9892 | BA76: 0.1 | BB76: 1.02891 | BC76: 685.76681 | BD76: 92.2286 | BE76: 3754.6522 | BF76: 1190.3126 | BG76: 1051.2135 | BH76: 27.22977 | BI76: 433.12901 | BJ76: 1748.9167 | BK76: 3749.7026 | BL76: 16092.803 | BM76: 15988.201 | BN76: 6508.8911 | BO76: 2667.3184 | BP76: 1554.7432 | BQ76: 24.23063 | BR76: 70.90057 | BS76: 6281.3401 | BT76: 7422.8614 | BU76: 13227.531 | BV76: 807289.03 | BW76: 4705.3118 | BX76: 21258.962 | BY76: 32968.352 | BZ76: 0.95642 | CA76: 59647.813 | CB76: 1435.3446 | CC76: 189.43752 | CD76: 200.32633 | CE76: 86.27954 | CF76: 6246.7951 | CG76: 3982.8901 | CH76: 41077.737 | CI76: 65171.979 | CJ76: 333.77302 | CK76: 42358.196 | CL76: 3292.7811 | CM76: 2535.7437 | CN76: 7233.9006 | CO76: 194.28973 | CP76: 0.73698 | CQ76: 1706.4697 | CR76: 12719.513 | CS76: 1718.4484 | CT76: 9664.3968 | CU76: 196.96491 | CV76: 660.8415 | CW76: 4211591.2
D92: Animales vivos | E92: Carnes y despojos comestibles | F92: Pescados y crustáceos, moluscos e invertebrados acuáticos | G92: Leche y productos lácteos, huevos, miel | H92: Demás productos de origen animal | I92: Plantas vivas y productos de la floricultura | J92: Legumbres y hortalizas, plantas, raíces y tubérculos | K92: Frutos comestibles, cortezas de agrios o melones | L92: Café, té, yerba mate y especias | M92: Cereales | N92: Productos de molinería, malta, almidón y fécula | O92: Semillas y frutos oleaginosos, forrajes | P92: Gomas, resinas, y demás jugos y extractos vegetales | Q92: Materias trenzables y demás productos vegetales | R92: Grasas y aceites animales o vegetales | S92: Preparaciones de carne, pescado, crustáceos, moluscos | T92: Azúcares y artículos confitería | U92: Cacao y sus preparaciones | V92: Preparaciones a base de cereal, harina, leche; pastelería | W92: Preparaciones de legumbres u hortalizas, frutos, otras | X92: Preparaciones alimenticias diversas | Y92: Bebidas, líquidos alcohólicos y vinagre | Z92: Residuos industrias alimentarias. Alimentos para animales | AA92: Tabaco, sucedáneos del tabaco elaborados | AB92: Sal; azufre; tierras y piedras; yesos, cales y cementos | AC92: Minerales, escorias y cenizas | AD92: Combustibles y aceites minerales y sus productos | AE92: Productos químicos inorgánicos | AF92: Productos químicos orgánicos | AG92: Productos farmacéuticos | AH92: Abonos | AI92: Extractos curtientes, pinturas, tintas | AJ92: Aceites esenciales, perfumería, cosméticos | AK92: Jabones, ceras artificiales, pastas | AL92: Materias albuminoideas, colas | AM92: Pólvoras, explosivos, fósforos | AN92: Productos fotográficos, cinematográficos | AO92: Productos diversos de las industrias químicas | AP92: Materias plásticas y manufacturas | AQ92: Caucho y manufacturas | AR92: Pieles y cueros | AS92: Manufacturas de cuero, artículos de viaje, bolsos | AT92: Peletería y confecciones | AU92: Madera, carbón vegetal y manufacturas de madera | AV92: Corcho y sus manufacturas | AW92: Manufactura de espartería y cestería | AX92: Pastas de madera, desperdicios de papel o cartón | AY92: Papel, cartón y sus manufacturas | AZ92: Productos editoriales, prensa, textos | BA92: Seda | BB92: Lana y pelo fino u ordinario; hilados y tejidos de crin | BC92: Algodón | BD92: Demás fibras vegetales, hilados de papel | BE92: Filamentos sintéticos o artificiales | BF92: Fibras sintéticas o artificiales discontinuas | BG92: Guata, fieltro y telas sin tejer; cordeles ,cuerdas, cordajes | BH92: Alfombras y materias textiles | BI92: Tejidos especiales, superficies textiles con pelo | BJ92: Tejidos impregnados, recubiertos | BK92: Tejidos de punto | BL92: Prendas y complementos de vestir, de punto | BM92: Prendas y complementos de vestir, excepto de punto | BN92: Demás artículos textiles confeccionados | BO92: Calzado, botines, artículos análogos y partes | BP92: Artículos de sombrerería y partes | BQ92: Paraguas, bastones, látigos y sus partes | BR92: Plumas, flores artificiales; manufactura de cabellos | BS92: Manufacturas de piedra, yeso, cemento, mica y análogas | BT92: Productos cerámicos | BU92: Vidrio y manufacturas | BV92: Perlas finas, piedras y metales preciosos | BW92: Fundición, hierro y acero | BX92: Manufactura de fundición, de hierro o acero | BY92: Cobre y sus manufacturas | BZ92: Níquel y sus manufacturas | CA92: Aluminio y sus manufacturas | CB92: Plomo y manufacturas | CC92: Zinc y manufacturas | CD92: Estaño y manufacturas | CE92: Demás metales comunes, "cermets" y manufacturas | CF92: Herramientas y útiles, cuchillería y cubiertos | CG92: Manufacturas diversas de metales comunes | CH92: Reactores nucleares, calderas, máquinas y partes | CI92: Aparatos y material eléctrico, de grabación o imagen | CJ92: Vehículos y material para vía férrea, aparatos de señalización | CK92: Vehículos automóviles, tractores, ciclos, partes y accesorios | CL92: Navegación aérea o espacial | CM92: Navegación marítima o fluvial | CN92: Instrumentos y aparatos de óptica, fotografía, cinematografía | CO92: Relojería | CP92: Instrumentos de música, partes y accesorios | CQ92: Armas y municiones, sus partes y accesorios | CR92: Muebles | CS92: Juguetes, artículos para recreo, deporte; partes y accesorios | CT92: Manufacturas diversas | CU92: Objetos de arte, de colección o de antigüedad | CV92: Disposiciones de tratamiento especial | CW92: Total exportaciones
B93: 2020 | C93: I | D93: =SUM(D3:D5) -> 32364.594 | E93: =SUM(E3:E5) -> 26160.503 | F93: =SUM(F3:F5) -> 26782.184 | G93: =SUM(G3:G5) -> 2319.8491 | H93: =SUM(H3:H5) -> 8785.4061 | I93: =SUM(I3:I5) -> 432903.15 | J93: =SUM(J3:J5) -> 6987.9861 | K93: =SUM(K3:K5) -> 344561.09 | ... CW93: =SUM(CW3:CW5) -> 8802127
C94: II | D94: =SUM(D6:D8) -> 40739.157 | E94: =SUM(E6:E8) -> 26445.971 | F94: =SUM(F6:F8) -> 27300.232 | G94: =SUM(G6:G8) -> 3666.1692 | H94: =SUM(H6:H8) -> 8024.1635 | I94: =SUM(I6:I8) -> 355008.92 | J94: =SUM(J6:J8) -> 5180.4593 | K94: =SUM(K6:K8) -> 287712.09 | ... CW94: =SUM(CW6:CW8) -> 6374892.4
C95: III | D95: =SUM(D9:D11) -> 28098.665 | E95: =SUM(E9:E11) -> 29200.774 | F95: =SUM(F9:F11) -> 36626.916 | G95: =SUM(G9:G11) -> 3653.8095 | H95: =SUM(H9:H11) -> 8672.1873 | I95: =SUM(I9:I11) -> 309482.6 | J95: =SUM(J9:J11) -> 5127.1557 | K95: =SUM(K9:K11) -> 257624 | ... CW95: =SUM(CW9:CW11) -> 7681628.6
C96: IV | D96: =SUM(D12:D14) -> 50366.248 | E96: =SUM(E12:E14) -> 44571.201 | F96: =SUM(F12:F14) -> 35619.743 | G96: =SUM(G12:G14) -> 7076.5874 | H96: =SUM(H12:H14) -> 9318.4679 | I96: =SUM(I12:I14) -> 333938.64 | J96: =SUM(J12:J14) -> 6776.915 | K96: =SUM(K12:K14) -> 394376 | ... CW96: =SUM(CW12:CW14) -> 8197162.6
B97: 2021 | C97: I | D97: =SUM(D15:D17) -> 58416.019 | E97: =SUM(E15:E17) -> 54265.642 | F97: =SUM(F15:F17) -> 27188.765 | G97: =SUM(G15:G17) -> 6207.3396 | H97: =SUM(H15:H17) -> 11070.81 | I97: =SUM(I15:I17) -> 489326.83 | J97: =SUM(J15:J17) -> 6647.733 | K97: =SUM(K15:K17) -> 346631.96 | ... CW97: =SUM(CW15:CW17) -> 8933484.6
C98: II | D98: =SUM(D18:D20) -> 29931.206 | E98: =SUM(E18:E20) -> 45698.933 | F98: =SUM(F18:F20) -> 33892.067 | G98: =SUM(G18:G20) -> 8931.452 | H98: =SUM(H18:H20) -> 11723.359 | I98: =SUM(I18:I20) -> 490635.68 | J98: =SUM(J18:J20) -> 5931.9024 | K98: =SUM(K18:K20) -> 383788.37 | ... CW98: =SUM(CW18:CW20) -> 9255501.3
C99: III | D99: =SUM(D21:D23) -> 21429.549 | E99: =SUM(E21:E23) -> 77822.983 | F99: =SUM(F21:F23) -> 31543.863 | G99: =SUM(G21:G23) -> 8493.0839 | H99: =SUM(H21:H23) -> 12349.176 | I99: =SUM(I21:I23) -> 318862.64 | J99: =SUM(J21:J23) -> 5720.6685 | K99: =SUM(K21:K23) -> 344311.21 | ... CW99: =SUM(CW21:CW23) -> 10701536
C100: IV | D100: =SUM(D24:D26) -> 50948.433 | E100: =SUM(E24:E26) -> 73216.911 | F100: =SUM(F24:F26) -> 37250.223 | G100: =SUM(G24:G26) -> 5600.4592 | H100: =SUM(H24:H26) -> 12734.123 | I100: =SUM(I24:I26) -> 457272.27 | J100: =SUM(J24:J26) -> 6066.3782 | K100: =SUM(K24:K26) -> 334692.67 | ... CW100: =SUM(CW24:CW26) -> 12499467
B101: 2022 | C101: I | D101: =SUM(D27:D29) -> 119381.13 | E101: =SUM(E27:E29) -> 45468.786 | F101: =SUM(F27:F29) -> 30171.778 | G101: =SUM(G27:G29) -> 3237.0335 | H101: =SUM(H27:H29) -> 13632.127 | I101: =SUM(I27:I29) -> 625035.1 | J101: =SUM(J27:J29) -> 7440.4275 | K101: =SUM(K27:K29) -> 328438.46 | ... CW101: =SUM(CW27:CW29) -> 12791017
C102: II | D102: =SUM(D30:D32) -> 83798.314 | E102: =SUM(E30:E32) -> 35014.69 | F102: =SUM(F30:F32) -> 34652.806 | G102: =SUM(G30:G32) -> 4985.1168 | H102: =SUM(H30:H32) -> 13932.748 | I102: =SUM(I30:I32) -> 616996.5 | J102: =SUM(J30:J32) -> 6646.3065 | K102: =SUM(K30:K32) -> 434005.52 | ... CW102: =SUM(CW30:CW32) -> 15620668
C103: III | D103: =SUM(D33:D35) -> 43378.434 | E103: =SUM(E33:E35) -> 63218.96 | F103: =SUM(F33:F35) -> 40807.365 | G103: =SUM(G33:G35) -> 6968.9573 | H103: =SUM(H33:H35) -> 15002.635 | I103: =SUM(I33:I35) -> 414431.32 | J103: =SUM(J33:J35) -> 5512.1827 | K103: =SUM(K33:K35) -> 355809.05 | ... CW103: =SUM(CW33:CW35) -> 15080938
C104: IV | D104: =SUM(D36:D38) -> 74173.011 | E104: =SUM(E36:E38) -> 49914.371 | F104: =SUM(F36:F38) -> 46399.701 | G104: =SUM(G36:G38) -> 7705.1936 | H104: =SUM(H36:H38) -> 16164.408 | I104: =SUM(I36:I38) -> 426376.93 | J104: =SUM(J36:J38) -> 7617.0233 | K104: =SUM(K36:K38) -> 357540.38 | ... CW104: =SUM(CW36:CW38) -> 13417514
B105: 2023 | C105: I | D105: =SUM(D39:D41) -> 53553.942 | E105: =SUM(E39:E41) -> 38275.591 | F105: =SUM(F39:F41) -> 32929.891 | G105: =SUM(G39:G41) -> 6324.4426 | H105: =SUM(H39:H41) -> 15516.116 | I105: =SUM(I39:I41) -> 600144.09 | J105: =SUM(J39:J41) -> 9937.9174 | K105: =SUM(K39:K41) -> 273647.64 | ... CW105: =SUM(CW39:CW41) -> 12437259
C106: II | D106: =SUM(D42:D44) -> 69465.856 | E106: =SUM(E42:E44) -> 33834.756 | F106: =SUM(F42:F44) -> 52807.95 | G106: =SUM(G42:G44) -> 7143.8134 | H106: =SUM(H42:H44) -> 13021.417 | I106: =SUM(I42:I44) -> 547177.22 | J106: =SUM(J42:J44) -> 8146.7503 | K106: =SUM(K42:K44) -> 382624.77 | ... CW106: =SUM(CW42:CW44) -> 12258495
C107: III | D107: =SUM(D45:D47) -> 34733.871 | E107: =SUM(E45:E47) -> 17095.099 | F107: =SUM(F45:F47) -> 41680.343 | G107: =SUM(G45:G47) -> 5430.319 | H107: =SUM(H45:H47) -> 14404.323 | I107: =SUM(I45:I47) -> 487855.02 | J107: =SUM(J45:J47) -> 7807.5184 | K107: =SUM(K45:K47) -> 296164.62 | ... CW107: =SUM(CW45:CW47) -> 12278856
C108: IV | D108: =SUM(D48:D50) -> 84209.019 | E108: =SUM(E48:E50) -> 27894.349 | F108: =SUM(F48:F50) -> 35974.367 | G108: =SUM(G48:G50) -> 6026.0631 | H108: =SUM(H48:H50) -> 15702.664 | I108: =SUM(I48:I50) -> 479973.61 | J108: =SUM(J48:J50) -> 9546.3602 | K108: =SUM(K48:K50) -> 398049.13 | ... CW108: =SUM(CW48:CW50) -> 12794516
B109: 2024 | C109: I | D109: =SUM(D51:D53) -> 79296.297 | E109: =SUM(E51:E53) -> 20881.878 | F109: =SUM(F51:F53) -> 40754.086 | G109: =SUM(G51:G53) -> 11111.666 | H109: =SUM(H51:H53) -> 13433.436 | I109: =SUM(I51:I53) -> 646885.34 | J109: =SUM(J51:J53) -> 11930.986 | K109: =SUM(K51:K53) -> 442071.39 | ... CW109: =SUM(CW51:CW53) -> 11299021
C110: II | D110: =SUM(D54:D56) -> 27137.444 | E110: =SUM(E54:E56) -> 18997.967 | F110: =SUM(F54:F56) -> 34805.427 | G110: =SUM(G54:G56) -> 17044.835 | H110: =SUM(H54:H56) -> 14828.073 | I110: =SUM(I54:I56) -> 642042.39 | J110: =SUM(J54:J56) -> 9643.2526 | K110: =SUM(K54:K56) -> 530106.37 | ... CW110: =SUM(CW54:CW56) -> 12719069
C111: III | D111: =SUM(D57:D59) -> 27273.443 | E111: =SUM(E57:E59) -> 31916.66 | F111: =SUM(F57:F59) -> 42065.817 | G111: =SUM(G57:G59) -> 15930.876 | H111: =SUM(H57:H59) -> 17510.494 | I111: =SUM(I57:I59) -> 542754.04 | J111: =SUM(J57:J59) -> 7690.2969 | K111: =SUM(K57:K59) -> 405056.66 | ... CW111: =SUM(CW57:CW59) -> 12622688
C112: IV | D112: =SUM(D60:D62) -> 65975.086 | E112: =SUM(E60:E62) -> 50160.032 | F112: =SUM(F60:F62) -> 26758.717 | G112: =SUM(G60:G62) -> 14244.103 | H112: =SUM(H60:H62) -> 10457.423 | I112: =SUM(I60:I62) -> 554163.98 | J112: =SUM(J60:J62) -> 10772.227 | K112: =SUM(K60:K62) -> 444972.61 | ... CW112: =SUM(CW60:CW62) -> 12915744
B113: 2025 | C113: I | D113: =SUM(D63:D65) -> 70700.733 | E113: =SUM(E64:E66) -> 48642.43 | F113: =SUM(F64:F66) -> 34379.02 | G113: =SUM(G64:G66) -> 18095.989 | H113: =SUM(H64:H66) -> 10800.918 | I113: =SUM(I64:I66) -> 710421.48 | J113: =SUM(J64:J66) -> 10438.283 | K113: =SUM(K64:K66) -> 538411.33 | L113: =SUM(L64:L66) -> 1468517.4 | ... CW113: =SUM(CW64:CW66) -> 12297506
C114: II | D114: =SUM(D66:D68) -> 40217.529 | E114: =SUM(E66:E68) -> 32351.041 | F114: =SUM(F66:F68) -> 52890.248 | G114: =SUM(G66:G68) -> 13708.27 | H114: =SUM(H66:H68) -> 15390.999 | I114: =SUM(I66:I68) -> 711459.1 | J114: =SUM(J66:J68) -> 8649.678 | K114: =SUM(K66:K68) -> 636607.13 | ... CW114: =SUM(CW66:CW68) -> 12434492
C115: III | D115: =SUM(D69:D71) -> 54514.07 | E115: =SUM(E69:E71) -> 43008.129 | F115: =SUM(F69:F71) -> 37372.325 | G115: =SUM(G69:G71) -> 14817.644 | H115: =SUM(H69:H71) -> 14081.084 | I115: =SUM(I69:I71) -> 475266.12 | J115: =SUM(J69:J71) -> 8498.6157 | K115: =SUM(K69:K71) -> 543705.55 | ... AQ115: =SUM(AQ69:AQ71) -> 27734.814 | AR115: =SUM(AR63:AR65) -> 8732.7642 | AS115: =SUM(AS63:AS65) -> 11814.756 | AT115: =SUM(AT63:AT65) -> 1359.6001 | AU115: =SUM(AU63:AU65) -> 11399.431 | AV115: =SUM(AV63:AV65) -> 82.42698 | AW115: =SUM(AW63:AW65) -> 392.10358 | AX115: =SUM(AX63:AX65) -> 839.11831 | AY115: =SUM(AY63:AY65) -> 108891.95 | ... CW115: =SUM(CW63:CW65) -> 11954818
C116: IV | D116: =+SUM(D72:D74) -> 32944.977 | E116: =+SUM(E72:E74) -> 30415.602 | F116: =+SUM(F72:F74) -> 44913.079 | G116: =+SUM(G72:G74) -> 22989.698 | H116: =+SUM(H72:H74) -> 10979.791 | I116: =+SUM(I72:I74) -> 548649.11 | J116: =+SUM(J72:J74) -> 9381.7915 | K116: =+SUM(K72:K74) -> 575568.68 | ... CW116: =+SUM(CW72:CW74) -> 12862825
B119: crecimientos | D119: Animales vivos | E119: Carnes y despojos comestibles | F119: Pescados y crustáceos, moluscos e invertebrados acuáticos | G119: Leche y productos lácteos, huevos, miel | H119: Demás productos de origen animal | I119: Plantas vivas y productos de la floricultura | J119: Legumbres y hortalizas, plantas, raíces y tubérculos | K119: Frutos comestibles, cortezas de agrios o melones | L119: Café, té, yerba mate y especias | M119: Cereales | N119: Productos de molinería, malta, almidón y fécula | O119: Semillas y frutos oleaginosos, forrajes | P119: Gomas, resinas, y demás jugos y extractos vegetales | Q119: Materias trenzables y demás productos vegetales | R119: Grasas y aceites animales o vegetales | S119: Preparaciones de carne, pescado, crustáceos, moluscos | T119: Azúcares y artículos confitería | U119: Cacao y sus preparaciones | V119: Preparaciones a base de cereal, harina, leche; pastelería | W119: Preparaciones de legumbres u hortalizas, frutos, otras | X119: Preparaciones alimenticias diversas | Y119: Bebidas, líquidos alcohólicos y vinagre | Z119: Residuos industrias alimentarias. Alimentos para animales | AA119: Tabaco, sucedáneos del tabaco elaborados | AB119: Sal; azufre; tierras y piedras; yesos, cales y cementos | AC119: Minerales, escorias y cenizas | AD119: Combustibles y aceites minerales y sus productos | AE119: Productos químicos inorgánicos | AF119: Productos químicos orgánicos | AG119: Productos farmacéuticos | AH119: Abonos | AI119: Extractos curtientes, pinturas, tintas | AJ119: Aceites esenciales, perfumería, cosméticos | AK119: Jabones, ceras artificiales, pastas | AL119: Materias albuminoideas, colas | AM119: Pólvoras, explosivos, fósforos | AN119: Productos fotográficos, cinematográficos | AO119: Productos diversos de las industrias químicas | AP119: Materias plásticas y manufacturas | AQ119: Caucho y manufacturas | AR119: Pieles y cueros | AS119: Manufacturas de cuero, artículos de viaje, bolsos | AT119: Peletería y confecciones | AU119: Madera, carbón vegetal y manufacturas de madera | AV119: Corcho y sus manufacturas | AW119: Manufactura de espartería y cestería | AX119: Pastas de madera, desperdicios de papel o cartón | AY119: Papel, cartón y sus manufacturas | AZ119: Productos editoriales, prensa, textos | BA119: Seda | BB119: Lana y pelo fino u ordinario; hilados y tejidos de crin | BC119: Algodón | BD119: Demás fibras vegetales, hilados de papel | BE119: Filamentos sintéticos o artificiales | BF119: Fibras sintéticas o artificiales discontinuas | BG119: Guata, fieltro y telas sin tejer; cordeles ,cuerdas, cordajes | BH119: Alfombras y materias textiles | BI119: Tejidos especiales, superficies textiles con pelo | BJ119: Tejidos impregnados, recubiertos | BK119: Tejidos de punto | BL119: Prendas y complementos de vestir, de punto | BM119: Prendas y complementos de vestir, excepto de punto | BN119: Demás artículos textiles confeccionados | BO119: Calzado, botines, artículos análogos y partes | BP119: Artículos de sombrerería y partes | BQ119: Paraguas, bastones, látigos y sus partes | BR119: Plumas, flores artificiales; manufactura de cabellos | BS119: Manufacturas de piedra, yeso, cemento, mica y análogas | BT119: Productos cerámicos | BU119: Vidrio y manufacturas | BV119: Perlas finas, piedras y metales preciosos | BW119: Fundición, hierro y acero | BX119: Manufactura de fundición, de hierro o acero | BY119: Cobre y sus manufacturas | BZ119: Níquel y sus manufacturas | CA119: Aluminio y sus manufacturas | CB119: Plomo y manufacturas | CC119: Zinc y manufacturas | CD119: Estaño y manufacturas | CE119: Demás metales comunes, "cermets" y manufacturas | CF119: Herramientas y útiles, cuchillería y cubiertos | CG119: Manufacturas diversas de metales comunes | CH119: Reactores nucleares, calderas, máquinas y partes | CI119: Aparatos y material eléctrico, de grabación o imagen | CJ119: Vehículos y material para vía férrea, aparatos de señalización | CK119: Vehículos automóviles, tractores, ciclos, partes y accesorios | CL119: Navegación aérea o espacial | CM119: Navegación marítima o fluvial | CN119: Instrumentos y aparatos de óptica, fotografía, cinematografía | CO119: Relojería | CP119: Instrumentos de música, partes y accesorios | CQ119: Armas y municiones, sus partes y accesorios | CR119: Muebles | CS119: Juguetes, artículos para recreo, deporte; partes y accesorios | CT119: Manufacturas diversas | CU119: Objetos de arte, de colección o de antigüedad | CV119: Disposiciones de tratamiento especial
B120: 2021 | C120: I | D120: =+(D97/D93)-1 -> 0.80493593 | E120: =+(E97/E93)-1 -> 1.0743348 | F120: =+(F97/F93)-1 -> 0.015180991 | G120: =+(G97/G93)-1 -> 1.6757514 | H120: =+(H97/H93)-1 -> 0.26013645 | I120: =+(I97/I93)-1 -> 0.13033789 | J120: =+(J97/J93)-1 -> -0.048691147 | K120: =+(K97/K93)-1 -> 0.0060101604 | ... CW120: =+(CW97/CW93)-1 -> 0.01492339
C121: II | D121: =+(D98/D94)-1 -> -0.26529639 | E121: =+(E98/E94)-1 -> 0.72801115 | F121: =+(F98/F94)-1 -> 0.24145712 | G121: =+(G98/G94)-1 -> 1.436181 | H121: =+(H98/H94)-1 -> 0.46100703 | I121: =+(I98/I94)-1 -> 0.3820376 | J121: =+(J98/J94)-1 -> 0.14505337 | K121: =+(K98/K94)-1 -> 0.333932 | ... CW121: =+(CW98/CW94)-1 -> 0.45186785
C122: III | D122: =+(D99/D95)-1 -> -0.23734634 | E122: =+(E99/E95)-1 -> 1.6651001 | F122: =+(F99/F95)-1 -> -0.13877917 | G122: =+(G99/G95)-1 -> 1.3244463 | H122: =+(H99/H95)-1 -> 0.42399785 | I122: =+(I99/I95)-1 -> 0.030308785 | J122: =+(J99/J95)-1 -> 0.11575868 | K122: =+(K99/K95)-1 -> 0.33648732 | ... CW122: =+(CW99/CW95)-1 -> 0.39313378
C123: IV | D123: =+(D100/D96)-1 -> 0.011559022 | E123: =+(E100/E96)-1 -> 0.64269549 | F123: =+(F100/F96)-1 -> 0.045774618 | G123: =+(G100/G96)-1 -> -0.20859322 | H123: =+(H100/H96)-1 -> 0.36654684 | I123: =+(I100/I96)-1 -> 0.36933023 | J123: =+(J100/J96)-1 -> -0.10484664 | K123: =+(K100/K96)-1 -> -0.15133613 | ... CW123: =+(CW100/CW96)-1 -> 0.52485286
B124: 2022 | C124: I | D124: =+(D101/D97)-1 -> 1.0436369 | E124: =+(E101/E97)-1 -> -0.16210729 | F124: =+(F101/F97)-1 -> 0.10971492 | G124: =+(G101/G97)-1 -> -0.47851516 | H124: =+(H101/H97)-1 -> 0.2313576 | I124: =+(I101/I97)-1 -> 0.27733667 | J124: =+(J101/J97)-1 -> 0.11924282 | K124: =+(K101/K97)-1 -> -0.052486511 | ... CW124: =+(CW101/CW97)-1 -> 0.43180598
C125: II | D125: =+(D102/D98)-1 -> 1.7996972 | E125: =+(E102/E98)-1 -> -0.23379634 | F125: =+(F102/F98)-1 -> 0.02244591 | G125: =+(G102/G98)-1 -> -0.44184699 | H125: =+(H102/H98)-1 -> 0.18846037 | I125: =+(I102/I98)-1 -> 0.25754511 | J125: =+(J102/J98)-1 -> 0.12043422 | K125: =+(K102/K98)-1 -> 0.13084593 | ... CW125: =+(CW102/CW98)-1 -> 0.68771715
C126: III | D126: =+(D103/D99)-1 -> 1.0242345 | E126: =+(E103/E99)-1 -> -0.18765694 | F126: =+(F103/F99)-1 -> 0.29367049 | G126: =+(G103/G99)-1 -> -0.17945502 | H126: =+(H103/H99)-1 -> 0.21486927 | I126: =+(I103/I99)-1 -> 0.2997174 | J126: =+(J103/J99)-1 -> -0.036444297 | K126: =+(K103/K99)-1 -> 0.033393738 | ... CW126: =+(CW103/CW99)-1 -> 0.40923112
...

Sheet Exportaciones tradicionales
V2: Bimestrallll
A3: MES | C3: Exportaciones tradicionales | Q3: Exportaciones no tradicionales | S3: Total exportaciones
C4: Café1 | F4: Carbón | I4: Petróleo y sus derivados | L4: Ferroníquel | O4: Total Exportaciones Tradicionales | T4: Perlas finas, piedras y metales preciosos | U4: Materias plásticas y manufacturas | V4: Plantas vivas y productos de la floricultura
C5: Miles de Dólares FOB | D5: Toneladas Métricas | F5: Miles de Dólares FOB | G5: Toneladas Métricas | I5: Miles de Dólares FOB | J5: Toneladas Métricas | L5: Miles de Dólares FOB | M5: Toneladas Métricas | O5: Miles de Dólares FOB | Q5: Miles de Dólares FOB | S5: Miles de Dólares FOB
A6: 43466 | B6: =YEAR(A6)&"-B"&INT((MONTH(A6)-1)/2)+1 -> 2019-B1 | C6: 252393.74 | D6: 80910.795 | F6: 456344.09 | G6: 5236729.3 | I6: 1159103.9 | J6: 3202169 | L6: 63598.803 | M6: 17725.022 | O6: 1931440.5 | Q6: 1134670 | S6: 3066110.5 | T6: 128747.47 | U6: 117959.27 | V6: 101820.18
A7: 43497 | B7: =YEAR(A7)&"-B"&INT((MONTH(A7)-1)/2)+1 -> 2019-B1 | C7: 201820.62 | D7: 66546.231 | F7: 609045.26 | G7: 6625955.8 | I7: 1115553.8 | J7: 2895705.5 | L7: 0 | M7: 0 | O7: 1926419.7 | Q7: 1256651.7 | S7: 3183071.4 | T7: 142045.09 | U7: 150375.67 | V7: 159516.65
A8: 43525 | B8: =YEAR(A8)&"-B"&INT((MONTH(A8)-1)/2)+1 -> 2019-B2 | C8: 186450.8 | D8: 62264.209 | F8: 465098.27 | G8: 5569819.5 | I8: 1450174.6 | J8: 3507420.9 | L8: 56049.791 | M8: 16773.581 | O8: 2157773.5 | Q8: 1187076.7 | S8: 3344850.1 | T8: 166904.13 | U8: 93939.808 | V8: 152037.52 | Z8: mes | AA8: Café | AB8: Carbón | AC8: Petróleo y derivados | AD8: Ferroníquel | AE8: Piedras y metales preciosos | AF8: Industria plástica | AG8: Floricultutra | AH8: Exportaciones tradicionales (eje derecho) | AI8: Exportaciones no tradicionales (eje derecho)
A9: 43556 | B9: =YEAR(A9)&"-B"&INT((MONTH(A9)-1)/2)+1 -> 2019-B2 | C9: 177457.84 | D9: 60374.852 | F9: 607264.14 | G9: 7066194.6 | I9: 1697742.8 | J9: 3780516.1 | L9: 60144.976 | M9: 17081.443 | O9: 2542609.8 | Q9: 1320209.4 | S9: 3862819.2 | T9: 145449.12 | U9: 129740.9 | V9: 107992.17 | Z9: =+A30 -> 44197 | AA9: =+C30/$S30 -> 0.094981275 | AB9: =+F30/$S30 -> 0.096179441 | AC9: =+I30/$S30 -> 0.35637591 | AD9: =+L30/$S30 -> 0.01282218 | AE9: =+T30/$S30 -> 0.073191982 | AF9: =+U30/$S30 -> 0.050085656 | AG9: =+V30/$S30 -> 0.049887236 | AH9: =+O30/$S30 -> 0.5603588 | AI9: =+Q30/$S30 -> 0.4396412
A10: 43586 | B10: =YEAR(A10)&"-B"&INT((MONTH(A10)-1)/2)+1 -> 2019-B3 | C10: 136462.17 | D10: 47680.55 | F10: 738893.25 | G10: 9335672.4 | I10: 1461780.9 | J10: 3329993.6 | L10: 6881.3862 | M10: 1724.422 | O10: 2344017.8 | Q10: 1404324.1 | S10: 3748341.8 | T10: 136905.46 | U10: 141614.37 | V10: 182186.61 | Z10: =+A31 -> 44228 | AA10: =+C31/$S31 -> 0.088405249 | AB10: =+F31/$S31 -> 0.15137803 | AC10: =+I31/$S31 -> 0.27465494 | AD10: =+L31/$S31 -> 0.0097445113 | AE10: =+T31/$S31 -> 0.088855166 | AF10: =+U31/$S31 -> 0.054120735 | AG10: =+V31/$S31 -> 0.052539949 | AH10: =+O31/$S31 -> 0.52418272 | AI10: =+Q31/$S31 -> 0.47581728
A11: 43617 | B11: =YEAR(A11)&"-B"&INT((MONTH(A11)-1)/2)+1 -> 2019-B3 | C11: 144177.55 | D11: 50519.851 | F11: 356479.26 | G11: 4691960.1 | I11: 1460751.9 | J11: 3571548.7 | L11: 25252.272 | M11: 6726.507 | O11: 1986661 | Q11: 1109701.5 | S11: 3096362.5 | T11: 114324.37 | U11: 104237.78 | V11: 134215.52 | Z11: =+A32 -> 44256 | AA11: =+C32/$S32 -> 0.078867677 | AB11: =+F32/$S32 -> 0.078262102 | AC11: =+I32/$S32 -> 0.33533437 | AD11: =+L32/$S32 -> 0.0087739205 | AE11: =+T32/$S32 -> 0.082616382 | AF11: =+U32/$S32 -> 0.044365569 | AG11: =+V32/$S32 -> 0.060486643 | AH11: =+O32/$S32 -> 0.50123807 | AI11: =+Q32/$S32 -> 0.49876193
A12: 43647 | B12: =YEAR(A12)&"-B"&INT((MONTH(A12)-1)/2)+1 -> 2019-B4 | C12: 197570.55 | D12: 67112.153 | F12: 457092.32 | G12: 6133746.3 | I12: 1287045.7 | J12: 3166077.2 | L12: 38057.979 | M12: 10638.743 | O12: 1979766.5 | Q12: 1276063.3 | S12: 3255829.8 | T12: 148681.77 | U12: 134880.36 | V12: 108351.44 | Z12: =+A33 -> 44287 | AA12: =+C33/$S33 -> 0.078788673 | AB12: =+F33/$S33 -> 0.11455438 | AC12: =+I33/$S33 -> 0.28971527 | AD12: =+L33/$S33 -> 0.010547752 | AE12: =+T33/$S33 -> 0.091387832 | AF12: =+U33/$S33 -> 0.056261906 | AG12: =+V33/$S33 -> 0.049492187 | AH12: =+O33/$S33 -> 0.49360607 | AI12: =+Q33/$S33 -> 0.50639393
A13: 43678 | B13: =YEAR(A13)&"-B"&INT((MONTH(A13)-1)/2)+1 -> 2019-B4 | C13: 212269.11 | D13: 69276.52 | F13: 366567.06 | G13: 5399812.7 | I13: 1337217.8 | J13: 3517813.4 | L13: 70158.364 | M13: 19135.39 | O13: 1986212.3 | Q13: 1278048.9 | S13: 3264261.2 | T13: 195240.71 | U13: 113397.43 | V13: 128067.22 | Z13: =+A34 -> 44317 | AA13: =+C34/$S34 -> 0.037686331 | AB13: =+F34/$S34 -> 0.10837063 | AC13: =+I34/$S34 -> 0.39203834 | AD13: =+L34/$S34 -> 0.0081867338 | AE13: =+T34/$S34 -> 0.097579973 | AF13: =+U34/$S34 -> 0.045510049 | AG13: =+V34/$S34 -> 0.070209053 | AH13: =+O34/$S34 -> 0.54628203 | AI13: =+Q34/$S34 -> 0.45371797
A14: 43709 | B14: =YEAR(A14)&"-B"&INT((MONTH(A14)-1)/2)+1 -> 2019-B5 | C14: 160152.42 | D14: 51934.43 | F14: 438470.92 | G14: 6264712.6 | I14: 1178230 | J14: 3038953.7 | L14: 28369.53 | M14: 7217.378 | O14: 1805222.9 | Q14: 1262126 | S14: 3067348.8 | T14: 193313.41 | U14: 132117.77 | V14: 94178.691 | Z14: =+A35 -> 44348 | AA14: =+C35/$S35 -> 0.033776627 | AB14: =+F35/$S35 -> 0.13079772 | AC14: =+I35/$S35 -> 0.35901918 | AD14: =+L35/$S35 -> 0.012244753 | AE14: =+T35/$S35 -> 0.089965479 | AF14: =+U35/$S35 -> 0.051899669 | AG14: =+V35/$S35 -> 0.039562735 | AH14: =+O35/$S35 -> 0.53583828 | AI14: =+Q35/$S35 -> 0.46416172
A15: 43739 | B15: =YEAR(A15)&"-B"&INT((MONTH(A15)-1)/2)+1 -> 2019-B5 | C15: 187881.4 | D15: 60639.151 | F15: 450063.96 | G15: 7037648.6 | I15: 1262664.7 | J15: 3295378.2 | L15: 103043.93 | M15: 21837.514 | O15: 2003654 | Q15: 1322843.2 | S15: 3326497.2 | T15: 170332.34 | U15: 133857.01 | V15: 104041.46 | Z15: =+A36 -> 44378 | AA15: =+C36/$S36 -> 0.08693427 | AB15: =+F36/$S36 -> 0.12125479 | AC15: =+I36/$S36 -> 0.28977495 | AD15: =+L36/$S36 -> 0.01258748 | AE15: =+T36/$S36 -> 0.090958615 | AF15: =+U36/$S36 -> 0.050845931 | AG15: =+V36/$S36 -> 0.031000287 | AH15: =+O36/$S36 -> 0.51055149 | AI15: =+Q36/$S36 -> 0.48944851
A16: 43770 | B16: =YEAR(A16)&"-B"&INT((MONTH(A16)-1)/2)+1 -> 2019-B6 | C16: 189894.54 | D16: 61253.905 | E16: 0 | F16: 313264.87 | G16: 4942908.3 | H16: 0 | I16: 1212852.7 | J16: 3118168.5 | K16: 0 | L16: 12231.529 | M16: 2384.134 | O16: 1728243.7 | Q16: 1215381 | S16: 2943624.7 | T16: 168606.71 | U16: 112233.64 | V16: 121440.73 | Z16: =+A37 -> 44409 | AA16: =+C37/$S37 -> 0.090951295 | AB16: =+F37/$S37 -> 0.13916906 | AC16: =+I37/$S37 -> 0.29689699 | AD16: =+L37/$S37 -> 0.012246584 | AE16: =+T37/$S37 -> 0.065162086 | AF16: =+U37/$S37 -> 0.050974301 | AG16: =+V37/$S37 -> 0.033068276 | AH16: =+O37/$S37 -> 0.53926393 | AI16: =+Q37/$S37 -> 0.46073607
A17: 43800 | B17: =YEAR(A17)&"-B"&INT((MONTH(A17)-1)/2)+1 -> 2019-B6 | C17: 235143.52 | D17: 74733.997 | E17: 0 | F17: 409745.59 | G17: 6391073.7 | H17: 0 | I17: 1338834.5 | J17: 3399086.4 | K17: 0 | L17: 81235.195 | M17: 17976.078 | O17: 2064958.8 | Q17: 1265091.7 | S17: 3330050.5 | T17: 251290.31 | U17: 107472.47 | V17: 101787.95 | Z17: =+A38 -> 44440 | AA17: =+C38/$S38 -> 0.067621503 | AB17: =+F38/$S38 -> 0.15271803 | AC17: =+I38/$S38 -> 0.33610866 | AD17: =+L38/$S38 -> 0.02894562 | AE17: =+T38/$S38 -> 0.07585477 | AF17: =+U38/$S38 -> 0.042237007 | AG17: =+V38/$S38 -> 0.02571213 | AH17: =+O38/$S38 -> 0.58539381 | AI17: =+Q38/$S38 -> 0.41460619
A18: 43831 | B18: =YEAR(A18)&"-B"&INT((MONTH(A18)-1)/2)+1 -> 2020-B1 | C18: 242391.72 | D18: 73419.94 | E18: 0 | F18: 826543.88 | G18: 14007616 | H18: 0 | I18: 1217174 | J18: 3154713.1 | K18: 0 | L18: 38790.492 | M18: 10129.448 | N18: 0 | O18: 2324900.1 | Q18: 1094565.6 | S18: 3419465.6 | T18: 116520.24 | U18: 100590.09 | V18: 98100.147 | Z18: =+A39 -> 44470 | AA18: =+C39/$S39 -> 0.083801004 | AB18: =+F39/$S39 -> 0.15645457 | AC18: =+I39/$S39 -> 0.34013917 | AD18: =+L39/$S39 -> 0.0009277979 | AE18: =+T39/$S39 -> 0.063778406 | AF18: =+U39/$S39 -> 0.051119698 | AG18: =+V39/$S39 -> 0.039319552 | AH18: =+O39/$S39 -> 0.58132254 | AI18: =+Q39/$S39 -> 0.41867746
A19: 43862 | B19: =YEAR(A19)&"-B"&INT((MONTH(A19)-1)/2)+1 -> 2020-B1 | C19: 208758.8 | D19: 61141.045 | E19: 0 | F19: 460774.28 | G19: 7153940.9 | H19: 0 | I19: 1022315.2 | J19: 3233680.7 | K19: 0 | L19: 1831.5915 | M19: 550.563 | O19: 1693679.8 | Q19: 1249946 | S19: 2943625.8 | T19: 191257.56 | U19: 116884.19 | V19: 180000.25 | Z19: =+A40 -> 44501 | AA19: =+C40/$S40 -> 0.073623225 | AB19: =+F40/$S40 -> 0.15273256 | AC19: =+I40/$S40 -> 0.34244318 | AD19: =+L40/$S40 -> 0.017921707 | AE19: =+T40/$S40 -> 0.07388225 | AF19: =+U40/$S40 -> 0.041974712 | AG19: =+V40/$S40 -> 0.03451273 | AH19: =+O40/$S40 -> 0.58672068 | AI19: =+Q40/$S40 -> 0.41327932
A20: 43891 | B20: =YEAR(A20)&"-B"&INT((MONTH(A20)-1)/2)+1 -> 2020-B2 | C20: 163184.89 | D20: 48317.975 | E20: 0 | F20: 322584.66 | G20: 5931301.4 | H20: 0 | I20: 628250.28 | J20: 3456975.8 | K20: 0 | L20: 49453.259 | M20: 13499.039 | O20: 1163473.1 | Q20: 1275562.5 | S20: 2439035.6 | T20: 203219.03 | U20: 115478.55 | V20: 154802.75 | Z20: =+A41 -> 44531 | AA20: =+C41/$S41 -> 0.079904055 | AB20: =+F41/$S41 -> 0.19595335 | AC20: =+I41/$S41 -> 0.30947853 | AD20: =+L41/$S41 -> 0.014824029 | AE20: =+T41/$S41 -> 0.08299837 | AF20: =+U41/$S41 -> 0.041647994 | AG20: =+V41/$S41 -> 0.03618944 | AH20: =+O41/$S41 -> 0.60015996 | AI20: =+Q41/$S41 -> 0.39984004
A21: 43922 | B21: =YEAR(A21)&"-B"&INT((MONTH(A21)-1)/2)+1 -> 2020-B2 | C21: 146600.07 | D21: 42838.151 | E21: 0 | F21: 317517.09 | G21: 4358397.8 | H21: 0 | I21: 384188.1 | J21: 2823337.4 | K21: 0 | L21: 40804.454 | M21: 11840.677 | O21: 889109.72 | Q21: 975129.11 | S21: 1864238.8 | T21: 125274.17 | U21: 116495.32 | V21: 107589.82 | Z21: =+A42 -> 44562 | AA21: =+C42/$S42 -> 0.084428283 | AB21: =+F42/$S42 -> 0.20407972 | AC21: =+I42/$S42 -> 0.33367347 | AD21: =+L42/$S42 -> 0.015451744 | AE21: =+T42/$S42 -> 0.05007053 | AF21: =+U42/$S42 -> 0.043856707 | AG21: =+V42/$S42 -> 0.03725662 | AH21: =+O42/$S42 -> 0.63763322 | AI21: =+Q42/$S42 -> 0.36236678
A22: 43952 | B22: =YEAR(A22)&"-B"&INT((MONTH(A22)-1)/2)+1 -> 2020-B3 | C22: 134753.52 | D22: 38852.902 | E22: 0 | F22: 378010.53 | G22: 7364539.7 | H22: 0 | I22: 550358.9 | J22: 3287695.7 | K22: 0 | L22: 30939.74 | M22: 10629.186 | O22: 1094062.7 | Q22: 1127108.8 | S22: 2221171.5 | T22: 225502.27 | U22: 84818.214 | V22: 146473.07 | Z22: =+A43 -> 44593 | AA22: =+C43/$S43 -> 0.087981288 | AB22: =+F43/$S43 -> 0.13412779 | AC22: =+I43/$S43 -> 0.33914733 | AD22: =+L43/$S43 -> 0.014082301 | AE22: =+T43/$S43 -> 0.063879502 | AF22: =+U43/$S43 -> 0.041645333 | AG22: =+V43/$S43 -> 0.061709289 | AH22: =+O43/$S43 -> 0.57533871 | AI22: =+Q43/$S43 -> 0.42466129
A23: 43983 | B23: =YEAR(A23)&"-B"&INT((MONTH(A23)-1)/2)+1 -> 2020-B3 | C23: 189164.76 | D23: 54759.207 | E23: 0 | F23: 361445.1 | G23: 6753013.4 | H23: 0 | I23: 559864.01 | J23: 2715498.3 | K23: 0 | L23: 32425.899 | M23: 11374.684 | O23: 1142899.8 | Q23: 1146582.3 | S23: 2289482.1 | T23: 247568.94 | U23: 78733.453 | V23: 100946.03 | Z23: =+A44 -> 44621 | AA23: =+C44/$S44 -> 0.083494053 | AB23: =+F44/$S44 -> 0.12967395 | AC23: =+I44/$S44 -> 0.38330553 | AD23: =+L44/$S44 -> 0.012682471 | AE23: =+T44/$S44 -> 0.052693123 | AF23: =+U44/$S44 -> 0.041975517 | AG23: =+V44/$S44 -> 0.046787358 | AH23: =+O44/$S44 -> 0.609156 | AI23: =+Q44/$S44 -> 0.390844
A24: 44013 | B24: =YEAR(A24)&"-B"&INT((MONTH(A24)-1)/2)+1 -> 2020-B4 | C24: 263302.4 | D24: 76263.174 | E24: 0 | F24: 301451.48 | G24: 5730246.4 | H24: 0 | I24: 635084.92 | J24: 2630195.9 | K24: 0 | L24: 28868.862 | M24: 9730.903 | O24: 1228707.7 | Q24: 1323280.6 | S24: 2551988.3 | T24: 291202.74 | U24: 113001.52 | V24: 107332.64 | Z24: =+A45 -> 44652 | AA24: =+C45/$S45 -> 0.057721627 | AB24: =+F45/$S45 -> 0.24164084 | AC24: =+I45/$S45 -> 0.35749632 | AD24: =+L45/$S45 -> 0.02047554 | AE24: =+T45/$S45 -> 0.046729148 | AF24: =+U45/$S45 -> 0.026418838 | AG24: =+V45/$S45 -> 0.034564376 | AH24: =+O45/$S45 -> 0.67733433 | AI24: =+Q45/$S45 -> 0.32266567
A25: 44044 | B25: =YEAR(A25)&"-B"&INT((MONTH(A25)-1)/2)+1 -> 2020-B4 | C25: 193753.3 | D25: 54843.843 | E25: 0 | F25: 271654.5 | G25: 5141055.3 | H25: 0 | I25: 830555.3 | J25: 3066626.3 | K25: 0 | L25: 41104.534 | M25: 12413.466 | O25: 1337067.6 | Q25: 1247699.1 | S25: 2584766.8 | T25: 287292.99 | U25: 106562.53 | V25: 93201.056 | Z25: =+A46 -> 44682 | AA25: =+C46/$S46 -> 0.056367791 | AB25: =+F46/$S46 -> 0.11567276 | AC25: =+I46/$S46 -> 0.39867339 | AD25: =+L46/$S46 -> 0.017100538 | AE25: =+T46/$S46 -> 0.059152444 | AF25: =+U46/$S46 -> 0.036952347 | AG25: =+V46/$S46 -> 0.05433574 | AH25: =+O46/$S46 -> 0.58781448 | AI25: =+Q46/$S46 -> 0.41218552
A26: 44075 | B26: =YEAR(A26)&"-B"&INT((MONTH(A26)-1)/2)+1 -> 2020-B5 | C26: 211241.67 | D26: 57576.702 | F26: 267370.86 | G26: 4606284.1 | I26: 664441 | J26: 2619002.4 | L26: 34917.071 | M26: 9784.757 | O26: 1177970.6 | Q26: 1366903 | S26: 2544873.6 | T26: 298528.68 | U26: 126820.73 | V26: 108948.9 | Z26: =+A47 -> 44713 | AA26: =+C47/$S47 -> 0.064119454 | AB26: =+F47/$S47 -> 0.2748133 | AC26: =+I47/$S47 -> 0.31107906 | AD26: =+L47/$S47 -> 0.02439493 | AE26: =+T47/$S47 -> 0.036470194 | AF26: =+U47/$S47 -> 0.028414493 | AG26: =+V47/$S47 -> 0.031816541 | AH26: =+O47/$S47 -> 0.67440674 | AI26: =+Q47/$S47 -> 0.32559326
A27: 44105 | B27: =YEAR(A27)&"-B"&INT((MONTH(A27)-1)/2)+1 -> 2020-B5 | C27: 165495.69 | D27: 43292.723 | F27: 224115.65 | G27: 3401587.3 | I27: 745109.43 | J27: 2995216.4 | L27: 41243.431 | M27: 10703.934 | O27: 1175964.2 | Q27: 1468989.3 | S27: 2644953.5 | T27: 378452.1 | U27: 101781.69 | V27: 101595.86 | Z27: =+A48 -> 44743 | AA27: =+C48/$S48 -> 0.064112858 | AB27: =+F48/$S48 -> 0.30601115 | AC27: =+I48/$S48 -> 0.31109641 | AD27: =+L48/$S48 -> 0.01364481 | AE27: =+T48/$S48 -> 0.052919924 | AF27: =+U48/$S48 -> 0.036543919 | AG27: =+V48/$S48 -> 0.024818305 | AH27: =+O48/$S48 -> 0.69486523 | AI27: =+Q48/$S48 -> 0.30513477
A28: 44136 | B28: =YEAR(A28)&"-B"&INT((MONTH(A28)-1)/2)+1 -> 2020-B6 | C28: 220942.57 | D28: 58718.699 | F28: 151059.81 | G28: 2020873.7 | I28: 720846.39 | J28: 2748713 | L28: 43913.219 | M28: 11264.112 | O28: 1136762 | Q28: 1386609.9 | S28: 2523371.9 | T28: 298377.68 | U28: 114105.92 | V28: 125965.22 | Z28: =+A49 -> 44774 | AA28: =+C49/$S49 -> 0.070266176 | AB28: =+F49/$S49 -> 0.16163627 | AC28: =+I49/$S49 -> 0.34531308 | AD28: =+L49/$S49 -> 0.017905423 | AE28: =+T49/$S49 -> 0.060930026 | AF28: =+U49/$S49 -> 0.04559179 | AG28: =+V49/$S49 -> 0.032408283 | AH28: =+O49/$S49 -> 0.59512095 | AI28: =+Q49/$S49 -> 0.40487905
A29: 44166 | B29: =YEAR(A29)&"-B"&INT((MONTH(A29)-1)/2)+1 -> 2020-B6 | C29: 307008.77 | D29: 83046.941 | F29: 283337.63 | G29: 4721207.1 | I29: 796579.82 | J29: 2553529 | L29: 51144.959 | M29: 12834.291 | O29: 1438071.2 | Q29: 1590766 | S29: 3028837.2 | T29: 331767.39 | U29: 147538.74 | V29: 106377.55 | Z29: =+A50 -> 44805 | AA29: =+C50/$S50 -> 0.067792417 | AB29: =+F50/$S50 -> 0.26075364 | AC29: =+I50/$S50 -> 0.28131338 | AD29: =+L50/$S50 -> 0.016999709 | AE29: =+T50/$S50 -> 0.052702989 | AF29: =+U50/$S50 -> 0.033580726 | AG29: =+V50/$S50 -> 0.026249205 | AH29: =+O50/$S50 -> 0.62685914 | AI29: =+Q50/$S50 -> 0.37314086
A30: 44197 | B30: =YEAR(A30)&"-B"&INT((MONTH(A30)-1)/2)+1 -> 2021-B1 | C30: 247990.07 | D30: 66104.927 | E30: 0 | F30: 251118.41 | G30: 3876853.4 | H30: 0 | I30: 930474.84 | J30: 2715960.9 | K30: 0 | L30: 33477.898 | M30: 8223.853 | O30: 1463061.2 | Q30: 1147875.2 | S30: 2610936.4 | T30: 191099.61 | U30: 130770.46 | V30: 130252.4 | Z30: =+A51 -> 44835 | AA30: =+C51/$S51 -> 0.07405845 | AB30: =+F51/$S51 -> 0.23210719 | AC30: =+I51/$S51 -> 0.28504808 | AD30: =+L51/$S51 -> 0.011255385 | AE30: =+T51/$S51 -> 0.068839802 | AF30: =+U51/$S51 -> 0.034232462 | AG30: =+V51/$S51 -> 0.034186941 | AH30: =+O51/$S51 -> 0.60246911 | AI30: =+Q51/$S51 -> 0.39753089
A31: 44228 | B31: =YEAR(A31)&"-B"&INT((MONTH(A31)-1)/2)+1 -> 2021-B1 | C31: 259822.51 | D31: 66701.667 | E31: 0 | F31: 444899.13 | G31: 7382962.7 | H31: 0 | I31: 807209.24 | J31: 2037807.2 | K31: 0 | L31: 28639.061 | M31: 6491.448 | O31: 1540569.9 | Q31: 1398424.2 | S31: 2938994.1 | T31: 261144.81 | U31: 159060.52 | V31: 154414.6 | Z31: =+A52 -> 44866 | AA31: =+C52/$S52 -> 0.061637437 | AB31: =+F52/$S52 -> 0.23774776 | AC31: =+I52/$S52 -> 0.31868743 | AD31: =+L52/$S52 -> 0.010927537 | AE31: =+T52/$S52 -> 0.056737092 | AF31: =+U52/$S52 -> 0.027937436 | AG31: =+V52/$S52 -> 0.03284531 | AH31: =+O52/$S52 -> 0.62900016 | AI31: =+Q52/$S52 -> 0.37099984
A32: 44256 | B32: =YEAR(A32)&"-B"&INT((MONTH(A32)-1)/2)+1 -> 2021-B2 | C32: 266853.05 | D32: 66732.483 | E32: 0 | F32: 264804.06 | G32: 3354949.6 | H32: 0 | I32: 1134622 | J32: 2840951.9 | K32: 0 | L32: 29687.034 | M32: 5688.474 | O32: 1695966.1 | Q32: 1687588 | S32: 3383554.1 | T32: 279537 | U32: 150113.3 | V32: 204659.83 | Z32: =+A53 -> 44896 | AA32: =+C53/$S53 -> 0.072531762 | AB32: =+F53/$S53 -> 0.24370573 | AC32: =+I53/$S53 -> 0.2844019 | AD32: =+L53/$S53 -> 0.014295578 | AE32: =+T53/$S53 -> 0.069728316 | AF32: =+U53/$S53 -> 0.029271124 | AG32: =+V53/$S53 -> 0.02854164 | AH32: =+O53/$S53 -> 0.61493497 | AI32: =+Q53/$S53 -> 0.38506503
A33: 44287 | B33: =YEAR(A33)&"-B"&INT((MONTH(A33)-1)/2)+1 -> 2021-B2 | C33: 234504.43 | D33: 59044.707 | E33: 0 | F33: 340956.49 | G33: 4205319.7 | H33: 0 | I33: 862300.51 | J33: 2199304.5 | K33: 0 | L33: 31394.037 | M33: 6479.565 | O33: 1469155.5 | Q33: 1507216.9 | S33: 2976372.3 | T33: 272004.22 | U33: 167456.38 | V33: 147307.18 | Z33: =+A54 -> 44927 | AA33: =+C54/$S54 -> 0.064649608 | AB33: =+F54/$S54 -> 0.24368239 | AC33: =+I54/$S54 -> 0.28466341 | AD33: =+L54/$S54 -> 0.026902869 | AE33: =+T54/$S54 -> 0.069150847 | AF33: =+U54/$S54 -> 0.029024499 | AG33: =+V54/$S54 -> 0.042619024 | AH33: =+O54/$S54 -> 0.61989828 | AI33: =+Q54/$S54 -> 0.38010172
A34: 44317 | B34: =YEAR(A34)&"-B"&INT((MONTH(A34)-1)/2)+1 -> 2021-B3 | C34: 116711.3 | D34: 28206.59 | E34: 0 | F34: 335614.44 | G34: 4803961.8 | H34: 0 | I34: 1214108.7 | J34: 2846524.1 | K34: 0 | L34: 25353.605 | M34: 5740.247 | O34: 1691788.1 | Q34: 1405125.2 | S34: 3096913.3 | T34: 302196.72 | U34: 140940.67 | V34: 217431.35 | Z34: =+A55 -> 44958 | AA34: =+C55/$S55 -> 0.059005495 | AB34: =+F55/$S55 -> 0.23285939 | AC34: =+I55/$S55 -> 0.30686179 | AD34: =+L55/$S55 -> 0.009958029 | AE34: =+T55/$S55 -> 0.063682805 | AF34: =+U55/$S55 -> 0.028302782 | AG34: =+V55/$S55 -> 0.053185324 | AH34: =+O55/$S55 -> 0.6086847 | AI34: =+Q55/$S55 -> 0.3913153
A35: 44348 | B35: =YEAR(A35)&"-B"&INT((MONTH(A35)-1)/2)+1 -> 2021-B3 | C35: 107484.51 | D35: 25681.686 | E35: 0 | F35: 416226.57 | G35: 5379085.2 | H35: 0 | I35: 1142476.5 | J35: 2558335.1 | K35: 0 | L35: 38965.445 | M35: 8990.31 | O35: 1705153 | Q35: 1477062.7 | S35: 3182215.7 | T35: 286289.56 | U35: 165155.94 | V35: 125897.16 | Z35: =+A56 -> 44986 | AA35: =+C56/$S56 -> 0.062540722 | AB35: =+F56/$S56 -> 0.21462801 | AC35: =+I56/$S56 -> 0.26947941 | AD35: =+L56/$S56 -> 0.014010588 | AE35: =+T56/$S56 -> 0.071021459 | AF35: =+U56/$S56 -> 0.031947222 | AG35: =+V56/$S56 -> 0.048283264 | AH35: =+O56/$S56 -> 0.56065873 | AI35: =+Q56/$S56 -> 0.43934127 | AM35: Piedras preciosas casi al nivel del petroleo
A36: 44378 | B36: =YEAR(A36)&"-B"&INT((MONTH(A36)-1)/2)+1 -> 2021-B4 | C36: 299415.35 | D36: 68911.922 | E36: 0 | F36: 417620.64 | G36: 4925174.1 | H36: 0 | I36: 998030.69 | J36: 2239338.5 | K36: 0 | L36: 43353.267 | M36: 9494.005 | O36: 1758420 | Q36: 1685738 | S36: 3444157.9 | T36: 313275.83 | U36: 175121.41 | V36: 106769.88 | Z36: =+A57 -> 45017 | AA36: =+C57/$S57 -> 0.054415579 | AB36: =+F57/$S57 -> 0.14548117 | AC36: =+I57/$S57 -> 0.3447564 | AD36: =+L57/$S57 -> 0.012758624 | AE36: =+T57/$S57 -> 0.069775075 | AF36: =+U57/$S57 -> 0.031016879 | AG36: =+V57/$S57 -> 0.039247508 | AH36: =+O57/$S57 -> 0.55741178 | AI36: =+Q57/$S57 -> 0.44258822 | AM36: subida de no tradicionales por sectores que no generan un valor añadido
A37: 44409 | B37: =YEAR(A37)&"-B"&INT((MONTH(A37)-1)/2)+1 -> 2021-B4 | C37: 315159.23 | D37: 68786.497 | E37: 0 | F37: 482240.66 | G37: 4809134.9 | H37: 0 | I37: 1028790.5 | J37: 2467481.3 | K37: 0 | L37: 42436.164 | M37: 8784.103 | O37: 1868626.6 | Q37: 1596516.3 | S37: 3465142.9 | T37: 225795.94 | U37: 176633.24 | V37: 114586.3 | Z37: =+A58 -> 45047 | AA37: =+C58/$S58 -> 0.053792675 | AB37: =+F58/$S58 -> 0.20341651 | AC37: =+I58/$S58 -> 0.26498506 | AD37: =+L58/$S58 -> 0.017812098 | AE37: =+T58/$S58 -> 0.077775257 | AF37: =+U58/$S58 -> 0.028853434 | AG37: =+V58/$S58 -> 0.050040071 | AH37: =+O58/$S58 -> 0.54000634 | AI37: =+Q58/$S58 -> 0.45999366
A38: 44440 | B38: =YEAR(A38)&"-B"&INT((MONTH(A38)-1)/2)+1 -> 2021-B5 | C38: 256436.67 | D38: 52881.292 | F38: 579142.72 | G38: 4952083.2 | I38: 1274603.2 | J38: 2703221.9 | L38: 109768.61 | M38: 21845.222 | O38: 2219951.2 | Q38: 1572284.3 | S38: 3792235.5 | T38: 287659.16 | U38: 160172.68 | V38: 97506.452 | Z38: =+A59 -> 45078 | AA38: =+C59/$S59 -> 0.052686417 | AB38: =+F59/$S59 -> 0.19331936 | AC38: =+I59/$S59 -> 0.29549783 | AD38: =+L59/$S59 -> 0.012399494 | AE38: =+T59/$S59 -> 0.067224173 | AF38: =+U59/$S59 -> 0.032039645 | AG38: =+V59/$S59 -> 0.04360377 | AH38: =+O59/$S59 -> 0.55390311 | AI38: =+Q59/$S59 -> 0.44609689
A39: 44470 | B39: =YEAR(A39)&"-B"&INT((MONTH(A39)-1)/2)+1 -> 2021-B5 | C39: 318369.34 | D39: 61772.156 | F39: 594388.33 | G39: 5079863.8 | I39: 1292226.5 | J39: 2587111.5 | L39: 3524.8075 | M39: 679.521 | O39: 2208509 | Q39: 1590602.3 | S39: 3799111.3 | T39: 242301.26 | U39: 194209.42 | V39: 149379.36 | Z39: =+A60 -> 45108 | AA39: =+C60/$S60 -> 0.051892547 | AB39: =+F60/$S60 -> 0.162962 | AC39: =+I60/$S60 -> 0.34319459 | AD39: =+L60/$S60 -> 0.012544464 | AE39: =+T60/$S60 -> 0.079791909 | AF39: =+U60/$S60 -> 0.029200638 | AG39: =+V60/$S60 -> 0.05199301 | AH39: =+O60/$S60 -> 0.57059361 | AI39: =+Q60/$S60 -> 0.42940639
A40: 44501 | B40: =YEAR(A40)&"-B"&INT((MONTH(A40)-1)/2)+1 -> 2021-B6 | C40: 305963.74 | D40: 56801.716 | F40: 634726.71 | G40: 4349458.3 | I40: 1423127 | J40: 2828686.3 | L40: 74479.115 | M40: 13487.466 | O40: 2438296.5 | Q40: 1717508.1 | S40: 4155804.7 | T40: 307040.2 | U40: 174438.7 | V40: 143428.16 | Z40: =+A61 -> 45139 | AA40: =+C61/$S61 -> 0.054394503 | AB40: =+F61/$S61 -> 0.12262694 | AC40: =+I61/$S61 -> 0.36437351 | AD40: =+L61/$S61 -> 0.016564859 | AE40: =+T61/$S61 -> 0.073041486 | AF40: =+U61/$S61 -> 0.03289138 | AG40: =+V61/$S61 -> 0.033528022 | AH40: =+O61/$S61 -> 0.55795981 | AI40: =+Q61/$S61 -> 0.44204019
A41: 44531 | B41: =YEAR(A41)&"-B"&INT((MONTH(A41)-1)/2)+1 -> 2021-B6 | C41: 363128.04 | D41: 63447.673 | F41: 890519.96 | G41: 6513946.4 | I41: 1406440.9 | J41: 3018451.9 | L41: 67368.556 | M41: 12633.223 | O41: 2727457.5 | Q41: 1817093.4 | S41: 4544550.9 | T41: 377190.32 | U41: 189271.43 | V41: 164464.75 | Z41: =+A62 -> 45170 | AA41: =+C62/$S62 -> 0.053244791 | AB41: =+F62/$S62 -> 0.15783051 | AC41: =+I62/$S62 -> 0.36351232 | AD41: =+L62/$S62 -> 0.0052088309 | AE41: =+T62/$S62 -> 0.078605912 | AF41: =+U62/$S62 -> 0.031203637 | AG41: =+V62/$S62 -> 0.03334116 | AH41: =+O62/$S62 -> 0.57979645 | AI41: =+Q62/$S62 -> 0.42020355
A42: 44562 | B42: =YEAR(A42)&"-B"&INT((MONTH(A42)-1)/2)+1 -> 2022-B1 | C42: 320963.34 | D42: 54138.646 | F42: 775831.33 | G42: 4769840.6 | I42: 1268496.1 | J42: 2435818 | L42: 58741.493 | M42: 10570.164 | O42: 2424032.3 | Q42: 1377576.9 | S42: 3801609.2 | T42: 190348.59 | U42: 166726.06 | V42: 141635.11 | Z42: =+A63 -> 45200 | AA42: =+C63/$S63 -> 0.042715742 | AB42: =+F63/$S63 -> 0.14864521 | AC42: =+I63/$S63 -> 0.37153298 | AD42: =+L63/$S63 -> 0.0085242654 | AE42: =+T63/$S63 -> 0.066182503 | AF42: =+U63/$S63 -> 0.037312063 | AG42: =+V63/$S63 -> 0.034672639 | AH42: =+O63/$S63 -> 0.5714182 | AI42: =+Q63/$S63 -> 0.4285818
A43: 44593 | B43: =YEAR(A43)&"-B"&INT((MONTH(A43)-1)/2)+1 -> 2022-B1 | C43: 370330.65 | D43: 59507.698 | F43: 564570.42 | G43: 4528719.3 | I43: 1427538.2 | J43: 2427773.3 | L43: 59275.191 | M43: 10672.488 | O43: 2421714.4 | Q43: 1787483.4 | S43: 4209197.8 | T43: 268881.46 | U43: 175293.44 | V43: 259746.61 | Z43: =+A64 -> 45231 | AA43: =+C64/$S64 -> 0.057168713 | AB43: =+F64/$S64 -> 0.19571914 | AC43: =+I64/$S64 -> 0.28936089 | AD43: =+L64/$S64 -> 0.01101406 | AE43: =+T64/$S64 -> 0.081767381 | AF43: =+U64/$S64 -> 0.029839114 | AG43: =+V64/$S64 -> 0.040533098 | AH43: =+O64/$S64 -> 0.5532628 | AI43: =+Q64/$S64 -> 0.4467372
A44: 44621 | B44: =YEAR(A44)&"-B"&INT((MONTH(A44)-1)/2)+1 -> 2022-B2 | C44: 399119.08 | D44: 62068.914 | F44: 619868.65 | G44: 3969534.8 | I44: 1832280.8 | J44: 2665389.9 | L44: 60624.87 | M44: 10464.452 | O44: 2911893.4 | Q44: 1868316.3 | S44: 4780209.7 | T44: 251884.18 | U44: 200651.77 | V44: 223653.38 | Z44: =+A65 -> 45261 | AA44: =+C65/$S65 -> 0.06611913 | AB44: =+F65/$S65 -> 0.1828132 | AC44: =+I65/$S65 -> 0.3286307 | AD44: =+L65/$S65 -> 0.0075399196 | AE44: =+T65/$S65 -> 0.074206764 | AF44: =+U65/$S65 -> 0.032450868 | AG44: =+V65/$S65 -> 0.037319266 | AH44: =+O65/$S65 -> 0.58510294 | AI44: =+Q65/$S65 -> 0.41489706
A45: 44652 | B45: =YEAR(A45)&"-B"&INT((MONTH(A45)-1)/2)+1 -> 2022-B2 | C45: 315190.75 | D45: 48519.221 | F45: 1319487.4 | G45: 7556021.6 | I45: 1952119.9 | J45: 2939730.7 | L45: 111807.33 | M45: 17404.661 | O45: 3698605.3 | Q45: 1761926 | S45: 5460531.3 | T45: 255165.98 | U45: 144260.89 | V45: 188739.86 | Z45: =+A66 -> 45292 | AA45: =+C66/$S66 -> 0.06125042 | AB45: =+F66/$S66 -> 0.17866894 | AC45: =+I66/$S66 -> 0.29293364 | AD45: =+L66/$S66 -> 0.01091573 | AE45: =+T66/$S66 -> 0.077063967 | AF45: =+U66/$S66 -> 0.033432734 | AG45: =+V66/$S66 -> 0.046463789 | AH45: =+O66/$S66 -> 0.54376873 | AI45: =+Q66/$S66 -> 0.45623127
A46: 44682 | B46: =YEAR(A46)&"-B"&INT((MONTH(A46)-1)/2)+1 -> 2022-B3 | C46: 262815.98 | D46: 40787.978 | F46: 539326.6 | G46: 2774226.4 | I46: 1858822.9 | J46: 2659079.4 | L46: 79731.611 | M46: 10030.671 | O46: 2740697.1 | Q46: 1921823.5 | S46: 4662520.5 | T46: 275799.49 | U46: 172291.07 | V46: 253341.51 | Z46: =+A67 -> 45323 | AA46: =+C67/$S67 -> 0.064761988 | AB46: =+F67/$S67 -> 0.16597391 | AC46: =+I67/$S67 -> 0.29353447 | AD46: =+L67/$S67 -> 0.0082658413 | AE46: =+T67/$S67 -> 0.065180583 | AF46: =+U67/$S67 -> 0.035177087 | AG46: =+V67/$S67 -> 0.066925487 | AH46: =+O67/$S67 -> 0.53253622 | AI46: =+Q67/$S67 -> 0.46746378
A47: 44713 | B47: =YEAR(A47)&"-B"&INT((MONTH(A47)-1)/2)+1 -> 2022-B3 | C47: 352504.17 | D47: 54566.665 | F47: 1510818.1 | G47: 6256375.3 | I47: 1710193.4 | J47: 2345689 | L47: 134113.97 | M47: 15247.25 | O47: 3707629.6 | Q47: 1789986.9 | S47: 5497616.5 | T47: 200499.14 | U47: 156211.98 | V47: 174915.14 | Z47: =+A68 -> 45352 | AA47: =+C68/$S68 -> 0.057993452 | AB47: =+F68/$S68 -> 0.13366702 | AC47: =+I68/$S68 -> 0.35185109 | AD47: =+L68/$S68 -> 0.0075989224 | AE47: =+T68/$S68 -> 0.062745604 | AF47: =+U68/$S68 -> 0.030831422 | AG47: =+V68/$S68 -> 0.057819395 | AH47: =+O68/$S68 -> 0.55111048 | AI47: =+Q68/$S68 -> 0.44888952
A48: 44743 | B48: =YEAR(A48)&"-B"&INT((MONTH(A48)-1)/2)+1 -> 2022-B4 | C48: 379143.04 | D48: 58466.577 | F48: 1809652.6 | G48: 7163179.3 | I48: 1839725.2 | J48: 2685452.7 | L48: 80691.063 | M48: 9396.834 | O48: 4109211.8 | Q48: 1804469.9 | S48: 5913681.8 | T48: 312951.59 | U48: 216109.11 | V48: 146767.56 | Z48: =+A69 -> 45383 | AA48: =+C69/$S69 -> 0.056437721 | AB48: =+F69/$S69 -> 0.14645813 | AC48: =+I69/$S69 -> 0.31070972 | AD48: =+L69/$S69 -> 0.012272763 | AE48: =+T69/$S69 -> 0.088587953 | AF48: =+U69/$S69 -> 0.035305243 | AG48: =+V69/$S69 -> 0.040851926 | AH48: =+O69/$S69 -> 0.52587833 | AI48: =+Q69/$S69 -> 0.47412167
A49: 44774 | B49: =YEAR(A49)&"-B"&INT((MONTH(A49)-1)/2)+1 -> 2022-B4 | C49: 308379.74 | D49: 47186.849 | F49: 709379.03 | G49: 3460752.6 | I49: 1515488.2 | J49: 2569955.2 | L49: 78582.185 | M49: 12551.745 | O49: 2611829.1 | Q49: 1776907.5 | S49: 4388736.6 | T49: 267405.84 | U49: 200090.36 | V49: 142231.42 | Z49: =+A70 -> 45413 | AA49: =+C70/$S70 -> 0.056649346 | AB49: =+F70/$S70 -> 0.14343027 | AC49: =+I70/$S70 -> 0.31802525 | AD49: =+L70/$S70 -> 0.015483421 | AE49: =+T70/$S70 -> 0.078634167 | AF49: =+U70/$S70 -> 0.031279935 | AG49: =+V70/$S70 -> 0.057840847 | AH49: =+O70/$S70 -> 0.53358828 | AI49: =+Q70/$S70 -> 0.46641172
... A58: 45047 | B58: =YEAR(A58)&"-B"&INT((MONTH(A58)-1)/2)+1 -> 2023-B3 | C58: 241952.05 | D58: 45756.106 | F58: 914939.48 | G58: 5665968.8 | I58: 1191866.3 | J58: 2765528.1 | L58: 80116.365 | M58: 17002.984 | O58: 2428874.2 | Q58: 2068988.2 | S58: 4497862.4 | T58: 349822.41 | U58: 129778.78 | V58: 225073.36 | Z58: =+A79 -> 45689 | AA58: =+C79/$S79 -> 0.11157952 | AB58: =+F79/$S79 -> 0.12334912 | AC58: =+I79/$S79 -> 0.22874 | AD58: =+L79/$S79 -> 0.0080281274 | AE58: =+T79/$S79 -> 0.09077427 | AF58: =+U79/$S79 -> 0.034577175 | AG58: =+V79/$S79 -> 0.062275176 | AH58: =+O79/$S79 -> 0.47169677 | AI58: =+Q79/$S79 -> 0.52830323
A59: 45078 | B59: =YEAR(A59)&"-B"&INT((MONTH(A59)-1)/2)+1 -> 2023-B3 | C59: 211874.17 | D59: 39997.096 | E59: 0 | F59: 777418.21 | G59: 5178976 | H59: 0 | I59: 1188320.7 | J59: 2685259.3 | K59: 0 | L59: 49863.562 | M59: 11110.86 | O59: 2227476.6 | Q59: 1793942.6 | S59: 4021419.2 | T59: 270336.58 | U59: 128844.84 | V59: 175349.04 | Z59: =+A80 -> 45717 | AA59: =+C80/$S80 -> 0.12112037 | AB59: =+F80/$S80 -> 0.052669576 | AC59: =+I80/$S80 -> 0.33178361 | AD59: =+L80/$S80 -> 0.0094455072 | AE59: =+T80/$S80 -> 0.081636261 | AF59: =+U80/$S80 -> 0.035700282 | AG59: =+V80/$S80 -> 0.06275998 | AH59: =+O80/$S80 -> 0.51501907 | AI59: =+Q80/$S80 -> 0.48498093
A60: 45108 | B60: =YEAR(A60)&"-B"&INT((MONTH(A60)-1)/2)+1 -> 2023-B4 | C60: 216248.78 | D60: 43384.805 | E60: 0 | F60: 679102.04 | G60: 5001503.2 | H60: 0 | I60: 1430174.8 | J60: 2940684.8 | K60: 0 | L60: 52275.813 | M60: 14135.475 | O60: 2377801.4 | Q60: 1789440.2 | S60: 4167241.6 | T60: 332512.16 | U60: 121686.11 | V60: 216667.44 | Z60: =+A81 -> 45748 | AA60: =+C81/$S81 -> 0.1128304 | AB60: =+F81/$S81 -> 0.097992855 | AC60: =+I81/$S81 -> 0.22815201 | AD60: =+L81/$S81 -> 0.010650944 | AE60: =+T81/$S81 -> 0.089296209 | AF60: =+U81/$S81 -> 0.035592865 | AG60: =+V81/$S81 -> 0.048307165 | AH60: =+O81/$S81 -> 0.44962621 | AI60: =+Q81/$S81 -> 0.55037379
A61: 45139 | B61: =YEAR(A61)&"-B"&INT((MONTH(A61)-1)/2)+1 -> 2023-B4 | C61: 214526.21 | D61: 45608.239 | E61: 0 | F61: 483627.78 | G61: 3606715.3 | H61: 0 | I61: 1437050.9 | J61: 2711708.6 | K61: 0 | L61: 65330.065 | M61: 15022.437 | O61: 2200534.9 | Q61: 1743360.1 | S61: 3943895.1 | T61: 288067.96 | U61: 129720.15 | V61: 132231 | Z61: =+A82 -> 45778 | AA61: =+C82/$S82 -> 0.093157858 | AB61: =+F82/$S82 -> 0.12688868 | AC61: =+I82/$S82 -> 0.24401148 | AD61: =+L82/$S82 -> 0.0087125786 | AE61: =+T82/$S82 -> 0.084546011 | AF61: =+U82/$S82 -> 0.032812168 | AG61: =+V82/$S82 -> 0.055614183 | AH61: =+O82/$S82 -> 0.4727706 | AI61: =+Q82/$S82 -> 0.5272294
A62: 45170 | B62: =YEAR(A62)&"-B"&INT((MONTH(A62)-1)/2)+1 -> 2023-B5 | C62: 221909.33 | D62: 49422.84 | F62: 657793.24 | G62: 4944679 | I62: 1515017.2 | J62: 2664057.2 | L62: 21708.944 | M62: 10128.661 | O62: 2416428.7 | Q62: 1751290.3 | S62: 4167719 | T62: 327607.35 | U62: 130047.99 | V62: 138956.59 | Z62: =+A83 -> 45809 | AA62: =+C83/$S83 -> 0.10042085 | AB62: =+F83/$S83 -> 0.098868654 | AC62: =+I83/$S83 -> 0.27193223 | AD62: =+L83/$S83 -> 0.010246143 | AE62: =+T83/$S83 -> 0.081518418 | AF62: =+U83/$S83 -> 0.034914941 | AG62: =+V83/$S83 -> 0.068254313 | AH62: =+O83/$S83 -> 0.48146788 | AI62: =+Q83/$S83 -> 0.51853212
A63: 45200 | B63: =YEAR(A63)&"-B"&INT((MONTH(A63)-1)/2)+1 -> 2023-B5 | C63: 177362.12 | D63: 41099.211 | F63: 617197.05 | G63: 4871835.2 | I63: 1542660.2 | J63: 2784095.2 | L63: 35394.019 | M63: 10996.343 | O63: 2372613.4 | Q63: 1779535.4 | S63: 4152148.8 | T63: 274799.6 | U63: 154925.24 | V63: 143965.96 | Z63: =+A84 -> 45839 | AA63: =+C84/$S84 -> 0.10539534 | AB63: =+F84/$S84 -> 0.10837521 | AC63: =+I84/$S84 -> 0.24999031 | AD63: =+L84/$S84 -> 0.0090495267 | AE63: =+T84/$S84 -> 0.093604299 | AF63: =+U84/$S84 -> 0.036068134 | AG63: =+V84/$S84 -> 0.036714797 | AH63: =+O84/$S84 -> 0.47281039 | AI63: =+Q84/$S84 -> 0.52718961
A64: 45231 | B64: =YEAR(A64)&"-B"&INT((MONTH(A64)-1)/2)+1 -> 2023-B6 | C64: 239801.85 | D64: 56180.348 | E64: 0 | F64: 820970.23 | G64: 7347376.9 | H64: 0 | I64: 1213763.1 | J64: 2452133 | K64: 0 | L64: 46199.957 | M64: 13428.2 | O64: 2320735.2 | Q64: 1873899.2 | S64: 4194634.4 | T64: 342984.27 | U64: 125164.18 | V64: 170021.53 | Z64: =+A85 -> 45870 | AA64: =+C85/$S85 -> 0.13506021 | AB64: =+F85/$S85 -> 0.057976831 | AC64: =+I85/$S85 -> 0.2555051 | AD64: =+L85/$S85 -> 0.010593128 | AE64: =+T85/$S85 -> 0.083797953 | AF64: =+U85/$S85 -> 0.034699227 | AG64: =+V85/$S85 -> 0.039504257 | AH64: =+O85/$S85 -> 0.45913527 | AI64: =+Q85/$S85 -> 0.54086473
A65: 45261 | B65: =YEAR(A65)&"-B"&INT((MONTH(A65)-1)/2)+1 -> 2023-B6 | C65: 294080.23 | D65: 66749.628 | F65: 813104.27 | G65: 6472134.9 | I65: 1461661.6 | J65: 3081637.6 | L65: 33535.549 | M65: 10276.951 | O65: 2602381.6 | Q65: 1845351.3 | S65: 4447732.9 | T65: 330051.87 | U65: 144332.79 | V65: 165986.13 | Z65: =+A86 -> 45901 | AA65: =+C86/$S86 -> 0.10645539 | AB65: =+F86/$S86 -> 0.11587406 | AC65: =+I86/$S86 -> 0.22634566 | AD65: =+L86/$S86 -> 0.007808076 | AE65: =+T86/$S86 -> 0.096883234 | AF65: =+U86/$S86 -> 0.034602649 | AG65: =+V86/$S86 -> 0.034356552 | AH65: =+O86/$S86 -> 0.45648319 | AI65: =+Q86/$S86 -> 0.54351681
A66: 45292 | B66: =YEAR(A66)&"-B"&INT((MONTH(A66)-1)/2)+1 -> 2024-B1 | C66: 221795.37 | D66: 49446.221 | F66: 646982.38 | G66: 4933924.1 | I66: 1060749 | J66: 2308004.2 | L66: 39527.213 | M66: 13060.634 | O66: 1969054 | Q66: 1652070 | S66: 3621124 | T66: 279058.18 | U66: 121064.07 | V66: 168251.14 | Z66: =+A87 -> 45931 | AA66: =+C87/$S87 -> 0.12420862 | AB66: =+F87/$S87 -> 0.099957336 | AC66: =+I87/$S87 -> 0.22238327 | AD66: =+L87/$S87 -> 0.0096136331 | AE66: =+T87/$S87 -> 0.10992154 | AF66: =+U87/$S87 -> 0.039190744 | AG66: =+V87/$S87 -> 0.039683895 | AH66: =+O87/$S87 -> 0.45616286 | AI66: =+Q87/$S87 -> 0.54383714
A67: 45323 | B67: =YEAR(A67)&"-B"&INT((MONTH(A67)-1)/2)+1 -> 2024-B1 | C67: 246804.77 | D67: 54447.286 | F67: 632518.47 | G67: 5319248.8 | I67: 1118645.5 | J67: 2351012 | L67: 31500.717 | M67: 10379.901 | O67: 2029469.5 | Q67: 1781481.6 | S67: 3810951.1 | T67: 248400.01 | U67: 134058.16 | V67: 255049.76 | Z67: =+A88 -> 45962 | AA67: =+C88/$S88 -> 0.14383884 | AB67: =+F88/$S88 -> 0.097555872 | AC67: =+I88/$S88 -> 0.22957467 | AD67: =+L88/$S88 -> 0.01059374 | AE67: =+T88/$S88 -> 0.087030906 | AF67: =+U88/$S88 -> 0.034766958 | AG67: =+V88/$S88 -> 0.047980751 | AH67: =+O88/$S88 -> 0.48156312 | AI67: =+Q88/$S88 -> 0.51843688
A68: 45352 | B68: =YEAR(A68)&"-B"&INT((MONTH(A68)-1)/2)+1 -> 2024-B2 | C68: 224257.52 | D68: 49096.031 | F68: 516883.09 | G68: 4918777.7 | I68: 1360589 | J68: 2728115.5 | L68: 29384.619 | M68: 9390.427 | O68: 2131114.2 | Q68: 1735831.3 | S68: 3866945.5 | T68: 242633.83 | U68: 119223.43 | V68: 223584.45 | Z68: =+A89 -> 45992 | AA68: =+C89/$S89 -> 0.11143052 | AB68: =+F89/$S89 -> 0.1020913 | AC68: =+I89/$S89 -> 0.21243559 | AD68: =+L89/$S89 -> 0.0099067743 | AE68: =+T89/$S89 -> 0.16291305 | AF68: =+U89/$S89 -> 0.027576966 | AG68: =+V89/$S89 -> 0.040753433 | AH68: =+O89/$S89 -> 0.43586419 | AI68: =+Q89/$S89 -> 0.56413581
A69: 45383 | B69: =YEAR(A69)&"-B"&INT((MONTH(A69)-1)/2)+1 -> 2024-B2 | C69: 248824.09 | D69: 54005.883 | E69: 0 | F69: 645708.41 | G69: 6059298.6 | H69: 0 | I69: 1369865.1 | J69: 2639342.7 | K69: 0 | L69: 54108.477 | M69: 15604.977 | O69: 2318506.1 | Q69: 2090319.9 | S69: 4408826 | T69: 390568.87 | U69: 155654.68 | V69: 180109.03 | Z69: =+A90 -> 46023 | AA69: =+C90/$S90 -> 0.14498954 | AB69: =+F90/$S90 -> 0.085426901 | AC69: =+I90/$S90 -> 0.23025882 | AD69: =+L90/$S90 -> 0 | AE69: =+T90/$S90 -> 0.16588519 | AF69: =+U90/$S90 -> 0.034346103 | AG69: =+V90/$S90 -> 0.043686499 | AH69: =+O90/$S90 -> 0.46067526 | AI69: =+Q90/$S90 -> 0.53932474
A70: 45413 | B70: =YEAR(A70)&"-B"&INT((MONTH(A70)-1)/2)+1 -> 2024-B3 | C70: 252141.31 | D70: 51629.171 | F70: 638395.63 | G70: 6597462.1 | I70: 1415502.7 | J70: 2844178.4 | L70: 68915.361 | M70: 18664.101 | O70: 2374955 | Q70: 2075958 | S70: 4450913 | T70: 349993.84 | U70: 139224.27 | V70: 257444.58 | Z70: =+A91 -> 46054 | AA70: =+C91/$S91 -> 0.095871801 | AB70: =+F91/$S91 -> 0.089942773 | AC70: =+I91/$S91 -> 0.206493 | AD70: =+L91/$S91 -> 0 | AE70: =+T91/$S91 -> 0.19168267 | AF70: =+U91/$S91 -> 0.029822865 | AG70: =+V91/$S91 -> 0.051791018 | AH70: =+O91/$S91 -> 0.39230757 | AI70: =+Q91/$S91 -> 0.60769243
A71: 45444 | B71: =YEAR(A71)&"-B"&INT((MONTH(A71)-1)/2)+1 -> 2024-B3 | C71: 271496.25 | D71: 53184.341 | F71: 461418.57 | G71: 3760993.8 | I71: 1314212.2 | J71: 2580412.4 | L71: 29589.768 | M71: 7844.885 | O71: 2076716.8 | Q71: 1782613 | S71: 3859329.8 | T71: 282200.43 | U71: 144058.86 | V71: 204488.78
A72: 45474 | B72: =YEAR(A72)&"-B"&INT((MONTH(A72)-1)/2)+1 -> 2024-B4 | C72: 273945.66 | D72: 51912.839 | F72: 885885.19 | G72: 8532368.6 | I72: 1338548.3 | J72: 2633497.5 | L72: 46752.223 | M72: 10948.907 | O72: 2545131.4 | Q72: 2073153.8 | S72: 4618285.2 | T72: 416363.08 | U72: 154100.31 | V72: 216369.61
A73: 45505 | B73: =YEAR(A73)&"-B"&INT((MONTH(A73)-1)/2)+1 -> 2024-B4 | C73: 305206.81 | D73: 55868.404 | F73: 352621.24 | G73: 3046320.3 | I73: 1292741 | J73: 2730522.1 | L73: 61741.337 | M73: 14897.387 | O73: 2012310.4 | Q73: 1833400.2 | S73: 3845710.6 | T73: 331497.27 | U73: 152377.83 | V73: 152906.27
A74: 45536 | B74: =YEAR(A74)&"-B"&INT((MONTH(A74)-1)/2)+1 -> 2024-B5 | C74: 268919.78 | D74: 48180.566 | F74: 542754.9 | G74: 4898272.6 | I74: 1187789.2 | J74: 2782940.3 | L74: 52747.959 | M74: 14215.751 | O74: 2052211.9 | Q74: 2106480.1 | S74: 4158691.9 | T74: 449429.7 | U74: 127052.44 | V74: 173478.16
A75: 45566 | B75: =YEAR(A75)&"-B"&INT((MONTH(A75)-1)/2)+1 -> 2024-B5 | C75: 322942.53 | D75: 55298.208 | F75: 460772.6 | G75: 4448321.1 | I75: 1229592.7 | J75: 2788262.1 | L75: 38221.587 | M75: 10639.959 | O75: 2051529.4 | Q75: 2257606.8 | S75: 4309136.1 | T75: 515368.42 | U75: 171291.7 | V75: 176824.98
A76: 45597 | B76: =YEAR(A76)&"-B"&INT((MONTH(A76)-1)/2)+1 -> 2024-B6 | C76: 313019.8 | D76: 52613.609 | F76: 744904.77 | G76: 6752440.3 | I76: 1101872.7 | J76: 2556794.1 | L76: 33619.258 | M76: 10046.592 | O76: 2193416.6 | Q76: 1932683.1 | S76: 4126099.7 | T76: 421141.93 | U76: 117688.52 | V76: 174182.09
A77: 45627 | B77: =YEAR(A77)&"-B"&INT((MONTH(A77)-1)/2)+1 -> 2024-B6 | C77: 444055.02 | D77: 72279.162 | F77: 577784.62 | G77: 5353492.9 | I77: 1242552.2 | J77: 2814536.3 | L77: 56038.11 | M77: 15826.466 | O77: 2320430 | Q77: 2160078.4 | S77: 4480508.3 | T77: 398510.23 | U77: 141123.46 | V77: 203156.91
A78: 45658 | B78: =YEAR(A78)&"-B"&INT((MONTH(A78)-1)/2)+1 -> 2025-B1 | C78: 462540.64 | D78: 70084.62 | F78: 326872.74 | G78: 2713459.9 | I78: 1085979.1 | J78: 2418874.6 | L78: 34880.505 | M78: 10004.294 | O78: 1910273 | Q78: 1866448.4 | S78: 3776721.4 | T78: 341543.54 | U78: 133508.12 | V78: 192730.53
A79: 45689 | B79: =YEAR(A79)&"-B"&INT((MONTH(A79)-1)/2)+1 -> 2025-B1 | C79: 421801.26 | D79: 59295.766 | F79: 466293.61 | G79: 4197585.8 | I79: 864700.08 | J79: 1988492.6 | L79: 30348.529 | M79: 9234.283 | O79: 1783143.5 | Q79: 1997131.5 | S79: 3780274.9 | T79: 343151.7 | U79: 130711.23 | V79: 235417.29
A80: 45717 | B80: =YEAR(A80)&"-B"&INT((MONTH(A80)-1)/2)+1 -> 2025-B2 | C80: 532665.78 | D80: 70631.241 | F80: 231631.39 | G80: 2123917.9 | I80: 1459125.1 | J80: 3230094 | L80: 41539.655 | M80: 12108.609 | O80: 2264961.9 | Q80: 2132859.6 | S80: 4397821.5 | T80: 359021.71 | U80: 157003.47 | V80: 276007.19
A81: 45748 | B81: =YEAR(A81)&"-B"&INT((MONTH(A81)-1)/2)+1 -> 2025-B2 | C81: 464794.63 | D81: 57000.639 | F81: 403672.72 | G81: 3901759.1 | I81: 939851.63 | J81: 2272389.5 | L81: 43875.6 | M81: 13628.114 | O81: 1852194.6 | Q81: 2267215.1 | S81: 4119409.7 | T81: 367847.67 | U81: 146621.59 | V81: 198997
A82: 45778 | B82: =YEAR(A82)&"-B"&INT((MONTH(A82)-1)/2)+1 -> 2025-B3 | C82: 405926.39 | D82: 49042.159 | F82: 552905.2 | G82: 6088401.5 | I82: 1063256.5 | J82: 2631534.7 | L82: 37964.222 | M82: 10751.295 | O82: 2060052.3 | Q82: 2297351.3 | S82: 4357403.6 | T82: 368401.09 | U82: 142975.86 | V82: 242333.44
... A90: 46023 | B90: =YEAR(A90)&"-B"&INT((MONTH(A90)-1)/2)+1 -> 2026-B1 | C90: 617460.23 | D90: 70595.059 | F90: 363803.59 | G90: 4205203.1 | I90: 980592.57 | J90: 2603866.9 | L90: 0 | M90: 0 | O90: 1961856.4 | Q90: 2296797.3 | S90: 4258653.7 | T90: 706447.56 | U90: 146268.16 | V90: 186045.67
A91: 46054 | B91: =YEAR(A91)&"-B"&INT((MONTH(A91)-1)/2)+1 -> 2026-B1 | C91: 403772.83 | D91: 46920.775 | F91: 378802.19 | G91: 4143100.5 | I91: 869664.09 | J91: 2245143.3 | O91: 1652239.1 | Q91: 2559352.1 | S91: 4211591.2 | T91: 807289.03 | U91: 125601.72 | V91: 218122.6
C93: Exportaciones tradicionales | Q93: Exportaciones no tradicionales | S93: Total exportaciones
C94: Café | F94: Carbón | I94: Petróleo y sus derivados | L94: Ferroníquel | O94: Total Exportaciones Tradicionales
